[{"id":7401,"t":"Corona Vaccinee","s":"corona-vaccinee","img":"https://img.gamemonetize.com/76baba1277j31qqakymnnaop4p3tzn01/512x384.jpg","c":4,"p":0,"r":0.0,"f":false},{"id":7402,"t":"Car Parking Simulator Classic","s":"car-parking-simulator-classic","img":"https://img.gamemonetize.com/6de4fy2x4sdy6ev53bwcjtsmlxjb84l7/512x384.jpg","c":4,"p":0,"r":0.0,"f":false},{"id":7403,"t":"Color shoot 2D","s":"color-shoot-2d","img":"https://img.gamemonetize.com/cp14ic23whl0rsr5i2q8j9l11udadsej/512x384.jpg","c":3,"p":0,"r":0.0,"f":false},{"id":7404,"t":"pppp","s":"pppp","img":"https://img.gamemonetize.com/0v8ftlfjbzdsdz3kqzxdlxjv6jxa67u2/512x384.jpg","c":4,"p":0,"r":0.0,"f":false},{"id":7405,"t":"Newpong Multiplayer","s":"newpong-multiplayer","img":"https://img.gamemonetize.com/hi401gvrcbyuwenjetslywx52kukav1e/512x384.jpg","c":7,"p":0,"r":0.0,"f":false},{"id":7406,"t":"Draw Couple","s":"draw-couple","img":"https://img.gamemonetize.com/o0hyhrgjacp7xkncjjsdhzzja84rfy4q/512x384.jpg","c":7,"p":0,"r":0.0,"f":false},{"id":7407,"t":"Halloween Hidden Stars","s":"halloween-hidden-stars","img":"https://img.gamemonetize.com/y19e5cahp10dpv7nskhvsvjyzpklamql/512x384.jpg","c":5,"p":0,"r":0.0,"f":false},{"id":7408,"t":"AmongusCraft","s":"amonguscraft","img":"https://img.gamemonetize.com/ci88i0gadx9nrb3hc55acycaq59jwwo2/512x384.jpg","c":4,"p":0,"r":0.0,"f":false},{"id":7409,"t":"Half And Half Celebrity Style","s":"half-and-half-celebrity-style","img":"https://img.gamemonetize.com/ntrd5osnplteae7wum5ct25fw28xqfk8/512x384.jpg","c":4,"p":0,"r":0.0,"f":false},{"id":7410,"t":"Matchcandy.io","s":"matchcandy-io","img":"https://img.gamemonetize.com/tpxorkvnswl2wqz8rwvebyong1g93lkf/512x384.jpg","c":5,"p":0,"r":0.0,"f":false},{"id":7411,"t":"Rotating Pumpkin","s":"rotating-pumpkin","img":"https://img.gamemonetize.com/2my4rr1087vqd8bn0hdw3uvfxjlbcv20/512x384.jpg","c":5,"p":0,"r":0.0,"f":false},{"id":7412,"t":"Halloween Princess Holiday Castle","s":"halloween-princess-holiday-castle","img":"https://img.gamemonetize.com/o8m2n6xbmkpvuuot4bdl11n3bn7p5mpt/512x384.jpg","c":5,"p":0,"r":0.0,"f":false},{"id":7413,"t":"Traffic Run Nature","s":"traffic-run-nature","img":"https://img.gamemonetize.com/5p3aywc0sajsmpbll3zyplp2qhss9x2e/512x384.jpg","c":5,"p":0,"r":0.0,"f":false},{"id":7414,"t":"Moto X3M Halloween","s":"moto-x3m-halloween","img":"https://img.gamemonetize.com/hlmgvewlf6122xcmkubad7s5f0ajf1fo/512x384.jpg","c":8,"p":0,"r":0.0,"f":false},{"id":7415,"t":"Sweet Baby Beauty Salon","s":"sweet-baby-beauty-salon","img":"https://img.gamemonetize.com/vpc0xcmuziufvkbx7wakwnh5f5eqs5ox/512x384.jpg","c":8,"p":0,"r":0.0,"f":false},{"id":7416,"t":"Hero Sheep","s":"hero-sheep","img":"https://img.gamemonetize.com/dj3gwkohbugdirfrdmrcfwn5udovrfl4/512x384.jpg","c":5,"p":0,"r":0.0,"f":false},{"id":7417,"t":"Wugy HalloweenTower War","s":"wugy-halloweentower-war","img":"https://img.gamemonetize.com/x6j61nzrbs5q1ns2n04hv55gs54gwl3f/512x384.jpg","c":5,"p":0,"r":0.0,"f":false},{"id":7418,"t":"Rotating Flappy Jack","s":"rotating-flappy-jack","img":"https://img.gamemonetize.com/fg3sx0idoi8jyu07roq2e8pwl6k5gber/512x384.jpg","c":5,"p":0,"r":0.0,"f":false},{"id":7419,"t":"Railway Road","s":"railway-road","img":"https://img.gamemonetize.com/pl0t95gafs4eodab8ikgkzfvwjefx8nx/512x384.jpg","c":5,"p":0,"r":0.0,"f":false},{"id":7420,"t":"Halloween Sliding Puzzle","s":"halloween-sliding-puzzle","img":"https://img.gamemonetize.com/feic2cngoyzi6aik37g4fwz391vcxzrg/512x384.jpg","c":5,"p":0,"r":0.0,"f":false},{"id":7421,"t":"Jumpero","s":"jumpero","img":"https://img.gamemonetize.com/2fyyutvxptoyowpibfoq298ty80ln5ma/512x384.jpg","c":1,"p":0,"r":0.0,"f":false},{"id":7422,"t":"Private King","s":"private-king","img":"https://img.gamemonetize.com/4wpmmu5u06gtu5d6xcl8npixo1eto9kw/512x384.jpg","c":1,"p":0,"r":0.0,"f":false},{"id":7423,"t":"Spin To Win Lucky Wheels","s":"spin-to-win-lucky-wheels","img":"https://img.gamemonetize.com/73jlgslv12h901dckcm2tq3ll4ke12rv/512x384.jpg","c":5,"p":0,"r":0.0,"f":false},{"id":7424,"t":"Fruit Break","s":"fruit-break","img":"https://img.gamemonetize.com/rjsty4uzdcjhkrvf1j1cmonyzah4z3i6/512x384.jpg","c":1,"p":0,"r":0.0,"f":false},{"id":7425,"t":"City Taxi 3D Simulator Game","s":"city-taxi-3d-simulator-game","img":"https://img.gamemonetize.com/3c8mnqi5bgs7cy19od9nhqehyqgha29f/512x384.jpg","c":1,"p":0,"r":0.0,"f":false},{"id":7426,"t":"Drifty Master 3D Game","s":"drifty-master-3d-game","img":"https://img.gamemonetize.com/rc2ebrmw31k1o6rqgdowbuu3kydhflcr/512x384.jpg","c":1,"p":0,"r":0.0,"f":false},{"id":7427,"t":"Subway Santa Princess Runner","s":"subway-santa-princess-runner","img":"https://img.gamemonetize.com/t98ouu7fy5oze8qrc0bh9295xsweb0ju/512x384.jpg","c":1,"p":0,"r":0.0,"f":false},{"id":7428,"t":"Color Crazy Ball Blast - Fire","s":"color-crazy-ball-blast-fire","img":"https://img.gamemonetize.com/7mifxqbveugr3pzi2b6s3sah8gaomoyn/512x384.jpg","c":5,"p":0,"r":0.0,"f":false},{"id":7429,"t":"Gothic Fashion","s":"gothic-fashion","img":"https://img.gamemonetize.com/lumx34kzge71mx29x4tteezpfknj2w3w/512x384.jpg","c":5,"p":0,"r":0.0,"f":false},{"id":7430,"t":"Basketball Stars: Multijoueur","s":"basketball-stars-multijoueur","img":"https://img.gamemonetize.com/v0cib43fj98ng1nq43eaavgmbaycwkgd/512x384.jpg","c":5,"p":0,"r":0.0,"f":false},{"id":7431,"t":"Queen Elisa Dress up","s":"queen-elisa-dress-up","img":"https://img.gamemonetize.com/80wf1lxt8yezhcypdp4agbtjxgh0oj5a/512x384.jpg","c":5,"p":0,"r":0.0,"f":false},{"id":7432,"t":"Endless Runner in Jungle","s":"endless-runner-in-jungle","img":"https://img.gamemonetize.com/4rrpir5srj8kq0j8l084bae5407qwtck/512x384.jpg","c":5,"p":0,"r":0.0,"f":false},{"id":7433,"t":"Princess Amelia Dressup","s":"princess-amelia-dressup","img":"https://img.gamemonetize.com/y1l2eqwm7bzcw4qejlr211ikcjbja4v5/512x384.jpg","c":5,"p":0,"r":0.0,"f":false},{"id":7434,"t":"Funny Tennis","s":"funny-tennis","img":"https://img.gamemonetize.com/8xr8a6iqqrrov06tk5mvckqtnfmyj9jf/512x384.jpg","c":8,"p":0,"r":0.0,"f":false},{"id":7435,"t":"Micro Golf Ball Game","s":"micro-golf-ball-game","img":"https://img.gamemonetize.com/sn8fyt8hk1igz10s3e4a7iekwefza1z3/512x384.jpg","c":8,"p":0,"r":0.0,"f":false},{"id":7436,"t":"Private Zombie Town","s":"private-zombie-town","img":"https://img.gamemonetize.com/01u0h96annu7msjhhmg6bgubolsxxs3j/512x384.jpg","c":1,"p":0,"r":0.0,"f":false},{"id":7437,"t":"Doll House","s":"doll-house","img":"https://img.gamemonetize.com/7q78fz2yrgvanq7t55r7x07h4fmqrokw/512x384.jpg","c":1,"p":0,"r":0.0,"f":false},{"id":7438,"t":"Wild Runner 2d","s":"wild-runner-2d","img":"https://img.gamemonetize.com/qask6gogd72j81a5is1j0udt0mjoekqv/512x384.jpg","c":4,"p":0,"r":0.0,"f":false},{"id":7439,"t":"Wood Block Puzzle Game","s":"wood-block-puzzle-game","img":"https://img.gamemonetize.com/4lt5oekllrv5nh9y7vwl7ij3t7l3f54a/512x384.jpg","c":5,"p":0,"r":0.0,"f":false},{"id":7440,"t":"Drink Buffet","s":"drink-buffet","img":"https://img.gamemonetize.com/6f2gnbbw7eueoxtspiukc87evlocjxqa/512x384.jpg","c":5,"p":0,"r":0.0,"f":false},{"id":7441,"t":"Pizza Maker Master Chef","s":"pizza-maker-master-chef","img":"https://img.gamemonetize.com/40tyewcpk5zeruz59f6k72q0qbw6562i/512x384.jpg","c":5,"p":0,"r":0.0,"f":false},{"id":7442,"t":"Buddy Halloween Adventure","s":"buddy-halloween-adventure","img":"https://img.gamemonetize.com/keowf3vyj18zquumiruyha1r0qhnhwoz/512x384.jpg","c":2,"p":0,"r":0.0,"f":false},{"id":7443,"t":"Rescue Vanguard","s":"rescue-vanguard","img":"https://img.gamemonetize.com/kpikszokydbajwjsydxg89qvaoyrcze2/512x384.jpg","c":2,"p":0,"r":0.0,"f":false},{"id":7444,"t":"Monster Cars: Ultimate Simulator","s":"monster-cars-ultimate-simulator","img":"https://img.gamemonetize.com/z68g27jvpyxguo5c3hbqqq1c7c7i1zqr/512x384.jpg","c":2,"p":0,"r":0.0,"f":false},{"id":7445,"t":"Stick Warrior Hero Battle","s":"stick-warrior-hero-battle","img":"https://img.gamemonetize.com/bg00n551jqiaopwgoxl94cb7ump6p2lf/512x384.jpg","c":2,"p":0,"r":0.0,"f":false},{"id":7446,"t":"Halloween Pumpkin Weighin;","s":"halloween-pumpkin-weighin","img":"https://img.gamemonetize.com/ms02xq6y4vslk37if6cksaoabl5bxcfw/512x384.jpg","c":5,"p":0,"r":0.0,"f":false},{"id":7447,"t":"Baby Taylor Superhero Emergency","s":"baby-taylor-superhero-emergency","img":"https://img.gamemonetize.com/lf74gthwyrzu3ddyvsdthg6poldt1wqi/512x384.jpg","c":5,"p":0,"r":0.0,"f":false},{"id":7448,"t":"Giant Rush Online 3D","s":"giant-rush-online-3d","img":"https://img.gamemonetize.com/zvn8gv24yngpds84lkovxpjc923byhzh/512x384.jpg","c":5,"p":0,"r":0.0,"f":false},{"id":7449,"t":"Ropeman 3D Game","s":"ropeman-3d-game","img":"https://img.gamemonetize.com/pjhfkg0odnm39arxs8zgisd955gdtrzl/512x384.jpg","c":5,"p":0,"r":0.0,"f":false},{"id":7450,"t":"Tricks - 3D Bike Racing Game","s":"tricks-3d-bike-racing-game","img":"https://img.gamemonetize.com/yh87uvwzdbr639onndeha33etktdznaq/512x384.jpg","c":2,"p":0,"r":0.0,"f":false},{"id":7451,"t":"Combat Reloaded 2","s":"combat-reloaded-2","img":"https://img.gamemonetize.com/qngjqt5qffzj4bl0uitsfitqk9wpjyb6/512x384.jpg","c":2,"p":0,"r":0.0,"f":false},{"id":7452,"t":"Hello Kitty Jigsaw Puzzle","s":"hello-kitty-jigsaw-puzzle","img":"https://img.gamemonetize.com/2xi8r0udgmi6vglh5dclmpvp6zm3mxe4/512x384.jpg","c":5,"p":0,"r":0.0,"f":false},{"id":7453,"t":"Alien Blaster","s":"alien-blaster","img":"https://img.gamemonetize.com/ygbci4cw0r4ss1tz6wj3otfh5itffl8e/512x384.jpg","c":3,"p":0,"r":0.0,"f":false},{"id":7454,"t":"Merge Master: Monster Playtime","s":"merge-master-monster-playtime","img":"https://img.gamemonetize.com/3xrn4pbnalnl11jjuw8cq3lh711pba5p/512x384.jpg","c":5,"p":0,"r":0.0,"f":false},{"id":7455,"t":"Subway Surfers Word Blocks","s":"subway-surfers-word-blocks","img":"https://img.gamemonetize.com/v9b7fgjan4oqsokmc6qd5j9o7qcyvhfr/512x384.jpg","c":5,"p":0,"r":0.0,"f":false},{"id":7456,"t":"Happy Cat Puzzle","s":"happy-cat-puzzle","img":"https://img.gamemonetize.com/99cb4xetp66t0euqejqbcbhwq0kvsnjz/512x384.jpg","c":5,"p":0,"r":0.0,"f":false},{"id":7457,"t":"Super Jumper","s":"super-jumper","img":"https://img.gamemonetize.com/j9n2rh05znsylj7lrsan5llguf5y6s2d/512x384.jpg","c":5,"p":0,"r":0.0,"f":false},{"id":7458,"t":"Beach Escape 2","s":"beach-escape-2","img":"https://img.gamemonetize.com/fur3vrrtsppzgdlfoku0qtdwyr9kg80m/512x384.jpg","c":5,"p":0,"r":0.0,"f":false},{"id":7459,"t":"Pink House Escape 2","s":"pink-house-escape-2","img":"https://img.gamemonetize.com/45a3n00d4fljizvkrnrn6ni271rche8w/512x384.jpg","c":5,"p":0,"r":0.0,"f":false},{"id":7460,"t":"Little panda match3","s":"little-panda-match3","img":"https://img.gamemonetize.com/thc7fv817rbmjm3nl4oi90l02i6wmjr4/512x384.jpg","c":4,"p":0,"r":0.0,"f":false},{"id":7461,"t":"Build a Bridge!","s":"build-a-bridge","img":"https://img.gamemonetize.com/6nev1nlzs0kycd4w1myxl5ua8x40hy8a/512x384.jpg","c":4,"p":0,"r":0.0,"f":false},{"id":7462,"t":"Flappy Penguin","s":"flappy-penguin","img":"https://img.gamemonetize.com/nlru86yzgu0odvpqrc3c3rs2qc5ifp1i/512x384.jpg","c":4,"p":0,"r":0.0,"f":false},{"id":7463,"t":"Upit Adventure Game","s":"upit-adventure-game","img":"https://img.gamemonetize.com/5y32jifxj3sprb85al1lzq2ba7nh9mje/512x384.jpg","c":3,"p":0,"r":0.0,"f":false},{"id":7464,"t":"Platformer War Day","s":"platformer-war-day","img":"https://img.gamemonetize.com/sfw0jafnkkszm9e3hd9pwfp66x6bejyg/512x384.jpg","c":3,"p":0,"r":0.0,"f":false},{"id":7465,"t":"Multi Level 7 Car Parking Sim","s":"multi-level-7-car-parking-sim","img":"https://img.gamemonetize.com/h8kcx1vrpbgo18ny1puv64du30l1dive/512x384.jpg","c":3,"p":0,"r":0.0,"f":false},{"id":7466,"t":"Beach Girl Dressup","s":"beach-girl-dressup","img":"https://img.gamemonetize.com/y1gdhl1tvhbcuz5wkwlj79tgprykea25/512x384.jpg","c":3,"p":0,"r":0.0,"f":false},{"id":7467,"t":"Nanychan vs Ghosts","s":"nanychan-vs-ghosts","img":"https://img.gamemonetize.com/5s39hhhezmovp7lkzhk9sn9lfipg5try/512x384.jpg","c":4,"p":0,"r":0.0,"f":false},{"id":7468,"t":"Funny Epic Roll","s":"funny-epic-roll","img":"https://img.gamemonetize.com/d67a4eouolhf8dn5wf42afgn6glufucp/512x384.jpg","c":4,"p":0,"r":0.0,"f":false},{"id":7469,"t":"Cute Girl Dress Up","s":"cute-girl-dress-up","img":"https://img.gamemonetize.com/yv9gnrq9find7gh1o57mrxekm9l8ivm2/512x384.jpg","c":4,"p":0,"r":0.0,"f":false},{"id":7470,"t":"Amgel Easy Room Escape 67","s":"amgel-easy-room-escape-67","img":"https://img.gamemonetize.com/n37jew2njcxvyy7ljic06pzt1w3em454/512x384.jpg","c":5,"p":0,"r":0.0,"f":false},{"id":7471,"t":"Amgel Kids Room Escape 74","s":"amgel-kids-room-escape-74","img":"https://img.gamemonetize.com/eiat4btwu9uv8p0wz7igcsbje4ww72jw/512x384.jpg","c":5,"p":0,"r":0.0,"f":false},{"id":7472,"t":"Flappy Pumpkin","s":"flappy-pumpkin","img":"https://img.gamemonetize.com/5lsgas04qudmovmsbhyeutz4brmylsu6/512x384.jpg","c":5,"p":0,"r":0.0,"f":false},{"id":7473,"t":"Elastic Car 3D","s":"elastic-car-3d","img":"https://img.gamemonetize.com/kaart3m85trc6fnuv0zpsnrbayz1sjsj/512x384.jpg","c":5,"p":0,"r":0.0,"f":false},{"id":7474,"t":"Join Scroll Run","s":"join-scroll-run","img":"https://img.gamemonetize.com/s7evsulff64o59vqds6toepb7cgl0w43/512x384.jpg","c":5,"p":0,"r":0.0,"f":false},{"id":7475,"t":"Trains.io 3D Game","s":"trains-io-3d-game","img":"https://img.gamemonetize.com/x6xllus6rl5cmuuv5mvf5c1caskepgob/512x384.jpg","c":5,"p":0,"r":0.0,"f":false},{"id":7476,"t":"Monster School Parkour Challenge","s":"monster-school-parkour-challenge","img":"https://img.gamemonetize.com/5kkuj80x0pb7u3dkjb1cekpivhmdl72x/512x384.jpg","c":5,"p":0,"r":0.0,"f":false},{"id":7477,"t":"Pumpkin Jump","s":"pumpkin-jump","img":"https://img.gamemonetize.com/fy28bdk8ybr3cnmtgetui5snin4pfuy1/512x384.jpg","c":2,"p":0,"r":0.0,"f":false},{"id":7478,"t":"Sudoku Game","s":"sudoku-game","img":"https://img.gamemonetize.com/eq71s0yfpagfhakn0byg77f7vlfm0c8r/512x384.jpg","c":2,"p":0,"r":0.0,"f":false},{"id":7479,"t":"TikTok Dance","s":"tiktok-dance","img":"https://img.gamemonetize.com/48q918mja9at5dxd7k0aa7o262nco8tc/512x384.jpg","c":2,"p":0,"r":0.0,"f":false},{"id":7480,"t":"Torn Pics Jigsaw Halloween","s":"torn-pics-jigsaw-halloween","img":"https://img.gamemonetize.com/n54zv7hq5f49mlewjh4szruwc1fyb70h/512x384.jpg","c":5,"p":0,"r":0.0,"f":false},{"id":7481,"t":"Halloween Clown Dressup","s":"halloween-clown-dressup","img":"https://img.gamemonetize.com/5ea9kvrrb75vlx8mkmyw4rv6x75r67tw/512x384.jpg","c":5,"p":0,"r":0.0,"f":false},{"id":7482,"t":"Gun Sprint - Gun Run","s":"gun-sprint-gun-run","img":"https://img.gamemonetize.com/5b1l63kef3p979mvrunaoew9txkg90ba/512x384.jpg","c":5,"p":0,"r":0.0,"f":false},{"id":7483,"t":"Pro Obunga vs CreepEnder","s":"pro-obunga-vs-creepender","img":"https://img.gamemonetize.com/dvdc9d8skuvv54u1l0epxnc7dlg2kz4h/512x384.jpg","c":4,"p":0,"r":0.0,"f":false},{"id":7484,"t":"Brawl Poo","s":"brawl-poo","img":"https://img.gamemonetize.com/t4urhb413373pw4kfmamjvv5gsjcm9dx/512x384.jpg","c":4,"p":0,"r":0.0,"f":false},{"id":7485,"t":"Hackers vs impostors","s":"hackers-vs-impostors","img":"https://img.gamemonetize.com/keqeyo14h4xkbs6of4ga7ka7zprpeujw/512x384.jpg","c":4,"p":0,"r":0.0,"f":false},{"id":7486,"t":"Stickman Huggy Spooky Holiday","s":"stickman-huggy-spooky-holiday","img":"https://img.gamemonetize.com/isy8l1rme2azm1g2n2hirk8v3hf12s79/512x384.jpg","c":4,"p":0,"r":0.0,"f":false},{"id":7487,"t":"4p","s":"4p","img":"https://img.gamemonetize.com/rrxw2z3kme4kdv8vy3felzc4ee5vy4fw/512x384.jpg","c":4,"p":0,"r":0.0,"f":false},{"id":7488,"t":"Real Car Parking : Parking Master GTA","s":"real-car-parking-parking-master-gta","img":"https://img.gamemonetize.com/p8kgml4r227t5br91mnuke7t5gg0z1yl/512x384.jpg","c":4,"p":0,"r":0.0,"f":false},{"id":7489,"t":"Cairn","s":"cairn","img":"https://img.gamemonetize.com/egxeoxz7amqriilj20rmt2w60rsoa5y7/512x384.jpg","c":4,"p":0,"r":0.0,"f":false},{"id":7490,"t":"Tom and Jerry Dress Up","s":"tom-and-jerry-dress-up","img":"https://img.gamemonetize.com/kawl9xfklzmxwq9kh5qzhkz6yi27mu1q/512x384.jpg","c":4,"p":0,"r":0.0,"f":false},{"id":7491,"t":"Amgel Kids Room Escape 73","s":"amgel-kids-room-escape-73","img":"https://img.gamemonetize.com/8xuphw1ltn22hbkocnre6onduwgpb2il/512x384.jpg","c":5,"p":0,"r":0.0,"f":false},{"id":7492,"t":"Amgel Easy Room Escape 66","s":"amgel-easy-room-escape-66","img":"https://img.gamemonetize.com/rv94c2iojsn5mra4cbo762ee1ozjogyq/512x384.jpg","c":5,"p":0,"r":0.0,"f":false},{"id":7493,"t":"Floaty Astronaut","s":"floaty-astronaut","img":"https://img.gamemonetize.com/62ifkkxeesp0c3rhwkqammt1xx5e2jzh/512x384.jpg","c":5,"p":0,"r":0.0,"f":false},{"id":7494,"t":"Trolls Puzzle Jigsaw","s":"trolls-puzzle-jigsaw","img":"https://img.gamemonetize.com/0kf5f3lzyfi4j91nxx59kv63g10a3v8u/512x384.jpg","c":5,"p":0,"r":0.0,"f":false},{"id":7495,"t":"Nick Jr. Sunny Day Super Search","s":"nick-jr-sunny-day-super-search","img":"https://img.gamemonetize.com/ihwb5gm2dqoly82rgua7ebumg5c5wnoa/512x384.jpg","c":5,"p":0,"r":0.0,"f":false},{"id":7496,"t":"Pixel Dragon","s":"pixel-dragon","img":"https://img.gamemonetize.com/4n4kzpu9xs9wyitlaz0udid1kpyoyubp/512x384.jpg","c":4,"p":0,"r":0.0,"f":false},{"id":7497,"t":"slime water","s":"slime-water","img":"https://img.gamemonetize.com/89cri52g3rrm4yp8dt3w7llpdpnzz68y/512x384.jpg","c":4,"p":0,"r":0.0,"f":false},{"id":7498,"t":"Ricky Zoom - Family Pairs","s":"ricky-zoom-family-pairs","img":"https://img.gamemonetize.com/lmivffii0d77amzgvlvhodnj4ijbpssk/512x384.jpg","c":5,"p":0,"r":0.0,"f":false},{"id":7499,"t":"Drop The Numbers","s":"drop-the-numbers","img":"https://img.gamemonetize.com/vjpcx4wficow57kg5q0e5qeqrwsg3lri/512x384.jpg","c":5,"p":0,"r":0.0,"f":false},{"id":7500,"t":"PJ Masks Howling Havoc","s":"pj-masks-ndash-howling-havoc","img":"https://img.gamemonetize.com/hcyzy8gy9m9xrj2nd4xny9zy4bn2yumi/512x384.jpg","c":5,"p":0,"r":0.0,"f":false}]