[{"id":8201,"t":"Coconut Volley","s":"coconut-volley","img":"https://img.gamemonetize.com/k3gy1o04halnxs5nx1e3hlhnwpglv1n8/512x384.jpg","c":8,"p":0,"r":0.0,"f":false},{"id":8202,"t":"Huggy Wuggy Jigsaw","s":"huggy-wuggy-jigsaw","img":"https://img.gamemonetize.com/u9xb4seryy2ehcjm7fem5xwgt9wbp3r5/512x384.jpg","c":5,"p":0,"r":0.0,"f":false},{"id":8203,"t":"Asphalt Legend","s":"asphalt-legend","img":"https://img.gamemonetize.com/0ihjp7bxr2qaz2ug625lkp5v333nkwxj/512x384.jpg","c":2,"p":0,"r":0.0,"f":false},{"id":8204,"t":"Mini Kart Rush","s":"mini-kart-rush","img":"https://img.gamemonetize.com/gw68pb4cz9w1bva5x0u0kjalqviqhi0i/512x384.jpg","c":2,"p":0,"r":0.0,"f":false},{"id":8205,"t":"PGA6 Blocky Combat SWAT Apocalypse 2022","s":"pga6-blocky-combat-swat-apocalypse-2022","img":"https://img.gamemonetize.com/8dyilp6ibwcpmpdyzphwr97jn9jajr44/512x384.jpg","c":3,"p":0,"r":0.0,"f":false},{"id":8206,"t":"Bffs Fall Fashion Trends","s":"bffs-fall-fashion-trends","img":"https://img.gamemonetize.com/7c9krjcmkw7sjcuq02vocslg4u3eq38q/512x384.jpg","c":3,"p":0,"r":0.0,"f":false},{"id":8207,"t":"Epic Roll","s":"epic-roll","img":"https://img.gamemonetize.com/jt9mzmjfn2joep57mc925up2fwknj389/512x384.jpg","c":3,"p":0,"r":0.0,"f":false},{"id":8208,"t":"Mermaid chage princess","s":"mermaid-chage-princess","img":"https://img.gamemonetize.com/vr2n0tid5um71h729crxrasz75z4cu2f/512x384.jpg","c":3,"p":0,"r":0.0,"f":false},{"id":8209,"t":"Marble Lines","s":"marble-lines","img":"https://img.gamemonetize.com/mrt2jm7oqohl2tnk501c50vbkbi41f1s/512x384.jpg","c":5,"p":0,"r":0.0,"f":false},{"id":8210,"t":"Battlefield Elite 3D","s":"battlefield-elite-3d","img":"https://img.gamemonetize.com/9urd2sprcg2cvcvg0nrmmk2wcxozli2k/512x384.jpg","c":5,"p":0,"r":0.0,"f":false},{"id":8211,"t":"Samurai Flash 3D","s":"samurai-flash-3d","img":"https://img.gamemonetize.com/jpq431zlvg1ghurraejh5dizzb24e4rz/512x384.jpg","c":5,"p":0,"r":0.0,"f":false},{"id":8212,"t":"Speed Traffic - Lane Change Master","s":"speed-traffic-lane-change-master","img":"https://img.gamemonetize.com/yfe5joqh63ec6patliqoe02aplb8cbly/512x384.jpg","c":2,"p":0,"r":0.0,"f":false},{"id":8213,"t":"Mia Dentist Ice Cream","s":"mia-dentist-ice-cream","img":"https://img.gamemonetize.com/h3aga20b6j3s1djs4yz9yuede6oiz4w4/512x384.jpg","c":2,"p":0,"r":0.0,"f":false},{"id":8214,"t":"Zhu Zhu Pets Tube Racers","s":"zhu-zhu-pets-tube-racers","img":"https://img.gamemonetize.com/sesg8dwp3bub2r7diu34p1ej4d01os0l/512x384.jpg","c":2,"p":0,"r":0.0,"f":false},{"id":8215,"t":"A  amp;amp; B Kids","s":"a-b-kids","img":"https://img.gamemonetize.com/j45iesye5y60xli8ui5wt6dl13oggt1a/512x384.jpg","c":5,"p":0,"r":0.0,"f":false},{"id":8216,"t":"Truck And Police","s":"truck-and-police","img":"https://img.gamemonetize.com/v7rtb5f7ya32ovjg8g8p9l3ujn0p5nbf/512x384.jpg","c":4,"p":0,"r":0.0,"f":false},{"id":8217,"t":"P. Kings Memory Game","s":"p-kings-memory-game","img":"https://img.gamemonetize.com/s4whdhcrdi62fjygncztcbzunxdbq9zj/512x384.jpg","c":5,"p":0,"r":0.0,"f":false},{"id":8218,"t":"Chop Fruits Master","s":"chop-fruits-master","img":"https://img.gamemonetize.com/zzxva6j0b08b4rie2uw437338ym3crp3/512x384.jpg","c":5,"p":0,"r":0.0,"f":false},{"id":8219,"t":"The Queen Of Fashion: Fashion show dress Up Game","s":"the-queen-of-fashion-fashion-show-dress-up-game","img":"https://img.gamemonetize.com/ybf6bmzmtee1rxcfimnmexe6fohykq4o/512x384.jpg","c":5,"p":0,"r":0.0,"f":false},{"id":8220,"t":"Water The Tree","s":"water-the-tree","img":"https://img.gamemonetize.com/idd0krd5zz90z6k97380oxwyxq3521ne/512x384.jpg","c":5,"p":0,"r":0.0,"f":false},{"id":8221,"t":"Julia Food Truck","s":"julia-food-truck","img":"https://img.gamemonetize.com/l2rrflvwquea3hunpv12p5t0fji7h8a3/512x384.jpg","c":5,"p":0,"r":0.0,"f":false},{"id":8222,"t":"Endless Siege Online","s":"endless-siege-online","img":"https://img.gamemonetize.com/s63yrwe569lbg83asdx01ehpzsha4x3j/512x384.jpg","c":5,"p":0,"r":0.0,"f":false},{"id":8223,"t":"Friday Night Funkin Online","s":"friday-night-funkin-online","img":"https://img.gamemonetize.com/otsz45if9cwsklzm5slw1ficefz5yz0v/512x384.jpg","c":5,"p":0,"r":0.0,"f":false},{"id":8224,"t":"Happy Gliding Online","s":"happy-gliding-online","img":"https://img.gamemonetize.com/uscsjr849xqfq8zyi8xtoksbwh5y71ux/512x384.jpg","c":5,"p":0,"r":0.0,"f":false},{"id":8225,"t":"Reptolia 2","s":"reptolia-2","img":"https://img.gamemonetize.com/s57w9imz7rpeciaq0a2wbm84jjtrluul/512x384.jpg","c":4,"p":0,"r":0.0,"f":false},{"id":8226,"t":"Drone Destruction - Ben 10","s":"drone-destruction-ben-10","img":"https://img.gamemonetize.com/cu4afltwlltb845ph5uilwelsfuax9oy/512x384.jpg","c":3,"p":0,"r":0.0,"f":false},{"id":8227,"t":"Bullet Stop 3D","s":"bullet-stop-3d","img":"https://img.gamemonetize.com/ijfoh1kvn3na4oqyjdegb7wa4mc12y6j/512x384.jpg","c":3,"p":0,"r":0.0,"f":false},{"id":8228,"t":"Chromatic Seals","s":"chromatic-seals","img":"https://img.gamemonetize.com/83shyumzmyj7dy586zvt95qx6nng3iab/512x384.jpg","c":5,"p":0,"r":0.0,"f":false},{"id":8229,"t":"Candy Super Sugar","s":"candy-super-sugar","img":"https://img.gamemonetize.com/bzydfltvi56a8ko7arb00d6dm6gb75nx/512x384.jpg","c":5,"p":0,"r":0.0,"f":false},{"id":8230,"t":"space invaders.io","s":"space-invaders-io","img":"https://img.gamemonetize.com/073g0p6vxdyvna6edg2m85b3r8276ksc/512x384.jpg","c":3,"p":0,"r":0.0,"f":false},{"id":8231,"t":"Pixel mario","s":"pixel-mario","img":"https://img.gamemonetize.com/aywmfijeuzzdv7zz20kooiguza8a0ozy/512x384.jpg","c":3,"p":0,"r":0.0,"f":false},{"id":8232,"t":"Crash Landing","s":"crash-landing","img":"https://img.gamemonetize.com/59xrf2k4rg47qk7qeweo50uqo2jxdvmi/512x384.jpg","c":3,"p":0,"r":0.0,"f":false},{"id":8233,"t":"1vs1","s":"1vs1","img":"https://img.gamemonetize.com/6f9jsocvpkijsd9jqlksepihximo401e/512x384.jpg","c":3,"p":0,"r":0.0,"f":false},{"id":8234,"t":"Heros Fermier Mini Saga","s":"heros-fermier-mini-saga","img":"https://img.gamemonetize.com/aq3enj8yx2ffix5ki7mfdxzxt1i81fe1/512x384.jpg","c":5,"p":0,"r":0.0,"f":false},{"id":8235,"t":"Reptolia","s":"reptolia","img":"https://img.gamemonetize.com/jgntj11qjbddgnauxsg2xhk1mr0p44ka/512x384.jpg","c":4,"p":0,"r":0.0,"f":false},{"id":8236,"t":"Cute Rabbit Dress Up","s":"cute-rabbit-dress-up","img":"https://img.gamemonetize.com/6ffk32iz4kij9syfuoknlyivw6d9h67c/512x384.jpg","c":4,"p":0,"r":0.0,"f":false},{"id":8237,"t":"Mario Pixel","s":"mario-pixel","img":"https://img.gamemonetize.com/9mfuvli2qp6awvbxuf8eq2h3rkbx41zv/512x384.jpg","c":4,"p":0,"r":0.0,"f":false},{"id":8238,"t":"Kitty Kate Caring Game","s":"kitty-kate-caring-game","img":"https://img.gamemonetize.com/tj5ugns8s0bdvgc4pbt4btxoybavxqji/512x384.jpg","c":4,"p":0,"r":0.0,"f":false},{"id":8239,"t":"Drive Mad Game","s":"drive-mad-game","img":"https://img.gamemonetize.com/c5t3d0nn601zum0ctct3vlyr07e26akn/512x384.jpg","c":4,"p":0,"r":0.0,"f":false},{"id":8240,"t":"Draw Rider","s":"draw-rider","img":"https://img.gamemonetize.com/fjpx5izlghqk91qffhfzppo2ndjkwnhu/512x384.jpg","c":4,"p":0,"r":0.0,"f":false},{"id":8241,"t":"Catch The Thief","s":"catch-the-thief","img":"https://img.gamemonetize.com/p5975lxccebw95jbl14e039151g98po0/512x384.jpg","c":5,"p":0,"r":0.0,"f":false},{"id":8242,"t":"Baby Dream City Buildings","s":"baby-dream-city-buildings","img":"https://img.gamemonetize.com/obqmy85i7a0ot8c0tzn5u8dcrzjlawxv/512x384.jpg","c":5,"p":0,"r":0.0,"f":false},{"id":8243,"t":"Baby Taylor Foot Treatment","s":"baby-taylor-foot-treatment","img":"https://img.gamemonetize.com/louebtx78dneogix5duxvffzr6in1uc2/512x384.jpg","c":5,"p":0,"r":0.0,"f":false},{"id":8244,"t":"Captain Photon and the planet of chaos","s":"captain-photon-and-the-planet-of-chaos","img":"https://img.gamemonetize.com/hb2irnfj259uvmcewjahwegwb3m6sfd8/512x384.jpg","c":3,"p":0,"r":0.0,"f":false},{"id":8245,"t":"Fill In the holes","s":"fill-in-the-holes","img":"https://img.gamemonetize.com/rncw0nw0zsphlmsp4mt3h2kdytzhtj4v/512x384.jpg","c":5,"p":0,"r":0.0,"f":false},{"id":8246,"t":"Fireman Plumber","s":"fireman-plumber","img":"https://img.gamemonetize.com/1l84tmer5b2d88ig6iie0tvsittqzy15/512x384.jpg","c":5,"p":0,"r":0.0,"f":false},{"id":8247,"t":"Tricky Kick 3D","s":"tricky-kick-3d","img":"https://img.gamemonetize.com/nsmipr62p5xgqk6nfl1c490yoqcivgbp/512x384.jpg","c":5,"p":0,"r":0.0,"f":false},{"id":8248,"t":"Fire Glow","s":"fire-glow","img":"https://img.gamemonetize.com/wtdluh8rduj40g8xsa3gcogslooh0xn7/512x384.jpg","c":5,"p":0,"r":0.0,"f":false},{"id":8249,"t":"Fish War","s":"fish-war","img":"https://img.gamemonetize.com/q2k9napa4s6xpbo9kecmaes2k7s93neg/512x384.jpg","c":5,"p":0,"r":0.0,"f":false},{"id":8250,"t":"Futurama: Worlds of Tomorrow","s":"futurama-worlds-of-tomorrow","img":"https://img.gamemonetize.com/r932sdfqt5sfcwbbcdgkhm8pe476oegl/512x384.jpg","c":5,"p":0,"r":0.0,"f":false},{"id":8251,"t":"Foot Starts","s":"foot-starts","img":"https://img.gamemonetize.com/6xtnv9ynct84av1hck4ig1utvxzwfyh1/512x384.jpg","c":8,"p":0,"r":0.0,"f":false},{"id":8252,"t":"Ninja Frog Adventure","s":"ninja-frog-adventure","img":"https://img.gamemonetize.com/jhcmm3yoaekmmrjclzpf4jwa4bfp51ma/512x384.jpg","c":4,"p":0,"r":0.0,"f":false},{"id":8253,"t":"SpongeBob Tasty Pastry Party","s":"spongebob-tasty-pastry-party","img":"https://img.gamemonetize.com/gzsh3vucbzplb84mqmrktrzs739m6oi8/512x384.jpg","c":4,"p":0,"r":0.0,"f":false},{"id":8254,"t":"Igrica Horse Riding Tales","s":"igrica-horse-riding-tales","img":"https://img.gamemonetize.com/lv2pg2wuo141jh2pow38lszjcag055kg/512x384.jpg","c":4,"p":0,"r":0.0,"f":false},{"id":8255,"t":"Super dash furious car","s":"super-dash-furious-car","img":"https://img.gamemonetize.com/sgele4027ojvvorwtp4601z0i5fbg6ln/512x384.jpg","c":4,"p":0,"r":0.0,"f":false},{"id":8256,"t":"King Soldiers 2","s":"king-soldiers-2","img":"https://img.gamemonetize.com/exqw389x6a93yqsynte7a1akjaevwujr/512x384.jpg","c":3,"p":0,"r":0.0,"f":false},{"id":8257,"t":"Kind Net","s":"kind-net","img":"https://img.gamemonetize.com/zx6erjhgs48265lw47ea0hae7az8emdn/512x384.jpg","c":4,"p":0,"r":0.0,"f":false},{"id":8258,"t":"Fast Fruit Master","s":"fast-fruit-master","img":"https://img.gamemonetize.com/57qgab4ijjis219xiho0nemj2vfype9n/512x384.jpg","c":4,"p":0,"r":0.0,"f":false},{"id":8259,"t":"Bee Connect","s":"bee-connect","img":"https://img.gamemonetize.com/jsgoewk6501r1i64rpwurs6qv4p8zvc8/512x384.jpg","c":5,"p":0,"r":0.0,"f":false},{"id":8260,"t":"Pixel Farm","s":"pixel-farm","img":"https://img.gamemonetize.com/zjck48l0ojoxe2om0j8jxr3q28qyea12/512x384.jpg","c":4,"p":0,"r":0.0,"f":false},{"id":8261,"t":"STACK BOUNCE BALL 3D","s":"stack-bounce-ball-3d","img":"https://img.gamemonetize.com/kkoxh6w93u977reucohy4x087hzt4ms9/512x384.jpg","c":4,"p":0,"r":0.0,"f":false},{"id":8262,"t":"Rope Bowling","s":"rope-bowling","img":"https://img.gamemonetize.com/p1s1b5dcu2sjw4q34lbih8wbdi0vy0tc/512x384.jpg","c":5,"p":0,"r":0.0,"f":false},{"id":8263,"t":"Real Car Parking : For Parking Master","s":"real-car-parking-for-parking-master","img":"https://img.gamemonetize.com/qk0yp52x1oqb8z3xmeq3bny5s87iwekk/512x384.jpg","c":2,"p":0,"r":0.0,"f":false},{"id":8264,"t":"Barbie Dreamhouse Adventures","s":"barbie-dreamhouse-adventures","img":"https://img.gamemonetize.com/31hskobgfca3c2i0chn3xngv71fs9ja7/512x384.jpg","c":2,"p":0,"r":0.0,"f":false},{"id":8265,"t":"City Wars","s":"city-wars","img":"https://img.gamemonetize.com/m4ogz9j756kfocanh3xp3rdtiy4xf3sx/512x384.jpg","c":2,"p":0,"r":0.0,"f":false},{"id":8266,"t":"Sweety Shapes","s":"sweety-shapes","img":"https://img.gamemonetize.com/1zsd5itydzwo9bha2ci8ogmgd4j0agcv/512x384.jpg","c":5,"p":0,"r":0.0,"f":false},{"id":8267,"t":"Baby Panda bath","s":"baby-panda-bath","img":"https://img.gamemonetize.com/vsobpkzd592d0lv7jr8gm3zodw1nn3k9/512x384.jpg","c":5,"p":0,"r":0.0,"f":false},{"id":8268,"t":"Car Parking: Traffic Jam 3D","s":"car-parking-traffic-jam-3d","img":"https://img.gamemonetize.com/xu8g06ptjfcyeg2uzgbxj9zt6u2ejjk5/512x384.jpg","c":2,"p":0,"r":0.0,"f":false},{"id":8269,"t":"The Killer Imposter Among Us","s":"the-killer-imposter-among-us","img":"https://img.gamemonetize.com/e9e56lai1f95awyk8kdguc1abywlcwwf/512x384.jpg","c":5,"p":0,"r":0.0,"f":false},{"id":8270,"t":"Disney Frozen Olaf","s":"disney-frozen-olaf","img":"https://img.gamemonetize.com/a8thgwj75cf1cfrejgec1eixjbe5atzg/512x384.jpg","c":5,"p":0,"r":0.0,"f":false},{"id":8271,"t":"Batman: The Enemy Within","s":"batman-the-enemy-within","img":"https://img.gamemonetize.com/gu2dah34mhaor0mafzu0kedi0xfln4p5/512x384.jpg","c":5,"p":0,"r":0.0,"f":false},{"id":8272,"t":"Captain America","s":"captain-america","img":"https://img.gamemonetize.com/ybiqbicbn18vxfnh9iqe3fmoj7yhqsy0/512x384.jpg","c":5,"p":0,"r":0.0,"f":false},{"id":8273,"t":"Kick The Poppy","s":"kick-the-poppy","img":"https://img.gamemonetize.com/b58wm52gztnofhx5x9lpeia94n9zqeac/512x384.jpg","c":5,"p":0,"r":0.0,"f":false},{"id":8274,"t":"Rescue the Brinjal","s":"rescue-the-brinjal","img":"https://img.gamemonetize.com/a578m00htxmdp3jayy4721wcc4tq88hs/512x384.jpg","c":5,"p":0,"r":0.0,"f":false},{"id":8275,"t":"Construction House Escape","s":"construction-house-escape","img":"https://img.gamemonetize.com/tmy8vg9wmd47khmet10lnns8xi2l1zi3/512x384.jpg","c":5,"p":0,"r":0.0,"f":false},{"id":8276,"t":"Sticky Basket 1","s":"sticky-basket-1","img":"https://img.gamemonetize.com/1i8j7qj1zq9rdzwkb567zg6iklloh89p/512x384.jpg","c":4,"p":0,"r":0.0,"f":false},{"id":8277,"t":"Tunko 2","s":"tunko-2","img":"https://img.gamemonetize.com/22zt55manskc3q2pvdg1opshlb720zik/512x384.jpg","c":4,"p":0,"r":0.0,"f":false},{"id":8278,"t":"Playtime Night Scary","s":"playtime-night-scary","img":"https://img.gamemonetize.com/njfqu6lf1p762h7d4tqvtyhc7sxoi219/512x384.jpg","c":4,"p":0,"r":0.0,"f":false},{"id":8279,"t":"Jumpy Frog","s":"jumpy-frog","img":"https://img.gamemonetize.com/02gmjmdfnqwf9b1ntsso6j5n1wbsf8i8/512x384.jpg","c":4,"p":0,"r":0.0,"f":false},{"id":8280,"t":"Survival Hero","s":"survival-hero","img":"https://img.gamemonetize.com/50llgp8iig7d3mp6fzfgr3ggliy20n3y/512x384.jpg","c":4,"p":0,"r":0.0,"f":false},{"id":8281,"t":"Super Mario Run Tour","s":"super-mario-run-tour","img":"https://img.gamemonetize.com/mucd7jmt36errp2518pxuiq161sjk6ve/512x384.jpg","c":4,"p":0,"r":0.0,"f":false},{"id":8282,"t":"Pikachu Classic","s":"pikachu-classic","img":"https://img.gamemonetize.com/f6camw2e7uqtlpbr29gncf6gvmrxr9q6/512x384.jpg","c":5,"p":0,"r":0.0,"f":false},{"id":8283,"t":"Tattoo Salon Art","s":"tattoo-salon-art","img":"https://img.gamemonetize.com/rxr2vhxr41isnf2a3ed9zsmc97w6q9n8/512x384.jpg","c":5,"p":0,"r":0.0,"f":false},{"id":8284,"t":"Fruits Master","s":"fruits-master","img":"https://img.gamemonetize.com/liaxyb5kl7ffmeecq7xczf30exmezo9w/512x384.jpg","c":5,"p":0,"r":0.0,"f":false},{"id":8285,"t":"Zombie Age Dead Jungle","s":"zombie-age-dead-jungle","img":"https://img.gamemonetize.com/e7d9xdv30v9bm533aco6wyytj1mmy7kh/512x384.jpg","c":5,"p":0,"r":0.0,"f":false},{"id":8286,"t":"Cat Stretch Game","s":"cat-stretch-game","img":"https://img.gamemonetize.com/ch3hwrfw42sgxtsuo22f5gbzqzsr86bx/512x384.jpg","c":5,"p":0,"r":0.0,"f":false},{"id":8287,"t":"Shoot Bubbles","s":"shoot-bubbles","img":"https://img.gamemonetize.com/l7tc8czsopt46oopaufh222mq7o60527/512x384.jpg","c":3,"p":0,"r":0.0,"f":false},{"id":8288,"t":"Funny Face","s":"funny-face","img":"https://img.gamemonetize.com/wpuqeoxce35xn9mde3ymhzm8bpif288l/512x384.jpg","c":5,"p":0,"r":0.0,"f":false},{"id":8289,"t":"Tribal wars","s":"tribal-wars","img":"https://img.gamemonetize.com/v3lcwfdygubvh79gdrcf891tx8g8dqlr/512x384.jpg","c":1,"p":0,"r":0.0,"f":false},{"id":8290,"t":"Fashion Tattoo Studio 4","s":"fashion-tattoo-studio-4","img":"https://img.gamemonetize.com/tnw9gudn4cn34mmm73zc7mzego5h4lfj/512x384.jpg","c":1,"p":0,"r":0.0,"f":false},{"id":8291,"t":"Super Tower War","s":"super-tower-war","img":"https://img.gamemonetize.com/jrr7acndi8zfc70i0cf0y5m74nci4zmm/512x384.jpg","c":1,"p":0,"r":0.0,"f":false},{"id":8292,"t":"Stupid Zombies Game","s":"stupid-zombies-game","img":"https://img.gamemonetize.com/w40uqcj11jyv8bbtwwhm77jttlo31h13/512x384.jpg","c":1,"p":0,"r":0.0,"f":false},{"id":8293,"t":"Princess E-Girl vs Soft Girl - Makeover Game","s":"princess-e-girl-vs-soft-girl-makeover-game","img":"https://img.gamemonetize.com/bwl8rvchmcud9o9w88l9nmbp093l4m6g/512x384.jpg","c":1,"p":0,"r":0.0,"f":false},{"id":8294,"t":"SuperHero.io","s":"superhero-io","img":"https://img.gamemonetize.com/eccaym7ri1dqacofsiygwcl9oc66hqwo/512x384.jpg","c":1,"p":0,"r":0.0,"f":false},{"id":8295,"t":"Bazooka Boy Adventure","s":"bazooka-boy-adventure","img":"https://img.gamemonetize.com/xl469cxrtiy9nok2s30y25llty5mkoa5/512x384.jpg","c":1,"p":0,"r":0.0,"f":false},{"id":8296,"t":"Blumgi Rocket Game","s":"blumgi-rocket-game","img":"https://img.gamemonetize.com/830q4dkk2atk7t6ioitf7qg3siq4d5w6/512x384.jpg","c":1,"p":0,"r":0.0,"f":false},{"id":8297,"t":"Pizza Chef","s":"pizza-chef","img":"https://img.gamemonetize.com/c2qdll8xblr8etagnsaiqelr6beudzqg/512x384.jpg","c":1,"p":0,"r":0.0,"f":false},{"id":8298,"t":"Flow Laser Quest","s":"flow-laser-quest","img":"https://img.gamemonetize.com/prsu5c4ea3l1ayf84ae93f52gcg0uma9/512x384.jpg","c":4,"p":0,"r":0.0,"f":false},{"id":8299,"t":"Glow Blast !","s":"glow-blast","img":"https://img.gamemonetize.com/ydau2m96beapjawel486408fsttkal00/512x384.jpg","c":4,"p":0,"r":0.0,"f":false},{"id":8300,"t":"Flower Blast","s":"flower-blast","img":"https://img.gamemonetize.com/ssm71b1bk33le1q1mg11ycknwzwbqplh/512x384.jpg","c":5,"p":0,"r":0.0,"f":false}]