[{"id":14801,"t":"Silent Speeder","s":"silent-speeder","img":"https://img.gamemonetize.com/gnoc2mi9djexlkih0fdipu2y59lansr6/512x384.jpg","c":2,"p":0,"r":0.0,"f":false},{"id":14802,"t":"Incredible Box","s":"incredible-box","img":"https://img.gamemonetize.com/f14u949kgkr1277i1fv24njteb6efmxe/512x384.jpg","c":5,"p":0,"r":0.0,"f":false},{"id":14803,"t":"Chinese Checkers Master","s":"chinese-checkers-master","img":"https://img.gamemonetize.com/87ja1h5uzoozejmgwwypaa6cc7w8c8kr/512x384.jpg","c":7,"p":0,"r":0.0,"f":false},{"id":14804,"t":"AmonJump","s":"amonjump","img":"https://img.gamemonetize.com/92he2h2xu3mwzsnvwcyl49k65x0gc2v4/512x384.jpg","c":8,"p":0,"r":0.0,"f":false},{"id":14805,"t":"Shoot impostors","s":"shoot-impostors","img":"https://img.gamemonetize.com/826y6hjag8dnh6z54v998tb92x6zpwam/512x384.jpg","c":8,"p":0,"r":0.0,"f":false},{"id":14806,"t":"Follow finger","s":"follow-finger","img":"https://img.gamemonetize.com/c9yixjolkmjq3xpjq5bwqexsou4pzxro/512x384.jpg","c":8,"p":0,"r":0.0,"f":false},{"id":14807,"t":"Among escape","s":"among-escape","img":"https://img.gamemonetize.com/1esqr27pq3x4i52kaiab8h04z3z0cj1n/512x384.jpg","c":8,"p":0,"r":0.0,"f":false},{"id":14808,"t":"Disc Challenge","s":"disc-challenge","img":"https://img.gamemonetize.com/tvw5ddin06ma8z98t1f9gewzsag6lo7p/512x384.jpg","c":8,"p":0,"r":0.0,"f":false},{"id":14809,"t":"Crab Game","s":"crab-game","img":"https://img.gamemonetize.com/eji6ha61v548onocf86eq57g2cibyjbw/512x384.jpg","c":1,"p":0,"r":0.0,"f":false},{"id":14810,"t":"Pukiimoon","s":"pukiimoon","img":"https://img.gamemonetize.com/kj3oej945qctvv39qna1jm329mxxz2y3/512x384.jpg","c":1,"p":0,"r":0.0,"f":false},{"id":14811,"t":"Gun Simulator","s":"gun-simulator","img":"https://img.gamemonetize.com/ioxpvdvjumy6a06kdx9a55c79psbrq6l/512x384.jpg","c":1,"p":0,"r":0.0,"f":false},{"id":14812,"t":"Jump The Block","s":"jump-the-block","img":"https://img.gamemonetize.com/bswntkpiz67ghp0pwmc8i82ezm26smtv/512x384.jpg","c":1,"p":0,"r":0.0,"f":false},{"id":14813,"t":"Thanksgiving Rush","s":"thanksgiving-rush","img":"https://img.gamemonetize.com/xumsoavjscfbp84o64p7kown3tvd3tfc/512x384.jpg","c":5,"p":0,"r":0.0,"f":false},{"id":14814,"t":"Tower Blocks Deluxe","s":"tower-blocks-deluxe","img":"https://img.gamemonetize.com/v702r77byf6atw8prvlh39twjikhpp8r/512x384.jpg","c":5,"p":0,"r":0.0,"f":false},{"id":14815,"t":"Alphabet Soup For Kids","s":"alphabet-soup-for-kids","img":"https://img.gamemonetize.com/5w3k57bq46e75i0uxn2v261n1zlzravw/512x384.jpg","c":5,"p":0,"r":0.0,"f":false},{"id":14816,"t":"Color Mixed Up","s":"color-mixed-up","img":"https://img.gamemonetize.com/j4oe0f6cq2qg2knihsrs0lh8mym3naf9/512x384.jpg","c":5,"p":0,"r":0.0,"f":false},{"id":14817,"t":"Fruit Frenzy","s":"fruit-frenzy","img":"https://img.gamemonetize.com/r9hubrwe45y44vj7cg7szc5fwwf3tnuf/512x384.jpg","c":5,"p":0,"r":0.0,"f":false},{"id":14818,"t":"Stick Merge","s":"stick-merge","img":"https://img.gamemonetize.com/fayy3t63ulyf074trnts40an71cqjcci/512x384.jpg","c":5,"p":0,"r":0.0,"f":false},{"id":14819,"t":"Super Mario Run 21","s":"super-mario-run-21","img":"https://img.gamemonetize.com/jwg35uw97n9vmcz5hoads7l4f0ysi8yg/512x384.jpg","c":5,"p":0,"r":0.0,"f":false},{"id":14820,"t":"Squid Doll Shooter Game","s":"squid-doll-shooter-game","img":"https://img.gamemonetize.com/hb74we4zc07gs3h3jcguyxdm3q81y4os/512x384.jpg","c":3,"p":0,"r":0.0,"f":false},{"id":14821,"t":"Santa Claus Coloring Book","s":"santa-claus-coloring-book","img":"https://img.gamemonetize.com/tja2s91kpljtud869aiu7o2qv961r96h/512x384.jpg","c":5,"p":0,"r":0.0,"f":false},{"id":14822,"t":"Brawl Stars Christmas Coloring","s":"brawl-stars-christmas-coloring","img":"https://img.gamemonetize.com/r0i2a5gzpjaee098gu6m9s42wu3c41kh/512x384.jpg","c":5,"p":0,"r":0.0,"f":false},{"id":14823,"t":"Spider Man : Multiverse","s":"spider-man-multiverse","img":"https://img.gamemonetize.com/20anovxv7b5uxezx7twhb3k9icakmbm0/512x384.jpg","c":5,"p":0,"r":0.0,"f":false},{"id":14824,"t":"8b blue house escape","s":"8b-blue-house-escape","img":"https://img.gamemonetize.com/mnr17o1mfwyf2rn265apdgpj82aushgz/512x384.jpg","c":5,"p":0,"r":0.0,"f":false},{"id":14825,"t":"Snoopy Escape","s":"snoopy-escape","img":"https://img.gamemonetize.com/x6xrgq30b1yg6s61zyq5uira6dasurj1/512x384.jpg","c":5,"p":0,"r":0.0,"f":false},{"id":14826,"t":"Fitness Trainer Escape","s":"fitness-trainer-escape","img":"https://img.gamemonetize.com/m1yybhk67hru75gdweqqdyuh45lnyw38/512x384.jpg","c":5,"p":0,"r":0.0,"f":false},{"id":14827,"t":"Fa Mulan Christmas Sweater Dress Up","s":"fa-mulan-christmas-sweater-dress-up","img":"https://img.gamemonetize.com/y6tno9btd52j157idbuvtqfednsn8o38/512x384.jpg","c":5,"p":0,"r":0.0,"f":false},{"id":14828,"t":"Ariel The Little Mermaid Christmas Dres Up","s":"ariel-the-little-mermaid-christmas-dres-up","img":"https://img.gamemonetize.com/rg4173xsv0aapylrh7nkdvvtfy4v0olm/512x384.jpg","c":5,"p":0,"r":0.0,"f":false},{"id":14829,"t":"Moana Christmas Sweater Dress Up","s":"moana-christmas-sweater-dress-up","img":"https://img.gamemonetize.com/rc5gq6zsc4uav49ya42gig6ovlls8s4f/512x384.jpg","c":5,"p":0,"r":0.0,"f":false},{"id":14830,"t":"Princess Aurora Christmas Sweater Dress Up","s":"princess-aurora-christmas-sweater-dress-up","img":"https://img.gamemonetize.com/noee246iai3htu07ajte8bvtfo1gfvgy/512x384.jpg","c":5,"p":0,"r":0.0,"f":false},{"id":14831,"t":"Jasmine | Aladdin Christmas Sweater Design","s":"jasmine-aladdin-christmas-sweater-design","img":"https://img.gamemonetize.com/xnpf2sxbi8wynhp54baqxf83hwgnqn4z/512x384.jpg","c":5,"p":0,"r":0.0,"f":false},{"id":14832,"t":"Rapunzel | Tangled Christmas Sweater Design","s":"rapunzel-tangled-christmas-sweater-design","img":"https://img.gamemonetize.com/xn885ci1ammaxm02ix0jhkqyal7ds1w2/512x384.jpg","c":5,"p":0,"r":0.0,"f":false},{"id":14833,"t":"Xmas Mahjong Deluxe","s":"xmas-mahjong-deluxe","img":"https://img.gamemonetize.com/vnelcgo6ketfnul27cvlwr54ij494111/512x384.jpg","c":5,"p":0,"r":0.0,"f":false},{"id":14834,"t":"Cannon Numbers","s":"cannon-numbers","img":"https://img.gamemonetize.com/aq3gmxekxl69oxf6tzungagtjnbkff75/512x384.jpg","c":4,"p":0,"r":0.0,"f":false},{"id":14835,"t":"Winter Trucks Jigsaw","s":"winter-trucks-jigsaw","img":"https://img.gamemonetize.com/pdpj62ys5jxjdf883e7mzxaz1wn6uti7/512x384.jpg","c":5,"p":0,"r":0.0,"f":false},{"id":14836,"t":"Squid Game the 7 challenge","s":"squid-game-the-7-challenge","img":"https://img.gamemonetize.com/03cp6fap1ygqbrnwnmnp04aabcoel6lu/512x384.jpg","c":5,"p":0,"r":0.0,"f":false},{"id":14837,"t":"Anna Frozen Christmas Sweater Design","s":"anna-frozen-christmas-sweater-design","img":"https://img.gamemonetize.com/qi87yy8vkfqy17kaxnja8bacn4d3h5bm/512x384.jpg","c":5,"p":0,"r":0.0,"f":false},{"id":14838,"t":"Barbie Christmas DressUp","s":"barbie-christmas-dressup","img":"https://img.gamemonetize.com/8am6jji3jembp2gv0y513ietpkt52adq/512x384.jpg","c":5,"p":0,"r":0.0,"f":false},{"id":14839,"t":"Happy Snowman Hidden","s":"happy-snowman-hidden","img":"https://img.gamemonetize.com/zgvcbtgvl4h9u532ybfd97y3a0zxn2i3/512x384.jpg","c":5,"p":0,"r":0.0,"f":false},{"id":14840,"t":"Pushed Balls","s":"pushed-balls","img":"https://img.gamemonetize.com/tdavgkdo04n7dkkpnki68p24ycwjj4yd/512x384.jpg","c":5,"p":0,"r":0.0,"f":false},{"id":14841,"t":"Words Geems","s":"words-geems","img":"https://img.gamemonetize.com/pvgp5noxuh7xmbqhdhvkdni9mh5ipxsj/512x384.jpg","c":5,"p":0,"r":0.0,"f":false},{"id":14842,"t":"Squid Game Hunter online","s":"squid-game-hunter-online","img":"https://img.gamemonetize.com/fds3yeagapaotsrv3x731id847qyoufk/512x384.jpg","c":3,"p":0,"r":0.0,"f":false},{"id":14843,"t":"Squid Games Red Light","s":"squid-games-red-light","img":"https://img.gamemonetize.com/har6syj1m4j6sfdy225s5rlvxtr6efh5/512x384.jpg","c":4,"p":0,"r":0.0,"f":false},{"id":14844,"t":"Join  amp; Strike","s":"join-amp-strike","img":"https://img.gamemonetize.com/90gtxq7z511qre74bugv02ix8zj50kxz/512x384.jpg","c":4,"p":0,"r":0.0,"f":false},{"id":14845,"t":"Emoji Color Sort Puzzle","s":"emoji-color-sort-puzzle","img":"https://img.gamemonetize.com/6imy2nuzjg8v1zi278bmz16ndnpanphc/512x384.jpg","c":5,"p":0,"r":0.0,"f":false},{"id":14846,"t":"Pokemon Jigsaw","s":"pokemon-jigsaw","img":"https://img.gamemonetize.com/g0tinffsqvh2csu943ccpwszecbodqvq/512x384.jpg","c":5,"p":0,"r":0.0,"f":false},{"id":14847,"t":"Desert 51 Shooting Game","s":"desert-51-shooting-game","img":"https://img.gamemonetize.com/ttq8gmv1bu00wo7fhm5h2f1wdhzbnq1s/512x384.jpg","c":3,"p":0,"r":0.0,"f":false},{"id":14848,"t":"Car ZigZag 3D","s":"car-zigzag-3d","img":"https://img.gamemonetize.com/syxl0ktpir2ca2jvkgz63wg2irdrmgxi/512x384.jpg","c":2,"p":0,"r":0.0,"f":false},{"id":14849,"t":"Cube Surffer - Smooth Cubes Building","s":"cube-surffer-smooth-cubes-building","img":"https://img.gamemonetize.com/ncyli6k3rt008fl81kfeyfv76jx0w0mn/512x384.jpg","c":4,"p":0,"r":0.0,"f":false},{"id":14850,"t":"Bus Simulation - City Bus Driver 3","s":"bus-simulation-city-bus-driver-3","img":"https://img.gamemonetize.com/tvqkdhcmrvpd7j0px6zga9uzs5xf298h/512x384.jpg","c":2,"p":0,"r":0.0,"f":false},{"id":14851,"t":"Bus Simulation - City Bus Driver","s":"bus-simulation-city-bus-driver","img":"https://img.gamemonetize.com/jw266cs654kavtbcxlql1yzmgfmtg0to/512x384.jpg","c":2,"p":0,"r":0.0,"f":false},{"id":14852,"t":"Bus Simulation - City Bus Driver 2","s":"bus-simulation-city-bus-driver-2","img":"https://img.gamemonetize.com/vizawtr6lm7l02mzer7gmpi77lytm3cs/512x384.jpg","c":2,"p":0,"r":0.0,"f":false},{"id":14853,"t":"Skull Arkanoide","s":"skull-arkanoide","img":"https://img.gamemonetize.com/0szhyqid3sj254awskn069p4u2e6gn79/512x384.jpg","c":2,"p":0,"r":0.0,"f":false},{"id":14854,"t":"Tiny Ball","s":"tiny-ball","img":"https://img.gamemonetize.com/bho8ivz00tt9b1yp2sl9hzgpm08ow2j6/512x384.jpg","c":5,"p":0,"r":0.0,"f":false},{"id":14855,"t":"StickMan Parkour 2","s":"stickman-parkour-2","img":"https://img.gamemonetize.com/ybbprvnzp8v7kixeiid7aum3fbxdty96/512x384.jpg","c":5,"p":0,"r":0.0,"f":false},{"id":14856,"t":"Stick Man Battle Fighting","s":"stick-man-battle-fighting","img":"https://img.gamemonetize.com/lyqrzmhsa4gdejjhe2c1fadi6uw6gaen/512x384.jpg","c":0,"p":0,"r":0.0,"f":false},{"id":14857,"t":"Kiki  amp;amp; Luna - Love Adventure","s":"kiki-luna-love-adventure","img":"https://img.gamemonetize.com/a3r5xjvkl4s9bfp593ptrmo2wyeau4km/512x384.jpg","c":0,"p":0,"r":0.0,"f":false},{"id":14858,"t":"Monki  amp;amp; Goru","s":"monki-goru","img":"https://img.gamemonetize.com/tefzu1ttut90mkokfwnwwwkgoj9nh2t1/512x384.jpg","c":0,"p":0,"r":0.0,"f":false},{"id":14859,"t":"Tom  amp;amp; Jerry Jigsaw Puzzle","s":"tom-jerry-jigsaw-puzzle","img":"https://img.gamemonetize.com/capb5z5nh56w76gkqqwd5962ybkw0ybo/512x384.jpg","c":0,"p":0,"r":0.0,"f":false},{"id":14860,"t":"Snow Car Drift  amp;amp; Car Racing 2023","s":"snow-car-drift-car-racing-2023","img":"https://img.gamemonetize.com/q08d190d72ezca1iniyzeedf66e5gas7/512x384.jpg","c":4,"p":0,"r":0.0,"f":false},{"id":14861,"t":"Mario  amp;amp; Banzai","s":"mario-banzai","img":"https://img.gamemonetize.com/ndyc9b1by8l0a1e7o9df9bttuaimvg1h/512x384.jpg","c":4,"p":0,"r":0.0,"f":false},{"id":14862,"t":"Pick  amp;amp; Match","s":"pick-match","img":"https://img.gamemonetize.com/1jcmnm8pt1f6oey44sxam4dkbu3jyzis/512x384.jpg","c":4,"p":0,"r":0.0,"f":false},{"id":14863,"t":"Wedding Dress Maker - Design  amp;amp; Style","s":"wedding-dress-maker-design-style","img":"https://img.gamemonetize.com/uq8nfjsn1pa9ttwov5xryennnyt7xoak/512x384.jpg","c":4,"p":0,"r":0.0,"f":false},{"id":14864,"t":"PlayTime Merge  amp;amp; Fight","s":"playtime-merge-fight","img":"https://img.gamemonetize.com/27g48eqzt0sprwpkbqune3qzeqxpha1g/512x384.jpg","c":3,"p":0,"r":0.0,"f":false},{"id":14865,"t":"Miraculous Ladybug  amp;amp; Cat Noir Jigsaw Puzzle","s":"miraculous-ladybug-cat-noir-jigsaw-puzzle","img":"https://img.gamemonetize.com/9tk0mpq9gm9186i4uiou62qkvcxmt9ho/512x384.jpg","c":3,"p":0,"r":0.0,"f":false},{"id":14866,"t":"Colored Water  amp;amp; Pin Game","s":"colored-water-pin-game","img":"https://img.gamemonetize.com/ycg9jf9jx78c5xbp4lnh6iuu1icold02/512x384.jpg","c":3,"p":0,"r":0.0,"f":false},{"id":14867,"t":"Puppy: Pet Salon  amp;amp; Dog Daycare","s":"puppy-pet-salon-dog-daycare","img":"https://img.gamemonetize.com/2rdzntxfli51o07aq51lx0uwlz1e1hm6/512x384.jpg","c":4,"p":0,"r":0.0,"f":false},{"id":14868,"t":"College Girl  amp;amp; Boy Makeover","s":"college-girl-boy-makeover","img":"https://img.gamemonetize.com/6lvixvko8m1fvo04d2p9awo5or48b55e/512x384.jpg","c":4,"p":0,"r":0.0,"f":false},{"id":14869,"t":"Monster Truck: Car Repair  amp;amp; Fix","s":"monster-truck-car-repair-fix","img":"https://img.gamemonetize.com/88cyjlq78o6kbjdnqgdhmcaxdwmhds45/512x384.jpg","c":4,"p":0,"r":0.0,"f":false},{"id":14870,"t":"Crash  amp;amp; Smash Cars","s":"crash-smash-cars","img":"https://img.gamemonetize.com/3jmt87m3rg6ny2yywoq7ao7iw1uoufli/512x384.jpg","c":2,"p":0,"r":0.0,"f":false},{"id":14871,"t":"Car Racing  amp;amp; BurnOut Drift","s":"car-racing-burnout-drift","img":"https://img.gamemonetize.com/9e5p8404dx3mel5abgm8uwvqgs6uhhdr/512x384.jpg","c":2,"p":0,"r":0.0,"f":false},{"id":14872,"t":"Merge Master: Poppy  amp;amp; Glamrock","s":"merge-master-poppy-glamrock","img":"https://img.gamemonetize.com/3imy2exjxatapeybfqfamxwnaqbdwujn/512x384.jpg","c":2,"p":0,"r":0.0,"f":false},{"id":14873,"t":"Halloween Hide  amp;amp; Seek","s":"halloween-hide-seek","img":"https://img.gamemonetize.com/4f62bnwvzkr8zv6sy0gdhj18nwnozqxf/512x384.jpg","c":2,"p":0,"r":0.0,"f":false},{"id":14874,"t":"Dracula , Frankenstein  amp;amp; Co","s":"dracula-frankenstein-co","img":"https://img.gamemonetize.com/xqph4jbaddk28fqq2f0xtyizl3pl9r4i/512x384.jpg","c":3,"p":0,"r":0.0,"f":false},{"id":14875,"t":"Dog  amp;amp; Duck","s":"dog-duck","img":"https://img.gamemonetize.com/fkdwggue3nbdpaxukm9fcq5zl171juxz/512x384.jpg","c":3,"p":0,"r":0.0,"f":false},{"id":14876,"t":"Fish  amp;amp; trip","s":"fish-trip","img":"https://img.gamemonetize.com/u92fzx3msocb8csc7ja5s85h6fvmawrd/512x384.jpg","c":3,"p":0,"r":0.0,"f":false},{"id":14877,"t":"Run  amp;amp; Jump: Jumbo Runner","s":"run-jump-jumbo-runner","img":"https://img.gamemonetize.com/msymfk14c0dc4s91k0csurujgtlnjj49/512x384.jpg","c":3,"p":0,"r":0.0,"f":false},{"id":14878,"t":"Key  amp;amp; Sheild","s":"key-sheild","img":"https://img.gamemonetize.com/8e42fm9ibrwwug99xwe0u1ruc7x7v6gb/512x384.jpg","c":3,"p":0,"r":0.0,"f":false},{"id":14879,"t":"Jigsaw Puzzle Cats  amp;amp; Kitten","s":"jigsaw-puzzle-cats-kitten","img":"https://img.gamemonetize.com/6igta01s1s6nazx72djcsn2agq6ubmb7/512x384.jpg","c":3,"p":0,"r":0.0,"f":false},{"id":14880,"t":"Lily s Garden - Design  amp;amp; Relax","s":"lily-rsquo-s-garden-design-relax","img":"https://img.gamemonetize.com/e3777ucsq9ql1cw3qfxyezwv0e8ex1aa/512x384.jpg","c":3,"p":0,"r":0.0,"f":false},{"id":14881,"t":"Tom  amp;amp; Angela Jump","s":"tom-angela-jump","img":"https://img.gamemonetize.com/swjuigc0cd2hcsxr1xo6jclbutjumzgt/512x384.jpg","c":3,"p":0,"r":0.0,"f":false},{"id":14882,"t":"Cake Shop Pastries  amp;amp; Waffles","s":"cake-shop-pastries-waffles","img":"https://img.gamemonetize.com/fq5ntnkx1rtu0zcpumeukd1l9zlexnvt/512x384.jpg","c":3,"p":0,"r":0.0,"f":false},{"id":14883,"t":"Black  amp;amp; white ski challenge","s":"black-white-ski-challenge","img":"https://img.gamemonetize.com/d1uqxetgxnkgfveuvnsxq5nkvib1jxlw/512x384.jpg","c":4,"p":0,"r":0.0,"f":false},{"id":14884,"t":"Chop  amp;amp; Mine 2","s":"chop-mine-2","img":"https://img.gamemonetize.com/9hg6c72m34t7bbpsv9cx5ntxhsrrab3x/512x384.jpg","c":1,"p":0,"r":0.0,"f":false},{"id":14885,"t":"Baby Taylor Farm Tour  amp;amp; Animal Caring","s":"baby-taylor-farm-tour-animal-caring","img":"https://img.gamemonetize.com/mozurd9lvnncrc6m8cqufu2ik38rgi5z/512x384.jpg","c":1,"p":0,"r":0.0,"f":false},{"id":14886,"t":"Tom  amp;amp; Jerry:Runner","s":"tom-jerry-runner","img":"https://img.gamemonetize.com/9j3csw5erc84p2kmq4okvgvw5nc18hp6/512x384.jpg","c":1,"p":0,"r":0.0,"f":false},{"id":14887,"t":"Tom  amp;amp; Friends Connect","s":"tom-friends-connect","img":"https://img.gamemonetize.com/9hcpayl9j5n00663g1b6mz1i4ef56e2c/512x384.jpg","c":1,"p":0,"r":0.0,"f":false},{"id":14888,"t":"Plumber  amp;amp; Pipes","s":"plumber-pipes","img":"https://img.gamemonetize.com/0x484xcur2gv94pu4yauo3mbi1czk7pi/512x384.jpg","c":1,"p":0,"r":0.0,"f":false},{"id":14889,"t":"Top Speed: Drag  amp;amp; Fast Racing","s":"top-speed-drag-fast-racing","img":"https://img.gamemonetize.com/nwhjh58fdbe2g8zeul553t26ldkr5agh/512x384.jpg","c":1,"p":0,"r":0.0,"f":false},{"id":14890,"t":"Dots  amp;amp; Boxes","s":"dots-boxes","img":"https://img.gamemonetize.com/1ldgaxfc2me8unfob5xfbp5n6rrd3gfa/512x384.jpg","c":1,"p":0,"r":0.0,"f":false},{"id":14891,"t":"Boys  amp;amp; Girls Bubble Pop","s":"boys-girls-bubble-pop","img":"https://img.gamemonetize.com/lwr8zzvam9lo2h9on0mx6pswi07xd461/512x384.jpg","c":1,"p":0,"r":0.0,"f":false},{"id":14892,"t":"Bmx Bike Freestyle  amp;amp; Racing","s":"bmx-bike-freestyle-racing","img":"https://img.gamemonetize.com/wvenwc6t1ybmoyix6qkayb8olio7ikcz/512x384.jpg","c":8,"p":0,"r":0.0,"f":false},{"id":14893,"t":"Cannon Ball  amp;amp; Pop It Fidget Game","s":"cannon-ball-pop-it-fidget-game","img":"https://img.gamemonetize.com/egq6rovu6g5pykqzdqfbkkh1s8sn5rr8/512x384.jpg","c":4,"p":0,"r":0.0,"f":false},{"id":14894,"t":"Fashion Doll Dream House Design  amp;amp; Decorating","s":"fashion-doll-dream-house-design-decorating","img":"https://img.gamemonetize.com/15rwx1k160jaxpw76i6s2lu3gjtvdomg/512x384.jpg","c":4,"p":0,"r":0.0,"f":false},{"id":14895,"t":"Ugi Bugi  amp;amp; Kisiy Misiy Summer","s":"ugi-bugi-kisiy-misiy-summer","img":"https://img.gamemonetize.com/xivfkbhxi4kqxu0cr8329ilh64g63jgm/512x384.jpg","c":4,"p":0,"r":0.0,"f":false},{"id":14896,"t":"Yellow Baby Horror Hide  amp;amp; Seek","s":"yellow-baby-horror-hide-seek","img":"https://img.gamemonetize.com/j45r4geqfx7q57vms5wkui2ao6j6w7c9/512x384.jpg","c":4,"p":0,"r":0.0,"f":false},{"id":14897,"t":"NERF Epic Pranks - Prank  amp;amp; Run","s":"nerf-epic-pranks-prank-run","img":"https://img.gamemonetize.com/qx9tyrn2r22yia8zom3j3rss9ysoj17j/512x384.jpg","c":4,"p":0,"r":0.0,"f":false},{"id":14898,"t":"Bmw Driving  amp;amp; Parking","s":"bmw-driving-parking","img":"https://img.gamemonetize.com/0stigvsud8jufd7dw6bu0vujtzkawpzi/512x384.jpg","c":4,"p":0,"r":0.0,"f":false},{"id":14899,"t":"Mini Fighters : Quest  amp;amp; battle","s":"mini-fighters-quest-battle","img":"https://img.gamemonetize.com/6540b5t38kezi3bq9d0v9lqexy9n12kk/512x384.jpg","c":4,"p":0,"r":0.0,"f":false},{"id":14900,"t":"Planet Hop","s":"planet-hop","img":"https://img.gamemonetize.com/ms05lkiccyqbsq7n5dm41wqcvl0g8zls/512x384.jpg","c":4,"p":0,"r":0.0,"f":false}]