[{"id":12701,"t":"Word Search Animals","s":"word-search-animals","img":"https://img.gamemonetize.com/v3ajh0iw0w7378cbkujvew8ykw9082ke/512x384.jpg","c":5,"p":0,"r":0.0,"f":false},{"id":12702,"t":"Among Us Crazy Shooter - Shooting Game","s":"among-us-crazy-shooter-shooting-game","img":"https://img.gamemonetize.com/xsi9ek1zvxm736wxbtjm0s0dpmbxa8gi/512x384.jpg","c":3,"p":0,"r":0.0,"f":false},{"id":12703,"t":"Red Tower - #456 Clash War","s":"red-tower-456-clash-war","img":"https://img.gamemonetize.com/dayy3i3619p3q72x39txi7sckzk5zcqv/512x384.jpg","c":5,"p":0,"r":0.0,"f":false},{"id":12704,"t":"Slope Ball","s":"slope-ball","img":"https://img.gamemonetize.com/qsl1d4uie9eh1p0tx61cfz2uar8n2ai4/512x384.jpg","c":5,"p":0,"r":0.0,"f":false},{"id":12705,"t":"Winx Bloom Coolgirl","s":"winx-bloom-coolgirl","img":"https://img.gamemonetize.com/dhn50p1onqztsl62pgvh7cak84oykfle/512x384.jpg","c":5,"p":0,"r":0.0,"f":false},{"id":12706,"t":"Roulette Simulator","s":"roulette-simulator","img":"https://img.gamemonetize.com/9ncojone1997bjfefuiti98ophx35onc/512x384.jpg","c":4,"p":0,"r":0.0,"f":false},{"id":12707,"t":"Among Us Online Edition - Find The Imposter","s":"among-us-online-edition-find-the-imposter","img":"https://img.gamemonetize.com/drrusvqsbnjaozaehuqsvg0oupu15yof/512x384.jpg","c":1,"p":0,"r":0.0,"f":false},{"id":12708,"t":"High Pizza - Fun  amp; Run 3D Game","s":"high-pizza-fun-amp-run-3d-game","img":"https://img.gamemonetize.com/ljpe7cxjvjg1tensbaf9em5k1pwbw3p5/512x384.jpg","c":1,"p":0,"r":0.0,"f":false},{"id":12709,"t":"Hit Villains - Shooting Game","s":"hit-villains-shooting-game","img":"https://img.gamemonetize.com/non07zue1njuolot11d0mkvipcniukdq/512x384.jpg","c":3,"p":0,"r":0.0,"f":false},{"id":12710,"t":"Spider-Man Green Goblin Havoc","s":"spider-man-green-goblin-havoc","img":"https://img.gamemonetize.com/470u7j17vlz08afen9c0j2xf8xei6di2/512x384.jpg","c":5,"p":0,"r":0.0,"f":false},{"id":12711,"t":"Spider-Man: Laboratory Lockdown","s":"spider-man-laboratory-lockdown","img":"https://img.gamemonetize.com/ekd2ofb21gr0ebukfar7sqrybwnpvyiv/512x384.jpg","c":5,"p":0,"r":0.0,"f":false},{"id":12712,"t":"Line  amp; Circle","s":"line-amp-circle","img":"https://img.gamemonetize.com/g11vnb6dacywobrlwyszepj0jamf5yhk/512x384.jpg","c":5,"p":0,"r":0.0,"f":false},{"id":12713,"t":"Johnny Runner","s":"johnny-runner","img":"https://img.gamemonetize.com/s4t8nbovy30x8q26fcsnkmw6esove29a/512x384.jpg","c":5,"p":0,"r":0.0,"f":false},{"id":12714,"t":"Furious Route","s":"furious-route","img":"https://img.gamemonetize.com/nc3iwt9gtdavfgesgv73opqgbp8qa6xh/512x384.jpg","c":5,"p":0,"r":0.0,"f":false},{"id":12715,"t":"My Cute Pony","s":"my-cute-pony","img":"https://img.gamemonetize.com/9ogpr4fb6a1fq8y06t1jk5tcqaseiv1d/512x384.jpg","c":5,"p":0,"r":0.0,"f":false},{"id":12716,"t":"Match Animals","s":"match-animals","img":"https://img.gamemonetize.com/vzj9o92ysu2grq9zz0qbx7udyex9u1mu/512x384.jpg","c":5,"p":0,"r":0.0,"f":false},{"id":12717,"t":"Tribal Zuma","s":"tribal-zuma","img":"https://img.gamemonetize.com/63lh22skhzyp4znidpgtt47qhn4rpatb/512x384.jpg","c":5,"p":0,"r":0.0,"f":false},{"id":12718,"t":"Beauty Princess Dressup","s":"beauty-princess-dressup","img":"https://img.gamemonetize.com/jre9k7s9csnzzrdl03cqg2ruspxijeeh/512x384.jpg","c":5,"p":0,"r":0.0,"f":false},{"id":12719,"t":"Sword Block Painter","s":"sword-block-painter","img":"https://img.gamemonetize.com/kwfj6flv1tv3la82r37icvesvu8m18m8/512x384.jpg","c":5,"p":0,"r":0.0,"f":false},{"id":12720,"t":"Huggy Wuggy Dress Up","s":"huggy-wuggy-dress-up","img":"https://img.gamemonetize.com/vrxvu291pympip5xpzw654p9bxyxx9yn/512x384.jpg","c":5,"p":0,"r":0.0,"f":false},{"id":12721,"t":"Pond Race","s":"pond-race","img":"https://img.gamemonetize.com/x7r4ij9pp5sptb5rj30svglg1fj83ji5/512x384.jpg","c":2,"p":0,"r":0.0,"f":false},{"id":12722,"t":"Supermarket Shopping Girls Game","s":"supermarket-shopping-girls-game","img":"https://img.gamemonetize.com/f3182g3bbrpr0nu1t3xy8ebccqt7h00v/512x384.jpg","c":4,"p":0,"r":0.0,"f":false},{"id":12723,"t":"Squid Survival Challenge","s":"squid-survival-challenge","img":"https://img.gamemonetize.com/a035c4hephik2hk1hmd8vnjuepjc7yr4/512x384.jpg","c":4,"p":0,"r":0.0,"f":false},{"id":12724,"t":"Ford Mustang California Special Slide","s":"ford-mustang-california-special-slide","img":"https://img.gamemonetize.com/vja9w52cj6879bi408pwecsochy77swf/512x384.jpg","c":5,"p":0,"r":0.0,"f":false},{"id":12725,"t":"Cookie Master","s":"cookie-master","img":"https://img.gamemonetize.com/l32c7naju05uprgn4fd2htg0t1rseo8y/512x384.jpg","c":5,"p":0,"r":0.0,"f":false},{"id":12726,"t":"Snake.is MLG Edition","s":"snake-is-mlg-edition","img":"https://img.gamemonetize.com/jczlp80l4h2g8335ozkb9rgsd26b30go/512x384.jpg","c":7,"p":0,"r":0.0,"f":false},{"id":12727,"t":"Woodcraft","s":"woodcraft","img":"https://img.gamemonetize.com/l8nqr04ewhoxi59ferotzzqw4639gq6b/512x384.jpg","c":7,"p":0,"r":0.0,"f":false},{"id":12728,"t":"Four Colors Game","s":"four-colors-game","img":"https://img.gamemonetize.com/9t9nh8knri6kb2nogsl2h60avh3cb74u/512x384.jpg","c":5,"p":0,"r":0.0,"f":false},{"id":12729,"t":"Rhino Rush Stampede","s":"rhino-rush-stampede","img":"https://img.gamemonetize.com/6y3cbmaiy7tfaqkdw6urqc4yc7ztgkz4/512x384.jpg","c":2,"p":0,"r":0.0,"f":false},{"id":12730,"t":"Robot Cars Match 3","s":"robot-cars-match-3","img":"https://img.gamemonetize.com/pmellcj7orhrsi3fqmlhyysf179v2nly/512x384.jpg","c":5,"p":0,"r":0.0,"f":false},{"id":12731,"t":"Super Shark World","s":"super-shark-world","img":"https://img.gamemonetize.com/lrn4ovcw8cjotn37j3vrdd9oecgb7gwo/512x384.jpg","c":5,"p":0,"r":0.0,"f":false},{"id":12732,"t":"Tri Puzzle","s":"tri-puzzle","img":"https://img.gamemonetize.com/q1oceg3goj2wfs7v3uwrwbopwk2uuk2r/512x384.jpg","c":5,"p":0,"r":0.0,"f":false},{"id":12733,"t":"Trial Tank","s":"trial-tank","img":"https://img.gamemonetize.com/v2aogkzp66tpbof1b2sfa46b62j3af42/512x384.jpg","c":2,"p":0,"r":0.0,"f":false},{"id":12734,"t":"Pixel Park 3D HTML5","s":"pixel-park-3d-html5","img":"https://img.gamemonetize.com/vnd0m6pxe8ll8lo2auax1lkjs1ybac9f/512x384.jpg","c":2,"p":0,"r":0.0,"f":false},{"id":12735,"t":"Fire And Water In Zombies World 2","s":"fire-and-water-in-zombies-world-2","img":"https://img.gamemonetize.com/2iypihs0rrdu3a5erywg59wbmykfdcml/512x384.jpg","c":2,"p":0,"r":0.0,"f":false},{"id":12736,"t":"Hovering Spaceship","s":"hovering-spaceship","img":"https://img.gamemonetize.com/uhxa8x0qyh4jnpbf7892gw1h4v8fi4uz/512x384.jpg","c":2,"p":0,"r":0.0,"f":false},{"id":12737,"t":"Tricky Track Game","s":"tricky-track-game","img":"https://img.gamemonetize.com/36d0wg9ufg5t3m8kk2l5stuqmyrli195/512x384.jpg","c":2,"p":0,"r":0.0,"f":false},{"id":12738,"t":"Rainbow Social Media Influencers","s":"rainbow-social-media-influencers","img":"https://img.gamemonetize.com/vw26ojjhvui9u5tgducnn5mmq05k936m/512x384.jpg","c":2,"p":0,"r":0.0,"f":false},{"id":12739,"t":"LOL Surprise Preppy Fashion","s":"lol-surprise-preppy-fashion","img":"https://img.gamemonetize.com/2a3deejcqnf84pgci8dgwknr14qqvbhq/512x384.jpg","c":2,"p":0,"r":0.0,"f":false},{"id":12740,"t":"Run Rubber Man 3D","s":"run-rubber-man-3d","img":"https://img.gamemonetize.com/zdwauz8wgb48x29sjecxa781uhyugxst/512x384.jpg","c":2,"p":0,"r":0.0,"f":false},{"id":12741,"t":"Jet Boat Racing","s":"jet-boat-racing","img":"https://img.gamemonetize.com/5r7362qipp68day343iq059sm3jp8wkv/512x384.jpg","c":2,"p":0,"r":0.0,"f":false},{"id":12742,"t":"Hero of Archery Games","s":"hero-of-archery-games","img":"https://img.gamemonetize.com/yr9s86e1qk0w4vdd9ot6rp28gafzdtyc/512x384.jpg","c":2,"p":0,"r":0.0,"f":false},{"id":12743,"t":"Stickman Dragon Ball Fight - Super Stick Warriors","s":"stickman-dragon-ball-fight-super-stick-warriors","img":"https://img.gamemonetize.com/f0hbsg1m7jfual8m1e8gtwqmu286chsr/512x384.jpg","c":2,"p":0,"r":0.0,"f":false},{"id":12744,"t":"Robot Car Emergency Rescue 2 - Help The Town","s":"robot-car-emergency-rescue-2-help-the-town","img":"https://img.gamemonetize.com/nr3h5nefmv6pz9uwr9mx9glp2mz5cl9g/512x384.jpg","c":2,"p":0,"r":0.0,"f":false},{"id":12745,"t":"Beauty Makeup Salon","s":"beauty-makeup-salon","img":"https://img.gamemonetize.com/zrtqkjxopyl2qv5yfgpy0iuowpscnd7z/512x384.jpg","c":2,"p":0,"r":0.0,"f":false},{"id":12746,"t":"Squid Game 123 Stop","s":"squid-game-123-stop","img":"https://img.gamemonetize.com/2bi1rwfm35dyc64ez0ry8lvl8wvts82g/512x384.jpg","c":2,"p":0,"r":0.0,"f":false},{"id":12747,"t":"Ice Man 3D","s":"ice-man-3d","img":"https://img.gamemonetize.com/19muh2ab3ms5j0ew9o84fjv7lvul5a4x/512x384.jpg","c":2,"p":0,"r":0.0,"f":false},{"id":12748,"t":"Polygon War Z Zombie","s":"polygon-war-z-zombie","img":"https://img.gamemonetize.com/9xrxwy97fyi5jgyu4fm8snoarjga3iwr/512x384.jpg","c":3,"p":0,"r":0.0,"f":false},{"id":12749,"t":"Crazy Stunt 3D","s":"crazy-stunt-3d","img":"https://img.gamemonetize.com/7fpjcxydju1ncfb2lh790t7rma10a1ci/512x384.jpg","c":3,"p":0,"r":0.0,"f":false},{"id":12750,"t":"Unblock Blocks","s":"unblock-blocks","img":"https://img.gamemonetize.com/eqjrx88mfac8je380hhrxwdmxh92dbbi/512x384.jpg","c":5,"p":0,"r":0.0,"f":false},{"id":12751,"t":"Click And Color Dinosaurs","s":"click-and-color-dinosaurs","img":"https://img.gamemonetize.com/dmdqafwcd4hvdz2caosgfskeltwk1j4o/512x384.jpg","c":5,"p":0,"r":0.0,"f":false},{"id":12752,"t":"Pop Fish Match Online Game","s":"pop-fish-match-online-game","img":"https://img.gamemonetize.com/puy9iy0wbcnc8de896zcr38styjnm46g/512x384.jpg","c":5,"p":0,"r":0.0,"f":false},{"id":12753,"t":"Ball Juggling","s":"ball-juggling","img":"https://img.gamemonetize.com/hku279ig870w1kx2u46aoetvgi7ghe51/512x384.jpg","c":8,"p":0,"r":0.0,"f":false},{"id":12754,"t":"Angry Goat Revenge Crazy","s":"angry-goat-revenge-crazy","img":"https://img.gamemonetize.com/orgzfn2brol13ycuer004u80rbjbq11v/512x384.jpg","c":8,"p":0,"r":0.0,"f":false},{"id":12755,"t":"Bob The Robber","s":"bob-the-robber","img":"https://img.gamemonetize.com/axjqhwihwo843nmu8hb30fqil40alqtu/512x384.jpg","c":8,"p":0,"r":0.0,"f":false},{"id":12756,"t":"Worm Survive","s":"worm-survive","img":"https://img.gamemonetize.com/1k63ein8bozw6odmzg4nm544xytdn7iq/512x384.jpg","c":2,"p":0,"r":0.0,"f":false},{"id":12757,"t":"Winx Makeover","s":"winx-makeover","img":"https://img.gamemonetize.com/wjyfr28ofa4y1t6djhjnxytyw0igbru1/512x384.jpg","c":2,"p":0,"r":0.0,"f":false},{"id":12758,"t":"Spiderman: Street Fighter","s":"spiderman-street-fighter","img":"https://img.gamemonetize.com/1zah7rt9fe0hyzg06gge9xmigsgw6gig/512x384.jpg","c":2,"p":0,"r":0.0,"f":false},{"id":12759,"t":"Bob The Robber 3","s":"bob-the-robber-3","img":"https://img.gamemonetize.com/mzvrht41dt5rp1qgyb28tc8h425pe8wh/512x384.jpg","c":2,"p":0,"r":0.0,"f":false},{"id":12760,"t":"Bus Parking 2022","s":"bus-parking-2022","img":"https://img.gamemonetize.com/ro9aac7ja0q0kocfl29odoajz8xtv15h/512x384.jpg","c":4,"p":0,"r":0.0,"f":false},{"id":12761,"t":"Squid Tower","s":"squid-tower","img":"https://img.gamemonetize.com/flm0fcf3qlgugdm7cznn56kwbttoamvk/512x384.jpg","c":5,"p":0,"r":0.0,"f":false},{"id":12762,"t":"Spiderman Masked Missions","s":"spiderman-masked-missions","img":"https://img.gamemonetize.com/j9frjyqvee8b1bi3b8g18d2wkewb1om3/512x384.jpg","c":2,"p":0,"r":0.0,"f":false},{"id":12763,"t":"Space Jump Online Game","s":"space-jump-online-game","img":"https://img.gamemonetize.com/tz841m5y0qo8vx4ie05epjc9aovksp8d/512x384.jpg","c":4,"p":0,"r":0.0,"f":false},{"id":12764,"t":"MonterShooter","s":"montershooter","img":"https://img.gamemonetize.com/gc54h4vn5pta1faz7b6rlkri783dsw08/512x384.jpg","c":3,"p":0,"r":0.0,"f":false},{"id":12765,"t":"Move the Blocks","s":"move-the-blocks","img":"https://img.gamemonetize.com/53qxe0y85r6w0kiq8rs0ef3w7e7jweud/512x384.jpg","c":5,"p":0,"r":0.0,"f":false},{"id":12766,"t":"Jungle Math Online Game","s":"jungle-math-online-game","img":"https://img.gamemonetize.com/ic1eko5vluxnjf79qab2kpvwe6cbp6zk/512x384.jpg","c":5,"p":0,"r":0.0,"f":false},{"id":12767,"t":"Love Cat Line","s":"love-cat-line","img":"https://img.gamemonetize.com/7kkpe70mi1pee3xz0ce7joszskmgwzgr/512x384.jpg","c":5,"p":0,"r":0.0,"f":false},{"id":12768,"t":"Tethan Arena","s":"tethan-arena","img":"https://img.gamemonetize.com/lvaw9m5z5wxn7v9ts6xz86zkxfx7t625/512x384.jpg","c":5,"p":0,"r":0.0,"f":false},{"id":12769,"t":"Minicarft Block Survival","s":"minicarft-block-survival","img":"https://img.gamemonetize.com/sqm0ikvwn57u4dxldluyrqioy7pwa9ht/512x384.jpg","c":5,"p":0,"r":0.0,"f":false},{"id":12770,"t":"Q Math","s":"q-math","img":"https://img.gamemonetize.com/iqa64rpu6v055pyogynmbnxfabqbmw0s/512x384.jpg","c":5,"p":0,"r":0.0,"f":false},{"id":12771,"t":"Trap Craft","s":"trap-craft","img":"https://img.gamemonetize.com/xtfcher6frext8d3yikjmg6j2ic52hkr/512x384.jpg","c":5,"p":0,"r":0.0,"f":false},{"id":12772,"t":"Free Kick Football","s":"free-kick-football","img":"https://img.gamemonetize.com/2dgwc7hkwpmai1n88pdafyed7e5pjl2e/512x384.jpg","c":8,"p":0,"r":0.0,"f":false},{"id":12773,"t":"Hexa Dungeon","s":"hexa-dungeon","img":"https://img.gamemonetize.com/yq85fdgp6sgv9ic4mc5xa9iw0eegy77k/512x384.jpg","c":5,"p":0,"r":0.0,"f":false},{"id":12774,"t":"Bumpy Ball","s":"bumpy-ball","img":"https://img.gamemonetize.com/c45pbpjq6ka2og259hlddk951g39njdz/512x384.jpg","c":5,"p":0,"r":0.0,"f":false},{"id":12775,"t":"Stage Show Designer","s":"stage-show-designer","img":"https://img.gamemonetize.com/w9fxml88pjqjlj5tdyjjcuugj5tfaobj/512x384.jpg","c":5,"p":0,"r":0.0,"f":false},{"id":12776,"t":"March Coloring Book","s":"march-coloring-book","img":"https://img.gamemonetize.com/o50g2ri4edcxcexpx1nmrte8jw5oqkt0/512x384.jpg","c":5,"p":0,"r":0.0,"f":false},{"id":12777,"t":"Knife Flip","s":"knife-flip","img":"https://img.gamemonetize.com/ozeicwdp21ijt35i17fywktdsxx225l6/512x384.jpg","c":5,"p":0,"r":0.0,"f":false},{"id":12778,"t":"Futurama","s":"futurama","img":"https://img.gamemonetize.com/ma8x179lhtxmhdeysyt51rqaopr7go4r/512x384.jpg","c":5,"p":0,"r":0.0,"f":false},{"id":12779,"t":"11 in 1 Arcade Games","s":"11-in-1-arcade-games","img":"https://img.gamemonetize.com/y2w9sloacurvnx97zrrl0i5sm9u46acb/512x384.jpg","c":4,"p":0,"r":0.0,"f":false},{"id":12780,"t":"Monster Shooter 3D","s":"monster-shooter-3d","img":"https://img.gamemonetize.com/s8ije1f11obfchnoeanq9lzm7zlm5a06/512x384.jpg","c":3,"p":0,"r":0.0,"f":false},{"id":12781,"t":"Love Test with Horoscopes","s":"love-test-with-horoscopes","img":"https://img.gamemonetize.com/98fv1ojvaizw72goqpgrxtdeczxi2ish/512x384.jpg","c":3,"p":0,"r":0.0,"f":false},{"id":12782,"t":"FPS Shooting Survival Sim","s":"fps-shooting-survival-sim","img":"https://img.gamemonetize.com/5rxwjnl6kc368x7uqdc6kzwx0do1731k/512x384.jpg","c":3,"p":0,"r":0.0,"f":false},{"id":12783,"t":"Soccer Flick The Ball","s":"soccer-flick-the-ball","img":"https://img.gamemonetize.com/u4l853ff5o5bb24631uynhzdhsdafwwl/512x384.jpg","c":4,"p":0,"r":0.0,"f":false},{"id":12784,"t":"Magical Unicorn Grooming World","s":"magical-unicorn-grooming-world","img":"https://img.gamemonetize.com/p8za3wfo8rnvdm6akws7ys282nyv1chs/512x384.jpg","c":4,"p":0,"r":0.0,"f":false},{"id":12785,"t":"Bubble Shooter Mania","s":"bubble-shooter-mania","img":"https://img.gamemonetize.com/nrqi0hp8spmn3i7cthewkva0c4qhldu9/512x384.jpg","c":5,"p":0,"r":0.0,"f":false},{"id":12786,"t":"My Virtual Pet Shop - Cute Animals","s":"my-virtual-pet-shop-cute-animals","img":"https://img.gamemonetize.com/k47d8gw3b8dk4dsm9ab1nufeblcyx80y/512x384.jpg","c":5,"p":0,"r":0.0,"f":false},{"id":12787,"t":"Candy Clicker","s":"candy-clicker","img":"https://img.gamemonetize.com/kgp2ccqm4lor9ma0urih2ut7d382egjp/512x384.jpg","c":5,"p":0,"r":0.0,"f":false},{"id":12788,"t":"FallIng The Ball 3D","s":"falling-the-ball-3d","img":"https://img.gamemonetize.com/db026nmfzn83dcoxi6ijthyt1zo5pnq3/512x384.jpg","c":4,"p":0,"r":0.0,"f":false},{"id":12789,"t":"Rope Ninja Game","s":"rope-ninja-game","img":"https://img.gamemonetize.com/q8bya6xuuv0vxnyls8udfxz0bf0bvswd/512x384.jpg","c":4,"p":0,"r":0.0,"f":false},{"id":12790,"t":"Football Cup Finger Soccer","s":"football-cup-finger-soccer","img":"https://img.gamemonetize.com/l2smbambmvvaytzq09fu4ux1xyw9uywh/512x384.jpg","c":4,"p":0,"r":0.0,"f":false},{"id":12791,"t":"Painting Rings","s":"painting-rings","img":"https://img.gamemonetize.com/7d7wmvh701m9r4u4l3f0570orn4c2wzu/512x384.jpg","c":4,"p":0,"r":0.0,"f":false},{"id":12792,"t":"Fruitz Shooter","s":"fruitz-shooter","img":"https://img.gamemonetize.com/io1d4qkdsyrd6f7ic3mar1o7jgxruhtr/512x384.jpg","c":5,"p":0,"r":0.0,"f":false},{"id":12793,"t":"OFFROAD Truck 4x4","s":"offroad-truck-4x4","img":"https://img.gamemonetize.com/uknn8d9rb2qq62ryyydjmgmnfbqctz2j/512x384.jpg","c":4,"p":0,"r":0.0,"f":false},{"id":12794,"t":"Bubble Shooter Blast Master","s":"bubble-shooter-blast-master","img":"https://img.gamemonetize.com/nnaz4rdxrhkfufcwjg6sq6qzxy8lophj/512x384.jpg","c":5,"p":0,"r":0.0,"f":false},{"id":12795,"t":"Pick Me Up City","s":"pick-me-up-city","img":"https://img.gamemonetize.com/hyvbfysgvskhmgf1b6mun9gm8h0wkbol/512x384.jpg","c":5,"p":0,"r":0.0,"f":false},{"id":12796,"t":"Barbie Fairy Star","s":"barbie-fairy-star","img":"https://img.gamemonetize.com/azs9j70phq1iklksye0s4l9rxokxerd6/512x384.jpg","c":5,"p":0,"r":0.0,"f":false},{"id":12797,"t":"Winx Stylish Dress","s":"winx-stylish-dress","img":"https://img.gamemonetize.com/x05ax1adf42x64fd657epyqhkzu3olfc/512x384.jpg","c":5,"p":0,"r":0.0,"f":false},{"id":12798,"t":"Winx Nail Makeover","s":"winx-nail-makeover","img":"https://img.gamemonetize.com/1y4yvpz1zohmquh2luwnrxvtmsk52903/512x384.jpg","c":5,"p":0,"r":0.0,"f":false},{"id":12799,"t":"Ben 10 Create Scene","s":"ben-10-create-scene","img":"https://img.gamemonetize.com/yovrb7ay4g2ghhrxg2imd91i7ta56s66/512x384.jpg","c":5,"p":0,"r":0.0,"f":false},{"id":12800,"t":"Cannon Bounce 3D","s":"cannon-bounce-3d","img":"https://img.gamemonetize.com/p8hgmouq7iwnno26uqhynazi6ryzvalo/512x384.jpg","c":3,"p":0,"r":0.0,"f":false}]