[{"id":17501,"t":"Kodi Kapow","s":"kodi-kapow","img":"https://img.gamemonetize.com/kjalpsudfq8399b140qsues0xjbk2jua/512x384.jpg","c":3,"p":0,"r":0.0,"f":false},{"id":17502,"t":"Subway Surfers World Mumbai","s":"subway-surfers-world-mumbai","img":"https://img.gamemonetize.com/b36hur39z5z2od8n9rqvbbx3dsdq9g87/512x384.jpg","c":4,"p":0,"r":0.0,"f":false},{"id":17503,"t":"Moto Bike Attack Race","s":"moto-bike-attack-race","img":"https://img.gamemonetize.com/z4ce9elc8bebrxqnqbr7vcl6693luh91/512x384.jpg","c":8,"p":0,"r":0.0,"f":false},{"id":17504,"t":"Mini-Muncher","s":"mini-muncher","img":"https://img.gamemonetize.com/8sqivf8n1b2uf820wsicewkgvkflrg9g/512x384.jpg","c":8,"p":0,"r":0.0,"f":false},{"id":17505,"t":"PixWars 2","s":"pixwars-2","img":"https://img.gamemonetize.com/dump9yuqyj17u2f6qmfup58iqal51ut2/512x384.jpg","c":8,"p":0,"r":0.0,"f":false},{"id":17506,"t":"Horror Nights Story","s":"horror-nights-story","img":"https://img.gamemonetize.com/xica5w6jn3wip623a3flvb0fxk8yfyuc/512x384.jpg","c":8,"p":0,"r":0.0,"f":false},{"id":17507,"t":"Smashy Duo","s":"smashy-duo","img":"https://img.gamemonetize.com/a0vsjksyyb7nhc5xr5mswtvnbarsgmye/512x384.jpg","c":8,"p":0,"r":0.0,"f":false},{"id":17508,"t":"Cut My Rope","s":"cut-my-rope","img":"https://img.gamemonetize.com/pefm3a8iiaf8lcva70prj4l7l8wbma9b/512x384.jpg","c":8,"p":0,"r":0.0,"f":false},{"id":17509,"t":"Subway Surfers Orleans","s":"subway-surfers-orleans","img":"https://img.gamemonetize.com/q43xi48x1b8dz9xxydpd3vl7vm3i9aj0/512x384.jpg","c":8,"p":0,"r":0.0,"f":false},{"id":17510,"t":"Dead Paradise: Race Shooter","s":"dead-paradise-race-shooter","img":"https://img.gamemonetize.com/61mrcblllfemg06dbr1lmu53e04e3p29/512x384.jpg","c":2,"p":0,"r":0.0,"f":false},{"id":17511,"t":"Stunt Car Challenge","s":"stunt-car-challenge","img":"https://img.gamemonetize.com/t6o1uc5zow2fpjk6u5i2kzh4xmt4teem/512x384.jpg","c":2,"p":0,"r":0.0,"f":false},{"id":17512,"t":"Potato Ball Panic","s":"potato-ball-panic","img":"https://img.gamemonetize.com/w5ehg4ojkkehz2l3ewve9wkmgji6g51i/512x384.jpg","c":2,"p":0,"r":0.0,"f":false},{"id":17513,"t":"Rally Point 3","s":"rally-point-3","img":"https://img.gamemonetize.com/p0v8kajsnxb388on3h7sdg4hxek9vzjk/512x384.jpg","c":2,"p":0,"r":0.0,"f":false},{"id":17514,"t":"Subway Surfers Havana","s":"subway-surfers-havana","img":"https://img.gamemonetize.com/2nar7qp7ooku6khswx07bji096e7micp/512x384.jpg","c":2,"p":0,"r":0.0,"f":false},{"id":17515,"t":"Skate Stars","s":"skate-stars","img":"https://img.gamemonetize.com/d2y749nelps2wyd8f4hu4wosqal5aysi/512x384.jpg","c":8,"p":0,"r":0.0,"f":false},{"id":17516,"t":"Subway Surfers St. Petersburg","s":"subway-surfers-st-petersburg","img":"https://img.gamemonetize.com/psmg2nzlc9zl9yajmhxxcr0yh3xyuekj/512x384.jpg","c":8,"p":0,"r":0.0,"f":false},{"id":17517,"t":"Run Rich 3D","s":"run-rich-3d","img":"https://img.gamemonetize.com/o8f0q0mx5cdcotsylxy00zltykhehk83/512x384.jpg","c":8,"p":0,"r":0.0,"f":false},{"id":17518,"t":"Sling Kong","s":"sling-kong","img":"https://img.gamemonetize.com/qusgnr3vyv7pe08fpw0l46rdmqgkz72w/512x384.jpg","c":4,"p":0,"r":0.0,"f":false},{"id":17519,"t":"Rabbit Avoid Thorn Ball","s":"rabbit-avoid-thorn-ball","img":"https://img.gamemonetize.com/j6db9237kqm4oxj9zccuyd5qdk1zbq2j/512x384.jpg","c":4,"p":0,"r":0.0,"f":false},{"id":17520,"t":"CrossWord","s":"crossword","img":"https://img.gamemonetize.com/z90aoprp32uzzdtrwrpyvvh90exbnz5b/512x384.jpg","c":4,"p":0,"r":0.0,"f":false},{"id":17521,"t":"Frozen 2 Jigsaw","s":"frozen-2-jigsaw","img":"https://img.gamemonetize.com/dl6ntq8wrz6occaxw2veod9rt655141a/512x384.jpg","c":4,"p":0,"r":0.0,"f":false},{"id":17522,"t":"Fireboy Watergirl In Zombies World","s":"fireboy-watergirl-in-zombies-world","img":"https://img.gamemonetize.com/vgchb0so8wnmqoxcm6knmntu8togt4az/512x384.jpg","c":4,"p":0,"r":0.0,"f":false},{"id":17523,"t":"Subway Surfers London","s":"subway-surfers-london","img":"https://img.gamemonetize.com/gulb79p0ikkjdiikhvtvs5bbw80svxvb/512x384.jpg","c":4,"p":0,"r":0.0,"f":false},{"id":17524,"t":"Bill The Bowman","s":"bill-the-bowman","img":"https://img.gamemonetize.com/kq15upalca47o0wejfzmvrsx4xrdqvrg/512x384.jpg","c":3,"p":0,"r":0.0,"f":false},{"id":17525,"t":"Kitty Scramble Stack Word","s":"kitty-scramble-stack-word","img":"https://img.gamemonetize.com/edrxkzd1a8bfs5agref0rgkfhl8vz12l/512x384.jpg","c":3,"p":0,"r":0.0,"f":false},{"id":17526,"t":"Master Archer","s":"master-archer","img":"https://img.gamemonetize.com/gvs2kor7h5yws4tkeqbcvfjhffytz8aw/512x384.jpg","c":3,"p":0,"r":0.0,"f":false},{"id":17527,"t":"Mermaid Lover In Beach","s":"mermaid-lover-in-beach","img":"https://img.gamemonetize.com/q0o904vkprfhcd1jinvds1t24gyim2ua/512x384.jpg","c":3,"p":0,"r":0.0,"f":false},{"id":17528,"t":"Cookie Crush Pokemon","s":"cookie-crush-pokemon","img":"https://img.gamemonetize.com/w6j5dwvaifktj7k3d6rfwhrqrps2iyre/512x384.jpg","c":3,"p":0,"r":0.0,"f":false},{"id":17529,"t":"Bubble Witch Saga","s":"bubble-witch-saga","img":"https://img.gamemonetize.com/aqu866ya5aowgd4r33uarlm3kl7rcpvn/512x384.jpg","c":3,"p":0,"r":0.0,"f":false},{"id":17530,"t":"Harvest Farm","s":"harvest-farm","img":"https://img.gamemonetize.com/sapsvri2rdswm6c50iuudl94g62c7vcz/512x384.jpg","c":3,"p":0,"r":0.0,"f":false},{"id":17531,"t":"Magic pet Bubble Connect","s":"magic-pet-bubble-connect","img":"https://img.gamemonetize.com/tnhriys540r9e4j6zvtknz4z0f08ahh4/512x384.jpg","c":3,"p":0,"r":0.0,"f":false},{"id":17532,"t":"Mario Bros Save Princess","s":"mario-bros-save-princess","img":"https://img.gamemonetize.com/pzluqw2ztrbz7w1tao6y171tvt1rrivv/512x384.jpg","c":3,"p":0,"r":0.0,"f":false},{"id":17533,"t":"Words Family","s":"words-family","img":"https://img.gamemonetize.com/vntwgs6y19nx39j0m9tu5mhrummtv8wr/512x384.jpg","c":3,"p":0,"r":0.0,"f":false},{"id":17534,"t":"Octopus Hugs","s":"octopus-hugs","img":"https://img.gamemonetize.com/j2co5qc1r71m7khfkymieh2n0mnyvtfe/512x384.jpg","c":3,"p":0,"r":0.0,"f":false},{"id":17535,"t":"Cut the Rope Time Travel.","s":"cut-the-rope-time-travel","img":"https://img.gamemonetize.com/25zj3ey9o9dh0wsahrzmvabmc5hsmo5p/512x384.jpg","c":3,"p":0,"r":0.0,"f":false},{"id":17536,"t":"Crazy 3D Moto Racing","s":"crazy-3d-moto-racing","img":"https://img.gamemonetize.com/mbnao7gxcmg9rjcta3uqekxn4z2tflwu/512x384.jpg","c":2,"p":0,"r":0.0,"f":false},{"id":17537,"t":"PuffyCat","s":"puffycat","img":"https://img.gamemonetize.com/h236l4jasya6anvzvcwl7nidd1nkzxlh/512x384.jpg","c":2,"p":0,"r":0.0,"f":false},{"id":17538,"t":"Merge Animal 2 : Farmland","s":"merge-animal-2-farmland","img":"https://img.gamemonetize.com/sg84v92x0m5wj3v2brfbhx3kbiklh5ca/512x384.jpg","c":2,"p":0,"r":0.0,"f":false},{"id":17539,"t":"Merge Monster : Pool Party","s":"merge-monster-pool-party","img":"https://img.gamemonetize.com/nxquazeetdxpu5ptojfdc6fabf216f0w/512x384.jpg","c":2,"p":0,"r":0.0,"f":false},{"id":17540,"t":"Copa America 2021","s":"copa-america-2021","img":"https://img.gamemonetize.com/k1orda4ozayeomp9aujirw4yqnuwxebh/512x384.jpg","c":8,"p":0,"r":0.0,"f":false},{"id":17541,"t":"Kiss Sweetly","s":"kiss-sweetly","img":"https://img.gamemonetize.com/98wt09hka9h75svcyzaramaetue07v5g/512x384.jpg","c":8,"p":0,"r":0.0,"f":false},{"id":17542,"t":"Merge To Million","s":"merge-to-million","img":"https://img.gamemonetize.com/it6ed7osx772ofjfxv3dmyaup80z1ykk/512x384.jpg","c":8,"p":0,"r":0.0,"f":false},{"id":17543,"t":"Cut The Rope","s":"cut-the-rope","img":"https://img.gamemonetize.com/0po1nwk3ebjwjsatsj4bpjzceeh72n83/512x384.jpg","c":8,"p":0,"r":0.0,"f":false},{"id":17544,"t":"Stickdoll 2 : Revenge Of Flame","s":"stickdoll-2-revenge-of-flame","img":"https://img.gamemonetize.com/qdjanxft2zdc9plo553j6jirnoat1ahs/512x384.jpg","c":9,"p":0,"r":0.0,"f":false},{"id":17545,"t":"Animal Guys","s":"animal-guys","img":"https://img.gamemonetize.com/mjh2nxm6iy5ndtfc7zxc74lhweyhumzh/512x384.jpg","c":2,"p":0,"r":0.0,"f":false},{"id":17546,"t":"Gotia.io","s":"gotia-io","img":"https://img.gamemonetize.com/8lt2g0nfzyedkpig1jp3b9vag9gvfo7n/512x384.jpg","c":7,"p":0,"r":0.0,"f":false},{"id":17547,"t":"Dora With Wizard In Forest","s":"dora-with-wizard-in-forest","img":"https://img.gamemonetize.com/tq3bv1etph99cw38erv0p644uix858yy/512x384.jpg","c":7,"p":0,"r":0.0,"f":false},{"id":17548,"t":"Wormo.io","s":"wormo-io","img":"https://img.gamemonetize.com/on57ewcv2740i24fbnohytevjs523pcr/512x384.jpg","c":7,"p":0,"r":0.0,"f":false},{"id":17549,"t":"Sonic Runners Adventure","s":"sonic-runners-adventure","img":"https://img.gamemonetize.com/ja5980kzoo751shr8j8j3kdo690xkjw3/512x384.jpg","c":7,"p":0,"r":0.0,"f":false},{"id":17550,"t":"Tom And Jerry In Cooperation","s":"tom-and-jerry-in-cooperation","img":"https://img.gamemonetize.com/kjfskz1lni3fmxdw4vtbd2hlfqv7o5a8/512x384.jpg","c":7,"p":0,"r":0.0,"f":false},{"id":17551,"t":"Bubble Shooter FreeDom","s":"bubble-shooter-freedom","img":"https://img.gamemonetize.com/k56hx2h8vetehtj1sbfo76krvjnm74zs/512x384.jpg","c":3,"p":0,"r":0.0,"f":false},{"id":17552,"t":"Euro 2020 ( 2021 )","s":"euro-2020-2021","img":"https://img.gamemonetize.com/afsdceo148sxpldq92poqda4jnauoe0z/512x384.jpg","c":8,"p":0,"r":0.0,"f":false},{"id":17553,"t":"PirateBattle.io","s":"piratebattle-io","img":"https://img.gamemonetize.com/56638s755x0g6jpzvsdmbc1ixwe5uxyz/512x384.jpg","c":7,"p":0,"r":0.0,"f":false},{"id":17554,"t":"Curling 2021","s":"curling-2021","img":"https://img.gamemonetize.com/aecvqwlouxwubm0p6mw6b4d2xml8sdc3/512x384.jpg","c":8,"p":0,"r":0.0,"f":false},{"id":17555,"t":"Candy Crush Saga King","s":"candy-crush-saga-king","img":"https://img.gamemonetize.com/ushitaltif0ig5by3w54p4cy9sd3yptt/512x384.jpg","c":8,"p":0,"r":0.0,"f":false},{"id":17556,"t":"Stickdoll : God Of Archery","s":"stickdoll-god-of-archery","img":"https://img.gamemonetize.com/s3vbagpvh14v5mxuzpg6u65h5xxr7620/512x384.jpg","c":8,"p":0,"r":0.0,"f":false},{"id":17557,"t":"Wormania.io","s":"wormania-io","img":"https://img.gamemonetize.com/rfcp8f0is0i4llemtxuzea4yvak811zt/512x384.jpg","c":7,"p":0,"r":0.0,"f":false},{"id":17558,"t":"Hair Challenge Online","s":"hair-challenge-online","img":"https://img.gamemonetize.com/dg88zsstw7vu97cxfj8sdxcoeotwgoeu/512x384.jpg","c":4,"p":0,"r":0.0,"f":false},{"id":17559,"t":"BBall Pro League","s":"bball-pro-league","img":"https://img.gamemonetize.com/tqm4go4o17cngyd30xx8f5qbl9opi2ac/512x384.jpg","c":8,"p":0,"r":0.0,"f":false},{"id":17560,"t":"Super Burger 2","s":"super-burger-2","img":"https://img.gamemonetize.com/4bb1yg64im13xl6pu12cz7d22i864489/512x384.jpg","c":8,"p":0,"r":0.0,"f":false},{"id":17561,"t":"Bubble Shooter Party","s":"bubble-shooter-party","img":"https://img.gamemonetize.com/jxu7s4gua7jnjxh6meq8xuuwbw11p8c9/512x384.jpg","c":3,"p":0,"r":0.0,"f":false},{"id":17562,"t":"Subway Surfers Pro2","s":"subway-surfers-pro2","img":"https://img.gamemonetize.com/esv6rh67g7jcv293bm7rlfpdbf5qkv6y/512x384.jpg","c":3,"p":0,"r":0.0,"f":false},{"id":17563,"t":"Mr One Punch: Action Fighting Game","s":"mr-one-punch-action-fighting-game","img":"https://img.gamemonetize.com/eis539n3diu3w1bh203tecnrwnvgn0t2/512x384.jpg","c":1,"p":0,"r":0.0,"f":false},{"id":17564,"t":"Among Arena","s":"among-arena","img":"https://img.gamemonetize.com/szy2u5o29vwi1oe6ce7407ik0ujte0i7/512x384.jpg","c":7,"p":0,"r":0.0,"f":false},{"id":17565,"t":"Imposter Rush 3D","s":"imposter-rush-3d","img":"https://img.gamemonetize.com/sj6gakp06r1vscnn14m4hbhp3pknxuap/512x384.jpg","c":7,"p":0,"r":0.0,"f":false},{"id":17566,"t":"BallRun2048","s":"ballrun2048","img":"https://img.gamemonetize.com/yso6yuyo4enm6vdxz6rdjmyvxrjxo75m/512x384.jpg","c":4,"p":0,"r":0.0,"f":false},{"id":17567,"t":"Bicycle Kick Master","s":"bicycle-kick-master","img":"https://img.gamemonetize.com/oonsdaa12i0e2xf7096c318el03ayh0m/512x384.jpg","c":8,"p":0,"r":0.0,"f":false},{"id":17568,"t":"SuperSpin.io","s":"superspin-io","img":"https://img.gamemonetize.com/2pus16go6pbe4yesrz1q2xpt9nfvxlz0/512x384.jpg","c":7,"p":0,"r":0.0,"f":false},{"id":17569,"t":"Block Puzzles Jewel","s":"block-puzzles-jewel","img":"https://img.gamemonetize.com/bolu221jvu9yj25hbua6xk83c0ofd67o/512x384.jpg","c":7,"p":0,"r":0.0,"f":false},{"id":17570,"t":"Where Is Walter The Wacky Walker","s":"where-is-walter-the-wacky-walker","img":"https://img.gamemonetize.com/baybqm7dsplsbz8ew7eu3j0ujnt7drfp/512x384.jpg","c":7,"p":0,"r":0.0,"f":false},{"id":17571,"t":"Fruit Party","s":"fruit-party","img":"https://img.gamemonetize.com/q44gwsdhfya9ojcdckc912bame38dkf4/512x384.jpg","c":7,"p":0,"r":0.0,"f":false},{"id":17572,"t":"Jelly Fruits","s":"jelly-fruits","img":"https://img.gamemonetize.com/qito6tlr8w74iw2t5q43x5dumpfrvrzl/512x384.jpg","c":7,"p":0,"r":0.0,"f":false},{"id":17573,"t":"Orc Temple Golf","s":"orc-temple-golf","img":"https://img.gamemonetize.com/79tar965cap6yzkzno8dxpi1lejtgyln/512x384.jpg","c":8,"p":0,"r":0.0,"f":false},{"id":17574,"t":"Gold Miner Tom","s":"gold-miner-tom","img":"https://img.gamemonetize.com/z54ksczitgqspapebvx9l3of56dc6dy6/512x384.jpg","c":8,"p":0,"r":0.0,"f":false},{"id":17575,"t":"Color Pixel","s":"color-pixel","img":"https://img.gamemonetize.com/zxt5zmioyarxp0oclwunv6w6jms0mjfl/512x384.jpg","c":8,"p":0,"r":0.0,"f":false},{"id":17576,"t":"Rugby Kicker","s":"rugby-kicker","img":"https://img.gamemonetize.com/f4xw5yf2p23qa2gysfmrhhtkedcgo9d3/512x384.jpg","c":8,"p":0,"r":0.0,"f":false},{"id":17577,"t":"Penguin Dinner","s":"penguin-dinner","img":"https://img.gamemonetize.com/hpziyqzthk9764hzn1m8ra98ff0145nl/512x384.jpg","c":4,"p":0,"r":0.0,"f":false},{"id":17578,"t":"March Madness","s":"march-madness","img":"https://img.gamemonetize.com/114olmnx2sug8fd38ykp54las0cod3af/512x384.jpg","c":8,"p":0,"r":0.0,"f":false},{"id":17579,"t":"Buyoda Sensei Kendo Academy","s":"buyoda-sensei-kendo-academy","img":"https://img.gamemonetize.com/c3fetm57ka7d2i2dn9hxlmbxuflqb39n/512x384.jpg","c":4,"p":0,"r":0.0,"f":false},{"id":17580,"t":"2 Player Among Soccer","s":"2-player-among-soccer","img":"https://img.gamemonetize.com/uoi3pc91mixkykwgdpjn88slj8u7d3z7/512x384.jpg","c":8,"p":0,"r":0.0,"f":false},{"id":17581,"t":"Skate Hooligans","s":"skate-hooligans","img":"https://img.gamemonetize.com/vy07es6s71vci1su3wzcqrp7e3ym0vtw/512x384.jpg","c":4,"p":0,"r":0.0,"f":false},{"id":17582,"t":"Just Fishing","s":"just-fishing","img":"https://img.gamemonetize.com/44cn3lk6w2ok3inoa3oert3mftymo49s/512x384.jpg","c":4,"p":0,"r":0.0,"f":false},{"id":17583,"t":"Super Hero Flip: Spider Stickman Hook","s":"super-hero-flip-spider-stickman-hook","img":"https://img.gamemonetize.com/wbax4rcnbmlrbljmx034rsh57gladdn9/512x384.jpg","c":4,"p":0,"r":0.0,"f":false},{"id":17584,"t":"BattleDudes.io","s":"battledudes-io","img":"https://img.gamemonetize.com/qaf7ryh54m4k9j3e0jhf3z45rzuyugql/512x384.jpg","c":3,"p":0,"r":0.0,"f":false},{"id":17585,"t":"Among Shooter Online","s":"among-shooter-online","img":"https://img.gamemonetize.com/mgjbot6wo0fvpjl8kgjo2v5ypjakty4g/512x384.jpg","c":3,"p":0,"r":0.0,"f":false},{"id":17586,"t":"Among Rescue","s":"among-rescue","img":"https://img.gamemonetize.com/wk7v1rr9u1rkqcobx3zzke5x9nsgfw9b/512x384.jpg","c":3,"p":0,"r":0.0,"f":false},{"id":17587,"t":"Color Rings Online","s":"color-rings-online","img":"https://img.gamemonetize.com/c49at6i05yghmxstys61igxixll79d8m/512x384.jpg","c":3,"p":0,"r":0.0,"f":false},{"id":17588,"t":"Crossy Road","s":"crossy-road","img":"https://img.gamemonetize.com/kpk56rb4da96qc09uhdryivu3g9xbpiw/512x384.jpg","c":3,"p":0,"r":0.0,"f":false},{"id":17589,"t":"Mahjong 3D","s":"mahjong-3d","img":"https://img.gamemonetize.com/ok0eqr2kw4cc3b4ecb09j9v4cidb1smp/512x384.jpg","c":4,"p":0,"r":0.0,"f":false},{"id":17590,"t":"Panda Bubble Shooter game free","s":"panda-bubble-shooter-game-free","img":"https://img.gamemonetize.com/1px3w4wwem3843gs6yvm7yqkiukhhmzj/512x384.jpg","c":4,"p":0,"r":0.0,"f":false},{"id":17591,"t":"Squirrel Bubble Woods","s":"squirrel-bubble-woods","img":"https://img.gamemonetize.com/64l8mh9ewuaju9zq9hgwzytk5xj2a1tg/512x384.jpg","c":4,"p":0,"r":0.0,"f":false},{"id":17592,"t":"Among Us - Impostor King Online","s":"among-us-impostor-king-online","img":"https://img.gamemonetize.com/tfk0or192m2mmii04dnrzidxwfnlez77/512x384.jpg","c":1,"p":0,"r":0.0,"f":false},{"id":17593,"t":"Sprinter 2","s":"sprinter-2","img":"https://img.gamemonetize.com/8e2jzql8m18fl3q30bhx6x11k7wgedtm/512x384.jpg","c":8,"p":0,"r":0.0,"f":false},{"id":17594,"t":"Bear Boom","s":"bear-boom","img":"https://img.gamemonetize.com/krl0tsxuqskqijitov0q6eh3y5cafg4z/512x384.jpg","c":8,"p":0,"r":0.0,"f":false},{"id":17595,"t":"Circle Crush","s":"circle-crush","img":"https://img.gamemonetize.com/fq2da36cwqnr627l22fzklb02rcfa7mq/512x384.jpg","c":8,"p":0,"r":0.0,"f":false},{"id":17596,"t":"Angry Birds Classic","s":"angry-birds-classic","img":"https://img.gamemonetize.com/j8ckmmlaa4hsqknbzbrvft9mqhvfdakx/512x384.jpg","c":4,"p":0,"r":0.0,"f":false},{"id":17597,"t":"Fruit Farm Crush","s":"fruit-farm-crush","img":"https://img.gamemonetize.com/nptfszf0k5ytqixllw2upru8s5wpofmb/512x384.jpg","c":4,"p":0,"r":0.0,"f":false},{"id":17598,"t":"Frozen Rush","s":"frozen-rush","img":"https://img.gamemonetize.com/gbrmujvess2wjg298mjqhu9md3hkfesv/512x384.jpg","c":4,"p":0,"r":0.0,"f":false},{"id":17599,"t":"Quantities","s":"quantities","img":"https://img.gamemonetize.com/pth798uu4j0gilxasyq1y8sd4jpdeqa3/512x384.jpg","c":4,"p":0,"r":0.0,"f":false},{"id":17600,"t":"Tiger Run","s":"tiger-run","img":"https://img.gamemonetize.com/hd2cepvbiqyaxoo6puec9iqxlnc1xwkf/512x384.jpg","c":4,"p":0,"r":0.0,"f":false}]