[{"id":22801,"t":"Car Traffic System","s":"car-traffic-system","img":"https://img.gamemonetize.com/cjtk2rijl72i0ppbq0va34tuqh48o6c0/512x384.jpg","c":2,"p":0,"r":0.0,"f":false},{"id":22802,"t":"Christmas Match 3 Deluxe","s":"christmas-match-3-deluxe","img":"https://img.gamemonetize.com/6h6g8o77jrft6aeyw5w2khdvq8apgjrn/512x384.jpg","c":2,"p":0,"r":0.0,"f":false},{"id":22803,"t":"Dwarf Hero Running","s":"dwarf-hero-running","img":"https://img.gamemonetize.com/gm4n2ptszswqdljo3pjf1zj0487sred7/512x384.jpg","c":2,"p":0,"r":0.0,"f":false},{"id":22804,"t":"Rescue the kangaroo","s":"rescue-the-kangaroo","img":"https://img.gamemonetize.com/okawdhmg6xenfpmlgslwqjmb3vbo3rbr/512x384.jpg","c":2,"p":0,"r":0.0,"f":false},{"id":22805,"t":"Tiny Zombies 2","s":"tiny-zombies-2","img":"https://img.gamemonetize.com/unq7n9we5ej4cw75w6cw4ir0f1f666yp/512x384.jpg","c":3,"p":0,"r":0.0,"f":false},{"id":22806,"t":"Delicious Food Mahjong Connects","s":"delicious-food-mahjong-connects","img":"https://img.gamemonetize.com/2f7e5njjbbh833m20f0izuoeo4lvzl41/512x384.jpg","c":3,"p":0,"r":0.0,"f":false},{"id":22807,"t":"Mad Taxi Driver","s":"mad-taxi-driver","img":"https://img.gamemonetize.com/3cl3sjguql2ahb5g4jfbrv813d3ks5uw/512x384.jpg","c":2,"p":0,"r":0.0,"f":false},{"id":22808,"t":"GN Red Ball","s":"gn-red-ball","img":"https://img.gamemonetize.com/kl47x7zyhxocexq4a2xof2i1go0q1bem/512x384.jpg","c":8,"p":0,"r":0.0,"f":false},{"id":22809,"t":"Fashion Competition Dress up and Makeup Games","s":"fashion-competition-dress-up-and-makeup-games","img":"https://img.gamemonetize.com/w6pqtdymy6z7hm5pmz24d0bn5e1t0x7s/512x384.jpg","c":8,"p":0,"r":0.0,"f":false},{"id":22810,"t":"Butterflies Puzzle","s":"butterflies-puzzle","img":"https://img.gamemonetize.com/b6b4x5cy6lgnemhyw3v0ryfaidhkp5z1/512x384.jpg","c":8,"p":0,"r":0.0,"f":false},{"id":22811,"t":"Ring Game","s":"ring-game","img":"https://img.gamemonetize.com/7doishwmx4e32lpwm5xvljlbxn2pjds3/512x384.jpg","c":8,"p":0,"r":0.0,"f":false},{"id":22812,"t":"Gravity Falls Slide","s":"gravity-falls-slide","img":"https://img.gamemonetize.com/lu11b9jb7u9g888vwt0o9xpr7y3khcr3/512x384.jpg","c":8,"p":0,"r":0.0,"f":false},{"id":22813,"t":"Easter 2020 Differences","s":"easter-2020-differences","img":"https://img.gamemonetize.com/cmmyswcrofqyt8ewjixtwv8o9bpkr4v4/512x384.jpg","c":8,"p":0,"r":0.0,"f":false},{"id":22814,"t":"Winter Warm Up Math","s":"winter-warm-up-math","img":"https://img.gamemonetize.com/x4s84915zzv4wvcgpjdn7z1v35th297r/512x384.jpg","c":8,"p":0,"r":0.0,"f":false},{"id":22815,"t":"Jumping Joe","s":"jumping-joe","img":"https://img.gamemonetize.com/wg3xp1ythsjeicpxveajwtkcludl7zgq/512x384.jpg","c":8,"p":0,"r":0.0,"f":false},{"id":22816,"t":"Boxers in Arena","s":"boxers-in-arena","img":"https://img.gamemonetize.com/kwmcq05p64jr5vpxzgy33k3qe8iu3d5o/512x384.jpg","c":8,"p":0,"r":0.0,"f":false},{"id":22817,"t":"Kart Slide","s":"kart-slide","img":"https://img.gamemonetize.com/leoxvfnhg3gnpevus2nt58cxs9487f9t/512x384.jpg","c":8,"p":0,"r":0.0,"f":false},{"id":22818,"t":"2020 Arch KRGT-1 Slide","s":"2020-arch-krgt-1-slide","img":"https://img.gamemonetize.com/08y363eln9waib57lywm4n7f0zyqc86d/512x384.jpg","c":8,"p":0,"r":0.0,"f":false},{"id":22819,"t":"Plane War 1941","s":"plane-war-1941","img":"https://img.gamemonetize.com/d06cilxx60xzl8suq7uperctmohlpil3/512x384.jpg","c":3,"p":0,"r":0.0,"f":false},{"id":22820,"t":"T-Rex Dinosaur Jigsaw","s":"t-rex-dinosaur-jigsaw","img":"https://img.gamemonetize.com/tg11a4y7wp5mcnu7xe6zyyxl6iopbnp4/512x384.jpg","c":3,"p":0,"r":0.0,"f":false},{"id":22821,"t":"Shapes Jigsaw Insects","s":"shapes-jigsaw-insects","img":"https://img.gamemonetize.com/7vo0xhsnpr1hvpo15u55s7auirldnkdv/512x384.jpg","c":3,"p":0,"r":0.0,"f":false},{"id":22822,"t":"Reversi   Othello","s":"reversi-othello","img":"https://img.gamemonetize.com/b8d00b6t3j7njqnoco01vzzq4cp70b8b/512x384.jpg","c":3,"p":0,"r":0.0,"f":false},{"id":22823,"t":"Snow Mountain Snowboard","s":"snow-mountain-snowboard","img":"https://img.gamemonetize.com/zx881n5auqqueiuz1mxjk165cxkhh2jh/512x384.jpg","c":8,"p":0,"r":0.0,"f":false},{"id":22824,"t":"Tripolygon","s":"tripolygon","img":"https://img.gamemonetize.com/dv63wh581re1i2uufnso0dl6xrlu9x4m/512x384.jpg","c":8,"p":0,"r":0.0,"f":false},{"id":22825,"t":"Intersection Chaos","s":"intersection-chaos","img":"https://img.gamemonetize.com/h4n2gk88ac4wi39h4blsvq2p2gkzdeeu/512x384.jpg","c":8,"p":0,"r":0.0,"f":false},{"id":22826,"t":"Mickey Mouse Match3","s":"mickey-mouse-match3","img":"https://img.gamemonetize.com/dzhsa4eea2gxaakoevfhsgnbz29lwdoa/512x384.jpg","c":8,"p":0,"r":0.0,"f":false},{"id":22827,"t":"Amazeballs Estate Escape","s":"amazeballs-estate-escape","img":"https://img.gamemonetize.com/0ep78lrtkpslxf2kxpw7n0uj7jcl1bl1/512x384.jpg","c":8,"p":0,"r":0.0,"f":false},{"id":22828,"t":"Untangle","s":"untangle","img":"https://img.gamemonetize.com/c59apa7bwfatur8b3cohric6k5yf7slj/512x384.jpg","c":8,"p":0,"r":0.0,"f":false},{"id":22829,"t":"HardFlex: The Last Flex","s":"hardflex-the-last-flex","img":"https://img.gamemonetize.com/7zgdizluuupr2sk5fk81pnn8nqxz8dzf/512x384.jpg","c":8,"p":0,"r":0.0,"f":false},{"id":22830,"t":"Retro Tiny Tennis","s":"retro-tiny-tennis","img":"https://img.gamemonetize.com/l5i1t3twy4zbyrv0u7dktn4jyigw89zv/512x384.jpg","c":8,"p":0,"r":0.0,"f":false},{"id":22831,"t":"Little Archer","s":"little-archer","img":"https://img.gamemonetize.com/t61ljzpluulgeb4wk72zqo5ev3jqm3mg/512x384.jpg","c":4,"p":0,"r":0.0,"f":false},{"id":22832,"t":"Christmas Klondike Solitaire","s":"christmas-klondike-solitaire","img":"https://img.gamemonetize.com/nec2satwcl98s5rzw882mpofnijkkmk8/512x384.jpg","c":4,"p":0,"r":0.0,"f":false},{"id":22833,"t":"Hunter Boy Escape","s":"hunter-boy-escape","img":"https://img.gamemonetize.com/2hj3of4kn4y0j4yjcmd584fj7czkfuki/512x384.jpg","c":4,"p":0,"r":0.0,"f":false},{"id":22834,"t":"Warrior And Beast","s":"warrior-and-beast","img":"https://img.gamemonetize.com/hg9h8lx94tre5wfwpwa2mz7cn5rv5cg1/512x384.jpg","c":4,"p":0,"r":0.0,"f":false},{"id":22835,"t":"Cute Cars Puzzle","s":"cute-cars-puzzle","img":"https://img.gamemonetize.com/tnhpytihxhlm3du56xk2xpotlupeymjs/512x384.jpg","c":4,"p":0,"r":0.0,"f":false},{"id":22836,"t":"Foody Triple Mahjong","s":"foody-triple-mahjong","img":"https://img.gamemonetize.com/cb8k6j0ezewli6bnxrwu3bjnbcrfxyg9/512x384.jpg","c":4,"p":0,"r":0.0,"f":false},{"id":22837,"t":"Alien Defense 1","s":"alien-defense-1","img":"https://img.gamemonetize.com/bmesbip6eprsyusavtyeuuvhxiwxvms6/512x384.jpg","c":3,"p":0,"r":0.0,"f":false},{"id":22838,"t":"Beauty Manicure Salon","s":"beauty-manicure-salon","img":"https://img.gamemonetize.com/jsi40x2yy6lcutfkgedzyz38tzthwmkg/512x384.jpg","c":3,"p":0,"r":0.0,"f":false},{"id":22839,"t":"Helicopter Puzzle","s":"helicopter-puzzle","img":"https://img.gamemonetize.com/os0qscy50cdsub3mq3ymowq4f1sea32z/512x384.jpg","c":3,"p":0,"r":0.0,"f":false},{"id":22840,"t":"Princesses First Days Of College","s":"princesses-first-days-of-college","img":"https://img.gamemonetize.com/62phn3nrzyvxmuesw09xfqnr2bptodl4/512x384.jpg","c":3,"p":0,"r":0.0,"f":false},{"id":22841,"t":"Girl Adventurer","s":"girl-adventurer","img":"https://img.gamemonetize.com/ja84q98j84e0eoe9zu8cc1ai7yc22s0m/512x384.jpg","c":3,"p":0,"r":0.0,"f":false},{"id":22842,"t":"Square Clicker","s":"square-clicker","img":"https://img.gamemonetize.com/xvizxtlibqz0hahektj8cngv48k0iu3f/512x384.jpg","c":3,"p":0,"r":0.0,"f":false},{"id":22843,"t":"Tap Tap Robot","s":"tap-tap-robot","img":"https://img.gamemonetize.com/iscbvk6ykcsp9dxy085lx8utcyu5h3jz/512x384.jpg","c":3,"p":0,"r":0.0,"f":false},{"id":22844,"t":"Amgel Halloween Room Escape 23","s":"amgel-halloween-room-escape-23","img":"https://img.gamemonetize.com/fscv3jad93ge9yx06tnch46bhqbc72vs/512x384.jpg","c":3,"p":0,"r":0.0,"f":false},{"id":22845,"t":"Crazy Mexican Coloring Book","s":"crazy-mexican-coloring-book","img":"https://img.gamemonetize.com/gkj8xxzxbkyhhciu5hq2ldhwqjtk7gvn/512x384.jpg","c":3,"p":0,"r":0.0,"f":false},{"id":22846,"t":"Kart Karting Slide","s":"kart-karting-slide","img":"https://img.gamemonetize.com/bax6vlwwd62k8kngeiu6ded06b33jgeu/512x384.jpg","c":3,"p":0,"r":0.0,"f":false},{"id":22847,"t":"Extermination of Flies","s":"extermination-of-flies","img":"https://img.gamemonetize.com/pv53xvubcwt5xx9ke1k5cm2jz1a09hsz/512x384.jpg","c":3,"p":0,"r":0.0,"f":false},{"id":22848,"t":"Skeletons Funny Jigsaw","s":"skeletons-funny-jigsaw","img":"https://img.gamemonetize.com/oz4xouifqdaf22w4yurx8kt1g90jxokl/512x384.jpg","c":3,"p":0,"r":0.0,"f":false},{"id":22849,"t":"Jump In The Circle","s":"jump-in-the-circle","img":"https://img.gamemonetize.com/q4v5i3fjqdfaidn1t7vaw8i1teeyd964/512x384.jpg","c":3,"p":0,"r":0.0,"f":false},{"id":22850,"t":"Sweet Candy Challenge Time","s":"sweet-candy-challenge-time","img":"https://img.gamemonetize.com/8p5lyfymvjlk3pqrt2ea3pdaixjqivjq/512x384.jpg","c":3,"p":0,"r":0.0,"f":false},{"id":22851,"t":"CAR MISSILE","s":"car-missile","img":"https://img.gamemonetize.com/khb1lfxqnl5qc1yka7hxia8q5vl84nxu/512x384.jpg","c":4,"p":0,"r":0.0,"f":false},{"id":22852,"t":"Snake and Ladders Game","s":"snake-and-ladders-game","img":"https://img.gamemonetize.com/o6zmu17puuwdmj37p2vhsto4xib0wg3k/512x384.jpg","c":4,"p":0,"r":0.0,"f":false},{"id":22853,"t":"Super lol surprise dolls adventure run","s":"super-lol-surprise-dolls-adventure-run","img":"https://img.gamemonetize.com/ke0eg845t9ct559zg9da2azaegpkv9gf/512x384.jpg","c":4,"p":0,"r":0.0,"f":false},{"id":22854,"t":"Speed Car Racer in Traffic","s":"speed-car-racer-in-traffic","img":"https://img.gamemonetize.com/uf50vou2kmgy9t6gphu3mgcj4yhhw3nq/512x384.jpg","c":2,"p":0,"r":0.0,"f":false},{"id":22855,"t":"Pick-a-Path The Loud House","s":"pick-a-path-the-loud-house","img":"https://img.gamemonetize.com/7y8sly7undojv13zzsu9l2ggmdq3cdpv/512x384.jpg","c":2,"p":0,"r":0.0,"f":false},{"id":22856,"t":"Car Wash Hidden","s":"car-wash-hidden","img":"https://img.gamemonetize.com/yo4myk4m75e6qqbw84pxqp0z8ex1k3ei/512x384.jpg","c":2,"p":0,"r":0.0,"f":false},{"id":22857,"t":"No Driver Parking","s":"no-driver-parking","img":"https://img.gamemonetize.com/v40u98ern9wd76pkllqeu6mje1ywuewp/512x384.jpg","c":2,"p":0,"r":0.0,"f":false},{"id":22858,"t":"Unicorn Run","s":"unicorn-run","img":"https://img.gamemonetize.com/dgg4g75d0bnum1jtcn2lpj20zuzdp2t3/512x384.jpg","c":2,"p":0,"r":0.0,"f":false},{"id":22859,"t":"Cowboy Escape Desert","s":"cowboy-escape-desert","img":"https://img.gamemonetize.com/d0nj5a6rab5xq8vadh5wai7jk1wqk16x/512x384.jpg","c":2,"p":0,"r":0.0,"f":false},{"id":22860,"t":"Snack Rush","s":"snack-rush","img":"https://img.gamemonetize.com/3evu6b4n6trg0m3maxejmn4tvy8kbf7f/512x384.jpg","c":8,"p":0,"r":0.0,"f":false},{"id":22861,"t":"Fit  amp;amp; Go - Shape Puzzle","s":"fit-go-shape-puzzle","img":"https://img.gamemonetize.com/49kim71k9ei5084diqx8cb5dmq6nwax0/512x384.jpg","c":8,"p":0,"r":0.0,"f":false},{"id":22862,"t":"Sudoku Classic","s":"sudoku-classic","img":"https://img.gamemonetize.com/y1to1v08tmqbc8r07spw8x6bqq4ql5qj/512x384.jpg","c":8,"p":0,"r":0.0,"f":false},{"id":22863,"t":"Cat And Kids Differences","s":"cat-and-kids-differences","img":"https://img.gamemonetize.com/js347jx6s4x4jclh0m6xgnfyrxtmpaa8/512x384.jpg","c":8,"p":0,"r":0.0,"f":false},{"id":22864,"t":"Cuban Vintage Cars Jigsaw","s":"cuban-vintage-cars-jigsaw","img":"https://img.gamemonetize.com/kcybzgr5axu9teib1fbf05l3w9ntl046/512x384.jpg","c":8,"p":0,"r":0.0,"f":false},{"id":22865,"t":"Metal Robot Puzzle","s":"metal-robot-puzzle","img":"https://img.gamemonetize.com/h9fkfikb6qidzitozfe1chv9twfb12nj/512x384.jpg","c":8,"p":0,"r":0.0,"f":false},{"id":22866,"t":"Baby Hazel Pet Doctor","s":"baby-hazel-pet-doctor","img":"https://img.gamemonetize.com/zhwowcp5wbl3fwpdnke9ucbtb5dg8rv8/512x384.jpg","c":8,"p":0,"r":0.0,"f":false},{"id":22867,"t":"Girls and Cars Slide","s":"girls-and-cars-slide","img":"https://img.gamemonetize.com/xkybktbclj9uagb43m2t14y75lxq8t75/512x384.jpg","c":8,"p":0,"r":0.0,"f":false},{"id":22868,"t":"Karate Sunset Warriors","s":"karate-sunset-warriors","img":"https://img.gamemonetize.com/bxgrh5u078f5mg5ewknf8okildz0480g/512x384.jpg","c":8,"p":0,"r":0.0,"f":false},{"id":22869,"t":"Gate Rusher","s":"gate-rusher","img":"https://img.gamemonetize.com/v7gm3c8vljfctj24xy1cmwmx2jwmj6ee/512x384.jpg","c":8,"p":0,"r":0.0,"f":false},{"id":22870,"t":"Mazda 3 Sedan Puzzle","s":"mazda-3-sedan-puzzle","img":"https://img.gamemonetize.com/3lh60x55f5uq422837rtqg9zhdxcjgcn/512x384.jpg","c":8,"p":0,"r":0.0,"f":false},{"id":22871,"t":"Impossible Platform Game","s":"impossible-platform-game","img":"https://img.gamemonetize.com/gvl4553722fulzws7vswgmi6800k3lmk/512x384.jpg","c":8,"p":0,"r":0.0,"f":false},{"id":22872,"t":"Football Flick","s":"football-flick","img":"https://img.gamemonetize.com/necs6mnhw2igl2f96padhtfjc4gyhyz4/512x384.jpg","c":8,"p":0,"r":0.0,"f":false},{"id":22873,"t":"Pirates Treasure","s":"pirates-treasure","img":"https://img.gamemonetize.com/usy7tg5i4pw64itjf7kbksonp60c5ypz/512x384.jpg","c":8,"p":0,"r":0.0,"f":false},{"id":22874,"t":"Squid Game Challenge Battle 3D","s":"squid-game-challenge-battle-3d","img":"https://img.gamemonetize.com/wl2wrd1ybyz8fb6olsahvpdqnyir7etd/512x384.jpg","c":8,"p":0,"r":0.0,"f":false},{"id":22875,"t":"1010 Halloween","s":"1010-halloween","img":"https://img.gamemonetize.com/y7odw49emkkfof2r6p0hepflfp7hacoh/512x384.jpg","c":8,"p":0,"r":0.0,"f":false},{"id":22876,"t":"Line Color 3d Squid Game Color Adventure","s":"line-color-3d-squid-game-color-adventure","img":"https://img.gamemonetize.com/tyycl4ftqi2t4hu4oiv5ur2dur21pkey/512x384.jpg","c":8,"p":0,"r":0.0,"f":false},{"id":22877,"t":"Owl Styles Jigsaw","s":"owl-styles-jigsaw","img":"https://img.gamemonetize.com/b4nwztgpg33iwc3ruubrr3cd01k7al7m/512x384.jpg","c":8,"p":0,"r":0.0,"f":false},{"id":22878,"t":"Lovely Christmas Toys Puzzle","s":"lovely-christmas-toys-puzzle","img":"https://img.gamemonetize.com/thgrnz7ecmtsmjbhfvdwakopanj1vh8p/512x384.jpg","c":8,"p":0,"r":0.0,"f":false},{"id":22879,"t":"HTML5 Parking Car","s":"html5-parking-car","img":"https://img.gamemonetize.com/4ynpg8qokk8483984z658mdddoscwm10/512x384.jpg","c":2,"p":0,"r":0.0,"f":false},{"id":22880,"t":"Squid Game Run","s":"squid-game-run","img":"https://img.gamemonetize.com/se5boz97o5crfeapnoyfhvvyte7nc52a/512x384.jpg","c":4,"p":0,"r":0.0,"f":false},{"id":22881,"t":"Which Is Different Halloween","s":"which-is-different-halloween","img":"https://img.gamemonetize.com/hzrzmb6763oi0mw4as8cdahjytgrqzr8/512x384.jpg","c":4,"p":0,"r":0.0,"f":false},{"id":22882,"t":"A Penguin Love","s":"a-penguin-love","img":"https://img.gamemonetize.com/15j6d20t1bivacw72kg12tpujttj63y8/512x384.jpg","c":4,"p":0,"r":0.0,"f":false},{"id":22883,"t":"Hidden Objects Insects","s":"hidden-objects-insects","img":"https://img.gamemonetize.com/cig3nyneyy4uexf731rfdbl80wo4rt44/512x384.jpg","c":4,"p":0,"r":0.0,"f":false},{"id":22884,"t":"Pig Family Jigsaw","s":"pig-family-jigsaw","img":"https://img.gamemonetize.com/g8kkpz4tmqjjb3p7q2nn65ff62zdy04f/512x384.jpg","c":4,"p":0,"r":0.0,"f":false},{"id":22885,"t":"HoneyDrop","s":"honeydrop","img":"https://img.gamemonetize.com/y13zpununnmw36g7bqjixqrpmxnvffed/512x384.jpg","c":4,"p":0,"r":0.0,"f":false},{"id":22886,"t":"Les Trolls Coloring Book","s":"les-trolls-coloring-book","img":"https://img.gamemonetize.com/zq1zq9fbo9rqm7h38o3o2gm2055dusz0/512x384.jpg","c":4,"p":0,"r":0.0,"f":false},{"id":22887,"t":"The Simpsons Jigsaw Puzzle","s":"the-simpsons-jigsaw-puzzle","img":"https://img.gamemonetize.com/24i7olujrardpmq0bt5nwyakv8i4pm4r/512x384.jpg","c":4,"p":0,"r":0.0,"f":false},{"id":22888,"t":"Color And Numbers","s":"color-and-numbers","img":"https://img.gamemonetize.com/mj6qcqat1umkqkkl31q2o1t0jeb7xgq6/512x384.jpg","c":4,"p":0,"r":0.0,"f":false},{"id":22889,"t":"Brooder House Escape","s":"brooder-house-escape","img":"https://img.gamemonetize.com/rkzmhs28sx3nl2z53mxcfr2yrlbukjvc/512x384.jpg","c":4,"p":0,"r":0.0,"f":false},{"id":22890,"t":"Stan The Man","s":"stan-the-man","img":"https://img.gamemonetize.com/1na0yvbtljebf4do3o695s39mlwqiu9k/512x384.jpg","c":3,"p":0,"r":0.0,"f":false},{"id":22891,"t":"Jail Drop","s":"jail-drop","img":"https://img.gamemonetize.com/z3urkmn3w3h0frx1up2d3gxgphatdeln/512x384.jpg","c":3,"p":0,"r":0.0,"f":false},{"id":22892,"t":"Flappier Bat","s":"flappier-bat","img":"https://img.gamemonetize.com/tt8j3ye6va2d8z7cqpmokvp3t596ws6p/512x384.jpg","c":3,"p":0,"r":0.0,"f":false},{"id":22893,"t":"Night Dress","s":"night-dress","img":"https://img.gamemonetize.com/9oigppnph07qvn2ic1xahyc07rkw0rd9/512x384.jpg","c":3,"p":0,"r":0.0,"f":false},{"id":22894,"t":"Pull Him Out","s":"pull-him-out","img":"https://img.gamemonetize.com/66qcgqu8ofu8b6zgj3amq7y5vdl48r5f/512x384.jpg","c":3,"p":0,"r":0.0,"f":false},{"id":22895,"t":"Work Desk Difference","s":"work-desk-difference","img":"https://img.gamemonetize.com/oxk73nwtgor5ffw915jujhr7wvd0jr27/512x384.jpg","c":3,"p":0,"r":0.0,"f":false},{"id":22896,"t":"Bike Racing Math","s":"bike-racing-math","img":"https://img.gamemonetize.com/h9jekbukthcw1wfq8zxsnscxk8pd10hs/512x384.jpg","c":2,"p":0,"r":0.0,"f":false},{"id":22897,"t":"Desert Shooter","s":"desert-shooter","img":"https://img.gamemonetize.com/jzx7qu9j1lmubl0t1mgeb9zjkcv6ksb3/512x384.jpg","c":3,"p":0,"r":0.0,"f":false},{"id":22898,"t":"Mouse Key","s":"mouse-key","img":"https://img.gamemonetize.com/ru3vxgy6d1hoay4imzalnromuf9rxmsp/512x384.jpg","c":3,"p":0,"r":0.0,"f":false},{"id":22899,"t":"Bubble Shooter Candy Popper","s":"bubble-shooter-candy-popper","img":"https://img.gamemonetize.com/uuzuw3iti1f7engskkcq2zmbh9i4kx2f/512x384.jpg","c":3,"p":0,"r":0.0,"f":false},{"id":22900,"t":"Baby Hazel Birthday Party","s":"baby-hazel-birthday-party","img":"https://img.gamemonetize.com/b2q64yqjo1gqu2tz11e7yg5cgx35yws9/512x384.jpg","c":3,"p":0,"r":0.0,"f":false}]