[{"id":2100,"t":"Parkour Blockcraft","s":"parkour-blockcraft","img":"https://img.gamemonetize.com/7bpo1yed3hi1p1jdodkfjeqs8du9wbae/512x384.jpg","c":1,"p":0,"r":0.0,"f":false},{"id":2101,"t":"Geometry Dash Maze Maps","s":"geometry-dash-maze-maps","img":"https://img.gamemonetize.com/m0f68pr59l5jbq3e4mgsi3dlq83c0wgs/512x384.jpg","c":4,"p":0,"r":0.0,"f":false},{"id":2102,"t":"Santa Fright Night","s":"santa-fright-night","img":"https://img.gamemonetize.com/bsnf1x48jp6u582h18ggyiogra8a67bt/512x384.jpg","c":5,"p":0,"r":0.0,"f":false},{"id":2103,"t":"Relax Bubble Shooter","s":"relax-bubble-shooter","img":"https://img.gamemonetize.com/5g511z49pcxiibi6zof88l2nosclaef8/512x384.jpg","c":5,"p":0,"r":0.0,"f":false},{"id":2104,"t":"Spa Salon Makeup Artist","s":"spa-salon-makeup-artist","img":"https://img.gamemonetize.com/w7jo7xkse7d0309wu5g8xjvvsugm0plb/512x384.jpg","c":5,"p":0,"r":0.0,"f":false},{"id":2105,"t":"Sweet Cotton Candy Maker","s":"sweet-cotton-candy-maker","img":"https://img.gamemonetize.com/duay2vzk328wwhrufwowb0gy5nlqvql2/512x384.jpg","c":5,"p":0,"r":0.0,"f":false},{"id":2106,"t":"Christmas N Tiles","s":"christmas-n-tiles","img":"https://img.gamemonetize.com/iwvh7551p26t7zopgmiq59bmwd65hlra/512x384.jpg","c":5,"p":0,"r":0.0,"f":false},{"id":2107,"t":"Archer Castle","s":"archer-castle","img":"https://img.gamemonetize.com/4bqi0lez8o1hpw6b17v853rw4q0axxx8/512x384.jpg","c":5,"p":0,"r":0.0,"f":false},{"id":2108,"t":"Princess Winter Ice Skating Outfits","s":"princess-winter-ice-skating-outfits","img":"https://img.gamemonetize.com/7365b4b7lpwr6la6h6476i6v8e5ep2nu/512x384.jpg","c":5,"p":0,"r":0.0,"f":false},{"id":2109,"t":"Cover Dance NY Party","s":"cover-dance-ny-party","img":"https://img.gamemonetize.com/968q3oos72nqzhi7ajs03sl9hj6awa9z/512x384.jpg","c":5,"p":0,"r":0.0,"f":false},{"id":2110,"t":"Xmas Mahjong Trio Solitaire","s":"xmas-mahjong-trio-solitaire","img":"https://img.gamemonetize.com/epdrb1yla4fjg4vrinle4t2nz1uayc68/512x384.jpg","c":5,"p":0,"r":0.0,"f":false},{"id":2111,"t":"BTS Chibi Claw Machine","s":"bts-chibi-claw-machine","img":"https://img.gamemonetize.com/fj3z2wrx3tgykilfkqqhc3df8l0phmkf/512x384.jpg","c":5,"p":0,"r":0.0,"f":false},{"id":2112,"t":"The Day of Zombies","s":"the-day-of-zombies","img":"https://img.gamemonetize.com/lr3qt0rzp8b8f97atvaiut5as8m4icfy/512x384.jpg","c":3,"p":0,"r":0.0,"f":false},{"id":2113,"t":"Amazing Digital Runner Circus","s":"amazing-digital-runner-circus","img":"https://img.gamemonetize.com/cnjyikth6ycyq1f2twv2iy4j0nu33vca/512x384.jpg","c":3,"p":0,"r":0.0,"f":false},{"id":2114,"t":"Runner Slapper","s":"runner-slapper","img":"https://img.gamemonetize.com/83jde18i3v6k79vj5x38gj5o7vulx7s5/512x384.jpg","c":4,"p":0,"r":0.0,"f":false},{"id":2115,"t":"Santa Claus Christmas Clicker","s":"santa-claus-christmas-clicker","img":"https://img.gamemonetize.com/vntca79wbugqa49us2g7rwg9u4aw6438/512x384.jpg","c":5,"p":0,"r":0.0,"f":false},{"id":2116,"t":"Match Card","s":"match-card","img":"https://img.gamemonetize.com/h3heboxsl4hsd2ot943kclmwsxinbpbj/512x384.jpg","c":5,"p":0,"r":0.0,"f":false},{"id":2117,"t":"Fruity Cubes Island","s":"fruity-cubes-island","img":"https://img.gamemonetize.com/7k9wdweu8k06v2fcv5dn2labv4xm2g50/512x384.jpg","c":5,"p":0,"r":0.0,"f":false},{"id":2118,"t":"Strike Galaxy Attack","s":"strike-galaxy-attack","img":"https://img.gamemonetize.com/5qoll80lcrsvumk53nurp6e1j40djm16/512x384.jpg","c":3,"p":0,"r":0.0,"f":false},{"id":2119,"t":"Parkour Craft Noob Steve","s":"parkour-craft-noob-steve","img":"https://img.gamemonetize.com/8mkc1eq0noitttklorxjpoe5epn9mafv/512x384.jpg","c":3,"p":0,"r":0.0,"f":false},{"id":2120,"t":"MushroomTarzan","s":"mushroomtarzan","img":"https://img.gamemonetize.com/dcms4he5bsr6jqp7zbn2wfyp2x2rx6ws/512x384.jpg","c":3,"p":0,"r":0.0,"f":false},{"id":2121,"t":"Digital Circus Tower Runner","s":"digital-circus-tower-runner","img":"https://img.gamemonetize.com/6gibkzz93u3ojuwcr6ddtfkr21bjioqq/512x384.jpg","c":4,"p":0,"r":0.0,"f":false},{"id":2122,"t":"Digital Circus Coloring Adventure","s":"digital-circus-coloring-adventure","img":"https://img.gamemonetize.com/io5a53tylbaxk9pgnlebqwrvmomidzgv/512x384.jpg","c":4,"p":0,"r":0.0,"f":false},{"id":2123,"t":"Duel Time","s":"duel-time","img":"https://img.gamemonetize.com/fh2qwe2glfh2n9pqdo995mi1p8fe66ch/512x384.jpg","c":1,"p":0,"r":0.0,"f":false},{"id":2124,"t":"Funny Mad Racing","s":"funny-mad-racing","img":"https://img.gamemonetize.com/oba2cgdvjemwvvloq5rnjr4ej7wjtksr/512x384.jpg","c":2,"p":0,"r":0.0,"f":false},{"id":2125,"t":"Infinity Zoom Art","s":"infinity-zoom-art","img":"https://img.gamemonetize.com/gcr9v0wvz6s9zy4b4w1zcoz9wf3hoy7p/512x384.jpg","c":2,"p":0,"r":0.0,"f":false},{"id":2126,"t":"Hidden Car Tires","s":"hidden-car-tires","img":"https://img.gamemonetize.com/q0tp0bykd4lmzj104i7yobr69i5he9kv/512x384.jpg","c":5,"p":0,"r":0.0,"f":false},{"id":2127,"t":"Pets Grooming Bubble Party","s":"pets-grooming-bubble-party","img":"https://img.gamemonetize.com/noy64das3607igtjtd2auk3eptzoyjb2/512x384.jpg","c":5,"p":0,"r":0.0,"f":false},{"id":2128,"t":"Baby Panda Handmade Crafts","s":"baby-panda-handmade-crafts","img":"https://img.gamemonetize.com/msdt6mfh6vk2nv7yp0n6ng6hlh4eart0/512x384.jpg","c":5,"p":0,"r":0.0,"f":false},{"id":2129,"t":"Circle Shooter Master","s":"circle-shooter-master","img":"https://img.gamemonetize.com/a858jiqhd9wu39oh88ckoc8alcydiw4k/512x384.jpg","c":1,"p":0,"r":0.0,"f":false},{"id":2130,"t":"Parking Jam Delivery Traffic","s":"parking-jam-delivery-traffic","img":"https://img.gamemonetize.com/2m5wywysh674dh6wstym87iazvsftblg/512x384.jpg","c":5,"p":0,"r":0.0,"f":false},{"id":2131,"t":"Rescue Girl","s":"rescue-girl","img":"https://img.gamemonetize.com/p6g9mx5rh65xml5zwbhrxp1rn5v0qmfk/512x384.jpg","c":5,"p":0,"r":0.0,"f":false},{"id":2132,"t":"Little Pandas Match 3","s":"little-pandas-match-3","img":"https://img.gamemonetize.com/fiv9vcdaweimf34cvzfwsj2l0poc7jyo/512x384.jpg","c":5,"p":0,"r":0.0,"f":false},{"id":2133,"t":"Space Bubble Pop","s":"space-bubble-pop","img":"https://img.gamemonetize.com/1t1esp2sc2pj1t09q84frvi97tvdcjlm/512x384.jpg","c":5,"p":0,"r":0.0,"f":false},{"id":2134,"t":"Sisters Decorate Bedroom","s":"sisters-decorate-bedroom","img":"https://img.gamemonetize.com/tryczneey2fqd30krlsv5ac8a8iqvqv4/512x384.jpg","c":5,"p":0,"r":0.0,"f":false},{"id":2135,"t":"Digital Circus Hide And Seek","s":"digital-circus-hide-and-seek","img":"https://img.gamemonetize.com/6c2s2pyxe65icdkse5t4svr0ihact3yi/512x384.jpg","c":1,"p":0,"r":0.0,"f":false},{"id":2136,"t":"Kikis Pink Christmas","s":"kikis-pink-christmas","img":"https://img.gamemonetize.com/xxkdcpukrrcue21soja473ucbnvfywjb/512x384.jpg","c":1,"p":0,"r":0.0,"f":false},{"id":2137,"t":"Baby Daily Habits","s":"baby-daily-habits","img":"https://img.gamemonetize.com/1gdpin5necb0pgiqj45j66d9w2uxw2zv/512x384.jpg","c":1,"p":0,"r":0.0,"f":false},{"id":2138,"t":"Santa Wheel","s":"santa-wheel","img":"https://img.gamemonetize.com/0p476c7wysv8iw8m1hmb0ktfw7zfx3ef/512x384.jpg","c":5,"p":0,"r":0.0,"f":false},{"id":2139,"t":"Cube Loop Jumper","s":"cube-loop-jumper","img":"https://img.gamemonetize.com/lt7ps1cfcysgcqjr8764qhlmedqxkn7u/512x384.jpg","c":4,"p":0,"r":0.0,"f":false},{"id":2140,"t":"AntiVirus / War Virus","s":"antivirus-war-virus","img":"https://img.gamemonetize.com/hrm17c127o6nlljqcmc8lokhtpyh07xc/512x384.jpg","c":4,"p":0,"r":0.0,"f":false},{"id":2141,"t":"CrossPath","s":"crosspath","img":"https://img.gamemonetize.com/hjn6mi6xhbc9g1ywv4nzxfqyihtkdiji/512x384.jpg","c":5,"p":0,"r":0.0,"f":false},{"id":2142,"t":"Frosty Connection Quest","s":"frosty-connection-quest","img":"https://img.gamemonetize.com/2zyan5wbwo9ekiujs51mqemyt8v32xar/512x384.jpg","c":5,"p":0,"r":0.0,"f":false},{"id":2143,"t":"Demolition Car Online","s":"demolition-car-online","img":"https://img.gamemonetize.com/t278lhv8eun90v8stxwuzrjhnyfghsia/512x384.jpg","c":5,"p":0,"r":0.0,"f":false},{"id":2144,"t":"Geometry Stack 2048 Run","s":"geometry-stack-2048-run","img":"https://img.gamemonetize.com/rjqphfn4bxgjze4lnto0i6a70fzk2r5x/512x384.jpg","c":4,"p":0,"r":0.0,"f":false},{"id":2145,"t":"Math Puzzles CLG","s":"math-puzzles-clg","img":"https://img.gamemonetize.com/tylzpz6yzt29mc6ixd4omj5opo9h7c7o/512x384.jpg","c":5,"p":0,"r":0.0,"f":false},{"id":2146,"t":"Blob Bridge Run","s":"blob-bridge-run","img":"https://img.gamemonetize.com/52h628dmeiaqe7e12qy0m76aafslkpr1/512x384.jpg","c":2,"p":0,"r":0.0,"f":false},{"id":2147,"t":"Happy Kids Jigsaw","s":"happy-kids-jigsaw","img":"https://img.gamemonetize.com/x0sm56p0trsxjuknqjxwq4phlk305t0t/512x384.jpg","c":5,"p":0,"r":0.0,"f":false},{"id":2148,"t":"Santa Flight Game","s":"santa-flight-game","img":"https://img.gamemonetize.com/zxyubxptcimejvgebqja9oxjnxzr1tfu/512x384.jpg","c":5,"p":0,"r":0.0,"f":false},{"id":2149,"t":"Mini Grand Thef City","s":"mini-grand-thef-city","img":"https://img.gamemonetize.com/3io73p9kwkkyxwssbkxzsngkh34vpenv/512x384.jpg","c":5,"p":0,"r":0.0,"f":false},{"id":2150,"t":"Space Room Escape","s":"space-room-escape","img":"https://img.gamemonetize.com/kic8zqy4xj0m8nxonv0ehy64w4b38rer/512x384.jpg","c":5,"p":0,"r":0.0,"f":false},{"id":2151,"t":"Infantry Attack:Battle 3D FPS","s":"infantry-attack-battle-3d-fps","img":"https://img.gamemonetize.com/foof3euvtu1r928pcec4j0vtslnqqqy6/512x384.jpg","c":3,"p":0,"r":0.0,"f":false},{"id":2152,"t":"Kids Dentist Games","s":"kids-dentist-games","img":"https://img.gamemonetize.com/z892ltdezy2ykev9141k0suz58fee4kq/512x384.jpg","c":3,"p":0,"r":0.0,"f":false},{"id":2153,"t":"Christmas Gifts Sorting","s":"christmas-gifts-sorting","img":"https://img.gamemonetize.com/wa3rcnp9vqfd404dewoum4kc9iagaxvo/512x384.jpg","c":5,"p":0,"r":0.0,"f":false},{"id":2154,"t":"Muscle Clicker: Gym game","s":"muscle-clicker-gym-game","img":"https://img.gamemonetize.com/t2d34yzcod0b3o4kqayfnia4cce3gjf2/512x384.jpg","c":8,"p":0,"r":0.0,"f":false},{"id":2155,"t":"Santa Claus Meet Grimace","s":"santa-claus-meet-grimace","img":"https://img.gamemonetize.com/su2iqflb6lokg2xx96wh3fdu3oc6beyg/512x384.jpg","c":5,"p":0,"r":0.0,"f":false},{"id":2156,"t":"Awesome Tanks2","s":"awesome-tanks2","img":"https://img.gamemonetize.com/bjy8mnr90x3tc8wu8b8ogy0fzyc2uvyp/512x384.jpg","c":5,"p":0,"r":0.0,"f":false},{"id":2157,"t":"Draw That Line","s":"draw-that-line","img":"https://img.gamemonetize.com/hob2dl7k687hel7glzvnqr67659dvief/512x384.jpg","c":5,"p":0,"r":0.0,"f":false},{"id":2158,"t":"Egg Challenge","s":"egg-challenge","img":"https://img.gamemonetize.com/o3393ixcsvl1ako9w4zpg7qnk2isq3ki/512x384.jpg","c":7,"p":0,"r":0.0,"f":false},{"id":2159,"t":"Stickman Merge Battle: Arena","s":"stickman-merge-battle-arena","img":"https://img.gamemonetize.com/obyhafhugknxn37yy4vsed6yknb9d6rl/512x384.jpg","c":7,"p":0,"r":0.0,"f":false},{"id":2160,"t":"Christmas Puzzle","s":"christmas-puzzle","img":"https://img.gamemonetize.com/7add4gdt4dw5wxe9lfsui5zvop1eluks/512x384.jpg","c":5,"p":0,"r":0.0,"f":false},{"id":2161,"t":"Crazy Extreme Truck Parking Simulation 3d","s":"crazy-extreme-truck-parking-simulation-3d","img":"https://img.gamemonetize.com/pasaxog8swaef17hvn4gchz552pawuwv/512x384.jpg","c":5,"p":0,"r":0.0,"f":false},{"id":2162,"t":"Santa Ice Jump","s":"santa-ice-jump","img":"https://img.gamemonetize.com/26j043x0hrjq19mxjq3kshj1n27gdox8/512x384.jpg","c":5,"p":0,"r":0.0,"f":false},{"id":2163,"t":"SlopeGame","s":"slopegame","img":"https://img.gamemonetize.com/2tscjd5hjy09sm7owo0saawmk6lbo3i3/512x384.jpg","c":5,"p":0,"r":0.0,"f":false},{"id":2164,"t":"Raccoon Retail","s":"raccoon-retail","img":"https://img.gamemonetize.com/uarwfpfzlcz414mq41kf3g82b5mpwxy1/512x384.jpg","c":1,"p":0,"r":0.0,"f":false},{"id":2165,"t":"Merge Muscle Tycoon","s":"merge-muscle-tycoon","img":"https://img.gamemonetize.com/wrn8er5k3jrmyo310joxsem9ilk6f6oo/512x384.jpg","c":1,"p":0,"r":0.0,"f":false},{"id":2166,"t":"MagicTower","s":"magictower","img":"https://img.gamemonetize.com/86s69hjykukvfzw769mjgg2da7uurpfl/512x384.jpg","c":1,"p":0,"r":0.0,"f":false},{"id":2167,"t":"Monster Duelist","s":"monster-duelist","img":"https://img.gamemonetize.com/rhifs2sxfqdfhjhczhecfb995cmmsc79/512x384.jpg","c":1,"p":0,"r":0.0,"f":false},{"id":2168,"t":"Duel of Builders","s":"duel-of-builders","img":"https://img.gamemonetize.com/hhqdm1lz6isab49dpaaaecxxkr465hs0/512x384.jpg","c":1,"p":0,"r":0.0,"f":false},{"id":2169,"t":"Car Rush Fast Game","s":"car-rush-fast-game","img":"https://img.gamemonetize.com/o3qz5blqw700khul2j2d6vm2d1nlhb3u/512x384.jpg","c":1,"p":0,"r":0.0,"f":false},{"id":2170,"t":"Floor Jumper Escape","s":"floor-jumper-escape","img":"https://img.gamemonetize.com/c01vq6i15woncpz2hku744930e70mdhk/512x384.jpg","c":1,"p":0,"r":0.0,"f":false},{"id":2171,"t":"Kids Alphabet","s":"kids-alphabet","img":"https://img.gamemonetize.com/zpmt9jn5art13av0mqzrlm0bd5eguogw/512x384.jpg","c":1,"p":0,"r":0.0,"f":false},{"id":2172,"t":"Remove Balls","s":"remove-balls","img":"https://img.gamemonetize.com/n179v92qghrd83x8ngnv10m0rtppcbvr/512x384.jpg","c":5,"p":0,"r":0.0,"f":false},{"id":2173,"t":"SpaceScape","s":"spacescape","img":"https://img.gamemonetize.com/ahwi8eb47d17xywemfazorenjii97j4e/512x384.jpg","c":5,"p":0,"r":0.0,"f":false},{"id":2174,"t":"Xmas Float Connect","s":"xmas-float-connect","img":"https://img.gamemonetize.com/3ty581lmcmu8ux1pl6rcfatjetapa8e4/512x384.jpg","c":5,"p":0,"r":0.0,"f":false},{"id":2175,"t":"Mutant Love Pins","s":"mutant-love-pins","img":"https://img.gamemonetize.com/p97msfl7a9jc9g9rwhgvbglh27a25lba/512x384.jpg","c":5,"p":0,"r":0.0,"f":false},{"id":2176,"t":"Garten of Banban 3D","s":"garten-of-banban-3d","img":"https://img.gamemonetize.com/qeb3iqappi8n66qcciu2fpnxxy3t3g32/512x384.jpg","c":5,"p":0,"r":0.0,"f":false},{"id":2177,"t":"Surprise Makeup Doll Unbox","s":"surprise-makeup-doll-unbox","img":"https://img.gamemonetize.com/e0m8pxfgguakdm25rx286jdyyuc4qpes/512x384.jpg","c":5,"p":0,"r":0.0,"f":false},{"id":2178,"t":"Crazy Bubble Breaker","s":"crazy-bubble-breaker","img":"https://img.gamemonetize.com/v31o8je906oivptxuqdki7tef4nhoqdj/512x384.jpg","c":5,"p":0,"r":0.0,"f":false},{"id":2179,"t":"Vehicle Parking Master 3D","s":"vehicle-parking-master-3d","img":"https://img.gamemonetize.com/9ghoak7lplirayqfumn9wj9eaj6rr3qk/512x384.jpg","c":5,"p":0,"r":0.0,"f":false},{"id":2180,"t":"Mr And Mrs Santa Christmas Adventure","s":"mr-and-mrs-santa-christmas-adventure","img":"https://img.gamemonetize.com/f6wi4i31gqgtscci6v7k8dcr4vnjv78q/512x384.jpg","c":5,"p":0,"r":0.0,"f":false},{"id":2181,"t":"DIY Grimace Shake","s":"diy-grimace-shake","img":"https://img.gamemonetize.com/4b03bc52g119a2g6j4x6kcsrmtqmdmo3/512x384.jpg","c":5,"p":0,"r":0.0,"f":false},{"id":2182,"t":"Pirate Block Craft Monster Shooter","s":"pirate-block-craft-monster-shooter","img":"https://img.gamemonetize.com/lhmi1jgygea8lv7arg44d30z2hnrel7p/512x384.jpg","c":3,"p":0,"r":0.0,"f":false},{"id":2183,"t":"Watermelon Fruit Merge","s":"watermelon-fruit-merge","img":"https://img.gamemonetize.com/4lyq1vdatcf88ms5eus7xdkp5pultb04/512x384.jpg","c":3,"p":0,"r":0.0,"f":false},{"id":2184,"t":"Christmas Block Challenge","s":"christmas-block-challenge","img":"https://img.gamemonetize.com/sgx650qk7j0vs8jxcw6wu9ucgyy7b8dh/512x384.jpg","c":5,"p":0,"r":0.0,"f":false},{"id":2185,"t":"Sword Run 3D","s":"sword-run-3d","img":"https://img.gamemonetize.com/8rdz9xsqriwu77kgvyjaiww1bf2e1m0i/512x384.jpg","c":4,"p":0,"r":0.0,"f":false},{"id":2186,"t":"Excavator Simulator 3D","s":"excavator-simulator-3d","img":"https://img.gamemonetize.com/7wov98mycit3fq1iqlxn1dxs020z4qnz/512x384.jpg","c":4,"p":0,"r":0.0,"f":false},{"id":2187,"t":"Musical Ball Jump","s":"musical-ball-jump","img":"https://img.gamemonetize.com/zqmtqyc7sryczxf8qgruwccepnq38ouw/512x384.jpg","c":4,"p":0,"r":0.0,"f":false},{"id":2188,"t":"Family Camping Trip","s":"family-camping-trip","img":"https://img.gamemonetize.com/34ken32mucs5o4xdg1d4jpi3ti6p2bv9/512x384.jpg","c":4,"p":0,"r":0.0,"f":false},{"id":2189,"t":"2048 2048","s":"2048-2048","img":"https://img.gamemonetize.com/3xh4d3pe4xoweplx0e5p63vp2t8ic7i5/512x384.jpg","c":4,"p":0,"r":0.0,"f":false},{"id":2190,"t":"Super Fighting Player","s":"super-fighting-player","img":"https://img.gamemonetize.com/bwstg0w9nyiwxg28uwqkbif74k3jd02b/512x384.jpg","c":7,"p":0,"r":0.0,"f":false},{"id":2191,"t":"Merge Plants and Zombies","s":"merge-plants-and-zombies","img":"https://img.gamemonetize.com/w2uepocvjteetpkcnmptuhf7fgi1h9z7/512x384.jpg","c":4,"p":0,"r":0.0,"f":false},{"id":2192,"t":"My Pets Shop","s":"my-pets-shop","img":"https://img.gamemonetize.com/mvlzpmz4k7onh6bw238n9t0wbcbe2wvt/512x384.jpg","c":4,"p":0,"r":0.0,"f":false},{"id":2193,"t":"Skibidi Elastic Head","s":"skibidi-elastic-head","img":"https://img.gamemonetize.com/mzhcqhok1b5whltst1sscbgd85ewzn2q/512x384.jpg","c":4,"p":0,"r":0.0,"f":false},{"id":2194,"t":"Real JCB Excavator Simulator","s":"real-jcb-excavator-simulator","img":"https://img.gamemonetize.com/lrhrhwj6zkb8o1drgkszffgv1z8k94ra/512x384.jpg","c":4,"p":0,"r":0.0,"f":false},{"id":2195,"t":"Dead City Zombie Invasion 2023","s":"dead-city-zombie-invasion-2023","img":"https://img.gamemonetize.com/jxdno88jafvyr9vfma8p4g8gxr8zb4tn/512x384.jpg","c":3,"p":0,"r":0.0,"f":false},{"id":2196,"t":"Skibidi Hit Master","s":"skibidi-hit-master","img":"https://img.gamemonetize.com/5v5di5766lz4kax3unxtr0qqaylr4me9/512x384.jpg","c":3,"p":0,"r":0.0,"f":false},{"id":2197,"t":"Fruit Survivor","s":"fruit-survivor","img":"https://img.gamemonetize.com/8wa28ov2va942vruzbs1nhsb677t9xek/512x384.jpg","c":1,"p":0,"r":0.0,"f":false},{"id":2198,"t":"GT Car Stunts Legends","s":"gt-car-stunts-legends","img":"https://img.gamemonetize.com/afach7283ov5gvxv5eugcrsev4omg8fq/512x384.jpg","c":2,"p":0,"r":0.0,"f":false},{"id":2199,"t":"Car Stunt Raching","s":"car-stunt-raching","img":"https://img.gamemonetize.com/m7do60m9yl1bdnv88bn57rlmec5kh1ni/512x384.jpg","c":2,"p":0,"r":0.0,"f":false}]