[{"id":16701,"t":"Break The Snowman Xmas","s":"break-the-snowman-xmas","img":"https://img.gamemonetize.com/a0luz1ov5klxhoa1j9og5fv5imkixn57/512x384.jpg","c":4,"p":0,"r":0.0,"f":false},{"id":16702,"t":"Unblock That","s":"unblock-that","img":"https://img.gamemonetize.com/ddj3po8z23tfxxfqi2z447ngx1jk41ai/512x384.jpg","c":4,"p":0,"r":0.0,"f":false},{"id":16703,"t":"Pen Art","s":"pen-art","img":"https://img.gamemonetize.com/pt0l5nzr6vvafzr7rj5wgaevvh2oebq3/512x384.jpg","c":4,"p":0,"r":0.0,"f":false},{"id":16704,"t":"Mahjong Flowers","s":"mahjong-flowers","img":"https://img.gamemonetize.com/o2kdjmcc4q3fzrcjka8665qw6fq4olkc/512x384.jpg","c":4,"p":0,"r":0.0,"f":false},{"id":16705,"t":"Jewel Pop","s":"jewel-pop","img":"https://img.gamemonetize.com/67u3mkrfs6fd5c3mjg2htccbzkkirltx/512x384.jpg","c":4,"p":0,"r":0.0,"f":false},{"id":16706,"t":"Jewel Magic Xmas","s":"jewel-magic-xmas","img":"https://img.gamemonetize.com/qab5o8hs56u4uytktnjzs991p42opqog/512x384.jpg","c":4,"p":0,"r":0.0,"f":false},{"id":16707,"t":"Bowling Hit 3D","s":"bowling-hit-3d","img":"https://img.gamemonetize.com/8gyhq5ekdr4lx5diowxvl4wb1lubpamy/512x384.jpg","c":4,"p":0,"r":0.0,"f":false},{"id":16708,"t":"Witch to Princess Makeover","s":"witch-to-princess-makeover","img":"https://img.gamemonetize.com/qeq1wwsv32l8gagr7rmgs6njkfxdrq2h/512x384.jpg","c":4,"p":0,"r":0.0,"f":false},{"id":16709,"t":"Hole Run","s":"hole-run","img":"https://img.gamemonetize.com/c7j2n6z1p9pi4f88yk23849sdf8r0fhd/512x384.jpg","c":4,"p":0,"r":0.0,"f":false},{"id":16710,"t":"Ball Adventure","s":"ball-adventure","img":"https://img.gamemonetize.com/euuizjrtxrzwpfj79hry7iyafodlm931/512x384.jpg","c":4,"p":0,"r":0.0,"f":false},{"id":16711,"t":"Knife Smash","s":"knife-smash","img":"https://img.gamemonetize.com/3cpadfbj1qzazaoqgb1d0a03i5mdexri/512x384.jpg","c":3,"p":0,"r":0.0,"f":false},{"id":16712,"t":"Ludo Legend","s":"ludo-legend","img":"https://img.gamemonetize.com/jubi7s8v0430vl7hkxhtqsyqnlaa7loq/512x384.jpg","c":3,"p":0,"r":0.0,"f":false},{"id":16713,"t":"Drag Racing Club","s":"drag-racing-club","img":"https://img.gamemonetize.com/bxtkxihg5nyvyvd1840yd67ko0g84ojg/512x384.jpg","c":2,"p":0,"r":0.0,"f":false},{"id":16714,"t":"Line Color 3D","s":"line-color-3d","img":"https://img.gamemonetize.com/eehn9vpi76cx2z12rweps8270t1t3i9h/512x384.jpg","c":4,"p":0,"r":0.0,"f":false},{"id":16715,"t":"Train Taxi","s":"train-taxi","img":"https://img.gamemonetize.com/r6ozr2cc8zsis1lzyarlf54rv9lcncye/512x384.jpg","c":4,"p":0,"r":0.0,"f":false},{"id":16716,"t":"City Metro Bus Simulator","s":"city-metro-bus-simulator","img":"https://img.gamemonetize.com/qz5wes51mnvpjm5x83fbdcnw866zm3rc/512x384.jpg","c":2,"p":0,"r":0.0,"f":false},{"id":16717,"t":"Rings Fall","s":"rings-fall","img":"https://img.gamemonetize.com/6r6en2r2e549cr8g0mozm0ztj9s76ulc/512x384.jpg","c":2,"p":0,"r":0.0,"f":false},{"id":16718,"t":"Panda Commander Air Combat","s":"panda-commander-air-combat","img":"https://img.gamemonetize.com/teqj2rn3a0f4vf2u51tqabgp2qfbrz7k/512x384.jpg","c":4,"p":0,"r":0.0,"f":false},{"id":16719,"t":"Winter Clash 3D","s":"winter-clash-3d","img":"https://img.gamemonetize.com/ya6quof6a1n40xzz3thz9xekh349abp8/512x384.jpg","c":3,"p":0,"r":0.0,"f":false},{"id":16720,"t":"Gravity Control","s":"gravity-control","img":"https://img.gamemonetize.com/qjgxyoeahnkrbb0rfj0udwwd2imqis38/512x384.jpg","c":4,"p":0,"r":0.0,"f":false},{"id":16721,"t":"Grate Cut Slice","s":"grate-cut-slice","img":"https://img.gamemonetize.com/5d8l9y6xsbi5a81q67dx8vcnj8ewwpk2/512x384.jpg","c":4,"p":0,"r":0.0,"f":false},{"id":16722,"t":"Super Flight Hero","s":"super-flight-hero","img":"https://img.gamemonetize.com/d08323oqpmy96g8t8446088edj71pee3/512x384.jpg","c":4,"p":0,"r":0.0,"f":false},{"id":16723,"t":"Tennis Championship","s":"tennis-championship","img":"https://img.gamemonetize.com/kf4yksc266yafcdl02xoxwiq71gf6fbr/512x384.jpg","c":8,"p":0,"r":0.0,"f":false},{"id":16724,"t":"Farm Heroes Saga","s":"farm-heroes-saga","img":"https://img.gamemonetize.com/2x9ow1a1omne0pm0n7153987rud7ut8w/512x384.jpg","c":8,"p":0,"r":0.0,"f":false},{"id":16725,"t":"Kawaii High School Teacher Dress Up","s":"kawaii-high-school-teacher-dress-up","img":"https://img.gamemonetize.com/17a6uq0nnqijo58u2cl099hvs8gkuckv/512x384.jpg","c":8,"p":0,"r":0.0,"f":false},{"id":16726,"t":"Galactic Car Stunts","s":"galactic-car-stunts","img":"https://img.gamemonetize.com/gylgd0ter5t4hmlzzicwoscvbimfuz3a/512x384.jpg","c":2,"p":0,"r":0.0,"f":false},{"id":16727,"t":"Car Traffic Sim","s":"car-traffic-sim","img":"https://img.gamemonetize.com/su206jbvo10ines32pg2bv1zrco0594y/512x384.jpg","c":2,"p":0,"r":0.0,"f":false},{"id":16728,"t":"Basketball Master","s":"basketball-master","img":"https://img.gamemonetize.com/zzyslce7s2i01wotz4rrtls0j1gz9np9/512x384.jpg","c":8,"p":0,"r":0.0,"f":false},{"id":16729,"t":"Zombie Massacre","s":"zombie-massacre","img":"https://img.gamemonetize.com/td0f69t6s6x6opcenflbd1iqi87zqerk/512x384.jpg","c":3,"p":0,"r":0.0,"f":false},{"id":16730,"t":"Warfare Area","s":"warfare-area","img":"https://img.gamemonetize.com/3fnk3e4rstcjsqolnpx158fe8ptp74eb/512x384.jpg","c":3,"p":0,"r":0.0,"f":false},{"id":16731,"t":"Super Drift 3D","s":"super-drift-3d","img":"https://img.gamemonetize.com/7cw38ely978i4wa5n6vto8ixhqb0detk/512x384.jpg","c":2,"p":0,"r":0.0,"f":false},{"id":16732,"t":"Solitaire Legend","s":"solitaire-legend","img":"https://img.gamemonetize.com/2izh2qx25m39748dyh661dursymeh1ij/512x384.jpg","c":2,"p":0,"r":0.0,"f":false},{"id":16733,"t":"Jewel Blocks","s":"jewel-blocks","img":"https://img.gamemonetize.com/6h80yq62uiqar6jst96wgjdb2bv6khjr/512x384.jpg","c":2,"p":0,"r":0.0,"f":false},{"id":16734,"t":"Get Ready For Halloween","s":"get-ready-for-halloween","img":"https://img.gamemonetize.com/pj5rozn19e0zszozkbbc89wqhy9epusf/512x384.jpg","c":2,"p":0,"r":0.0,"f":false},{"id":16735,"t":"Assault Fury","s":"assault-fury","img":"https://img.gamemonetize.com/4genqjou76k2edgbmqvj9692cat382kd/512x384.jpg","c":3,"p":0,"r":0.0,"f":false},{"id":16736,"t":"Monster Truck Rally","s":"monster-truck-rally","img":"https://img.gamemonetize.com/hphlgf6n4b8u62u28grxlmt8fscrhmay/512x384.jpg","c":2,"p":0,"r":0.0,"f":false},{"id":16737,"t":"City Bus Driver","s":"city-bus-driver","img":"https://img.gamemonetize.com/afw50rmkfj0v5061jcfdf7z05eca4wxe/512x384.jpg","c":2,"p":0,"r":0.0,"f":false},{"id":16738,"t":"Car Stunt Driver","s":"car-stunt-driver","img":"https://img.gamemonetize.com/6stwp4ao05o39lbea0e39wqd9zlrkv1q/512x384.jpg","c":2,"p":0,"r":0.0,"f":false},{"id":16739,"t":"Merge Hit Weapons","s":"merge-hit-weapons","img":"https://img.gamemonetize.com/s3iyol9izo3f8kyglpnrl2u49vsfttql/512x384.jpg","c":2,"p":0,"r":0.0,"f":false},{"id":16740,"t":"Surfer Bus","s":"surfer-bus","img":"https://img.gamemonetize.com/4oyt28u6jluujageun20s197kgluh2um/512x384.jpg","c":2,"p":0,"r":0.0,"f":false},{"id":16741,"t":"Ludo Online","s":"ludo-online","img":"https://img.gamemonetize.com/8qdk9clkiv3bzcmbgkh0ehtxwpgzjhjr/512x384.jpg","c":7,"p":0,"r":0.0,"f":false},{"id":16742,"t":"Gangster City Crime","s":"gangster-city-crime","img":"https://img.gamemonetize.com/t318hsbrsh6dxkxwzco6j1f291r1z8gt/512x384.jpg","c":7,"p":0,"r":0.0,"f":false},{"id":16743,"t":"Indian Cargo Driver","s":"indian-cargo-driver","img":"https://img.gamemonetize.com/1jyilfgsoko0ab6ywq8eo2ico205znf1/512x384.jpg","c":2,"p":0,"r":0.0,"f":false},{"id":16744,"t":"Bull Racing","s":"bull-racing","img":"https://img.gamemonetize.com/qn42kht2x03of1pf8bo38cpaev6etpxj/512x384.jpg","c":2,"p":0,"r":0.0,"f":false},{"id":16745,"t":"Sugar Match","s":"sugar-match","img":"https://img.gamemonetize.com/0eks867gszt9mozqw60vnaje9jdnb68c/512x384.jpg","c":2,"p":0,"r":0.0,"f":false},{"id":16746,"t":"Christmas Monster Truck","s":"christmas-monster-truck","img":"https://img.gamemonetize.com/qxbvxf7z1d8cytxn4etq8fj6ru98psmg/512x384.jpg","c":2,"p":0,"r":0.0,"f":false},{"id":16747,"t":"Chained Tractor Towing Train","s":"chained-tractor-towing-train","img":"https://img.gamemonetize.com/yv2hbmzw22as2ic7xfvfnhw2m908isuh/512x384.jpg","c":2,"p":0,"r":0.0,"f":false},{"id":16748,"t":"Darts Pro Multiplayer","s":"darts-pro-multiplayer","img":"https://img.gamemonetize.com/v75bhmn4rk5wbsovgrvbjzfzx1bqpclk/512x384.jpg","c":7,"p":0,"r":0.0,"f":false},{"id":16749,"t":"Checkers Legend","s":"checkers-legend","img":"https://img.gamemonetize.com/78izsars8sldmlgna8zeor2fxspu07x8/512x384.jpg","c":7,"p":0,"r":0.0,"f":false},{"id":16750,"t":"Mahjong Master 2","s":"mahjong-master-2","img":"https://img.gamemonetize.com/7wjgkt6tp78mkrvri6qe4rrsboxee72m/512x384.jpg","c":7,"p":0,"r":0.0,"f":false},{"id":16751,"t":"PLANE GO!","s":"plane-go","img":"https://img.gamemonetize.com/ibqdzu3r2aoptvnzn3xnkqojf4iuqsl9/512x384.jpg","c":4,"p":0,"r":0.0,"f":false},{"id":16752,"t":"Gravity Snowman Christmas","s":"gravity-snowman-christmas","img":"https://img.gamemonetize.com/i27j4xccuciyh6unzxk6m8npjm6qryp9/512x384.jpg","c":4,"p":0,"r":0.0,"f":false},{"id":16753,"t":"Connect The Christmas","s":"connect-the-christmas","img":"https://img.gamemonetize.com/rzxjcund9jj4xjvwwptr00crtaa0bwp2/512x384.jpg","c":4,"p":0,"r":0.0,"f":false},{"id":16754,"t":"Santa Claus Jump","s":"santa-claus-jump","img":"https://img.gamemonetize.com/nfsim3mjcxy54t0ngarrvn2vnxdjh384/512x384.jpg","c":4,"p":0,"r":0.0,"f":false},{"id":16755,"t":"Juice Maker","s":"juice-maker","img":"https://img.gamemonetize.com/xs5zr7xcjy0h97ofg67nif2gszsdu89s/512x384.jpg","c":4,"p":0,"r":0.0,"f":false},{"id":16756,"t":"Domino","s":"domino","img":"https://img.gamemonetize.com/jejbeoj5vgeqduwxf0ypzo4lby8bh4t0/512x384.jpg","c":4,"p":0,"r":0.0,"f":false},{"id":16757,"t":"Real Estate Sim","s":"real-estate-sim","img":"https://img.gamemonetize.com/v5umwqp6aa7u04itarijhuibb72iiyhd/512x384.jpg","c":4,"p":0,"r":0.0,"f":false},{"id":16758,"t":"Jewel And Crazy Birds","s":"jewel-and-crazy-birds","img":"https://img.gamemonetize.com/0k2br3yplxcbcohwwf2wiop3ckv4imvj/512x384.jpg","c":4,"p":0,"r":0.0,"f":false},{"id":16759,"t":"Pizza Cutter","s":"pizza-cutter","img":"https://img.gamemonetize.com/twg7f9i2pu09r362iu5n39nqibtfjzcc/512x384.jpg","c":4,"p":0,"r":0.0,"f":false},{"id":16760,"t":"Heart Box - physics puzzles game","s":"heart-box-physics-puzzles-game","img":"https://img.gamemonetize.com/m4qrp2locszmxh6vtcaibgi4phewv6yh/512x384.jpg","c":4,"p":0,"r":0.0,"f":false},{"id":16761,"t":"Adventures of Flig - air hockey shooter","s":"adventures-of-flig-air-hockey-shooter","img":"https://img.gamemonetize.com/u45zjrq1d00d39ic4p4eq2m6y0zo2i1w/512x384.jpg","c":4,"p":0,"r":0.0,"f":false},{"id":16762,"t":"Cut it Fair","s":"cut-it-fair","img":"https://img.gamemonetize.com/mxl7ch0aseiihwtgceqemfvmpyoaqhud/512x384.jpg","c":4,"p":0,"r":0.0,"f":false},{"id":16763,"t":"Subway Runner","s":"subway-runner","img":"https://img.gamemonetize.com/xfqaymtsmmb5di5z2k0sj8okbvhh31g1/512x384.jpg","c":4,"p":0,"r":0.0,"f":false},{"id":16764,"t":"Roll This Ball","s":"roll-this-ball","img":"https://img.gamemonetize.com/ga60e46mqmsgc2a4n8ec42u9aqnshs0y/512x384.jpg","c":4,"p":0,"r":0.0,"f":false},{"id":16765,"t":"Jewel Pets Match","s":"jewel-pets-match","img":"https://img.gamemonetize.com/20ntpuqciwjuzsijq6zmke0pz8v037w5/512x384.jpg","c":4,"p":0,"r":0.0,"f":false},{"id":16766,"t":"Mahjong Mania!","s":"mahjong-mania","img":"https://img.gamemonetize.com/0ea8nd6q0sakjc8fh9q036yf22xch4xi/512x384.jpg","c":4,"p":0,"r":0.0,"f":false},{"id":16767,"t":"Bouncy Musical Ball","s":"bouncy-musical-ball","img":"https://img.gamemonetize.com/3o3t995jp39lqusdheoq6z9the6wpzvt/512x384.jpg","c":4,"p":0,"r":0.0,"f":false},{"id":16768,"t":"Murder The Homicidal Liu - Into Damnation","s":"murder-the-homicidal-liu-into-damnation","img":"https://img.gamemonetize.com/ljclklz8lf0h21wmbrct8xrdnjxhtegf/512x384.jpg","c":3,"p":0,"r":0.0,"f":false},{"id":16769,"t":"Finger Soccer HD","s":"finger-soccer-hd","img":"https://img.gamemonetize.com/86kbn5nq7jhzzkkxp1camtsg78gkvqy4/512x384.jpg","c":3,"p":0,"r":0.0,"f":false},{"id":16770,"t":"Fishing Sim","s":"fishing-sim","img":"https://img.gamemonetize.com/ermkhnoto46oor8cng3zbo3losk43osh/512x384.jpg","c":3,"p":0,"r":0.0,"f":false},{"id":16771,"t":"Balls Rotate","s":"balls-rotate","img":"https://img.gamemonetize.com/5dojngoowdie0lhx3yxx49h0ktg1pxpv/512x384.jpg","c":3,"p":0,"r":0.0,"f":false},{"id":16772,"t":"Wild Wolves","s":"wild-wolves","img":"https://img.gamemonetize.com/3wkyhqybeoa8t6lit1desrgdjn1gwexz/512x384.jpg","c":3,"p":0,"r":0.0,"f":false},{"id":16773,"t":"MUSIC LINE 2 CHRISTMAS","s":"music-line-2-christmas","img":"https://img.gamemonetize.com/vdkk80ahb95lnasx53bj2siy8u43vllq/512x384.jpg","c":4,"p":0,"r":0.0,"f":false},{"id":16774,"t":"Train Travels","s":"train-travels","img":"https://img.gamemonetize.com/ly4mldex0wqejztovtthg8a5i1kttkue/512x384.jpg","c":4,"p":0,"r":0.0,"f":false},{"id":16775,"t":"Horse Rider","s":"horse-rider","img":"https://img.gamemonetize.com/d0nm3wfycn3qtbmpjhe150w0r64l10hf/512x384.jpg","c":2,"p":0,"r":0.0,"f":false},{"id":16776,"t":"Taxi Simulator","s":"taxi-simulator","img":"https://img.gamemonetize.com/llon0jnm4c5dd8daux4jca8boqs93j3o/512x384.jpg","c":2,"p":0,"r":0.0,"f":false},{"id":16777,"t":"Mister Shooter","s":"mister-shooter","img":"https://img.gamemonetize.com/utk5d1ocpjv1i7dqb1e1um12vzx8y32t/512x384.jpg","c":3,"p":0,"r":0.0,"f":false},{"id":16778,"t":"Ultimate Car Tracks","s":"ultimate-car-tracks","img":"https://img.gamemonetize.com/6cvn1124ixd64bo994f2wn2eqnnv2qp9/512x384.jpg","c":2,"p":0,"r":0.0,"f":false},{"id":16779,"t":"Zombie Derby","s":"zombie-derby","img":"https://img.gamemonetize.com/2vs14l9pnwvmjcfjetrai72uld2235u6/512x384.jpg","c":2,"p":0,"r":0.0,"f":false},{"id":16780,"t":"European Football","s":"european-football","img":"https://img.gamemonetize.com/avbwl97t4aupzxi433vl0i7ivx9jhofr/512x384.jpg","c":2,"p":0,"r":0.0,"f":false},{"id":16781,"t":"Sweet Candy Mania","s":"sweet-candy-mania","img":"https://img.gamemonetize.com/yffsgao8y28tlwvlmh37ld053j7kt2mr/512x384.jpg","c":2,"p":0,"r":0.0,"f":false},{"id":16782,"t":"Pirate Bomber - Jewel Hunter","s":"pirate-bomber-jewel-hunter","img":"https://img.gamemonetize.com/qdf4j4iww1j30m7vqrjfp5biecievbxl/512x384.jpg","c":2,"p":0,"r":0.0,"f":false},{"id":16783,"t":"Superhero Tower","s":"superhero-tower","img":"https://img.gamemonetize.com/b7764pvzaofcjckp8mfszc9338hq7qlj/512x384.jpg","c":2,"p":0,"r":0.0,"f":false},{"id":16784,"t":"Cake Master 3D","s":"cake-master-3d","img":"https://img.gamemonetize.com/dl9ijps610qgjvgm21l5uemdy97fds2r/512x384.jpg","c":2,"p":0,"r":0.0,"f":false},{"id":16785,"t":"Fullscreen Mario","s":"fullscreen-mario","img":"https://img.gamemonetize.com/w75fparbaawjjml77vzq46cnifmj38kz/512x384.jpg","c":4,"p":0,"r":0.0,"f":false},{"id":16786,"t":"Extreme Bike Rider","s":"extreme-bike-rider","img":"https://img.gamemonetize.com/mim63hfu0s829wzqjktpf6o53adou70g/512x384.jpg","c":2,"p":0,"r":0.0,"f":false},{"id":16787,"t":"Fun Run Race 2 : Multiplayer","s":"fun-run-race-2-multiplayer","img":"https://img.gamemonetize.com/p3hmuse2872voxmmw3lsd8g23hz0j078/512x384.jpg","c":2,"p":0,"r":0.0,"f":false},{"id":16788,"t":"Super Onion Boy","s":"super-onion-boy","img":"https://img.gamemonetize.com/jtnau6xam3feocnkwi3xn5i4qc0l1kpk/512x384.jpg","c":4,"p":0,"r":0.0,"f":false},{"id":16789,"t":"maya","s":"maya","img":"https://img.gamemonetize.com/2l9vbobcqs99g85dqrymy5oehlf4dwvg/512x384.jpg","c":4,"p":0,"r":0.0,"f":false},{"id":16790,"t":"Offroad Mania","s":"offroad-mania","img":"https://img.gamemonetize.com/817p7wyrnobq1pt7zuq7sbxkygcb2f5b/512x384.jpg","c":2,"p":0,"r":0.0,"f":false},{"id":16791,"t":"Supra Drift 3D","s":"supra-drift-3d","img":"https://img.gamemonetize.com/snoo7xzfsr69fyrqj7xpbsg3mcyx0obs/512x384.jpg","c":2,"p":0,"r":0.0,"f":false},{"id":16792,"t":"Chop  amp;amp; Mine","s":"chop-mine","img":"https://img.gamemonetize.com/a9odqry1clp1ol7bvdfv9ibvvfwjvko6/512x384.jpg","c":2,"p":0,"r":0.0,"f":false},{"id":16793,"t":"Sand Balls","s":"sand-balls","img":"https://img.gamemonetize.com/xzhj8ujif2ymu0yf7x0h35z9t4wryiov/512x384.jpg","c":2,"p":0,"r":0.0,"f":false},{"id":16794,"t":"Merge 13","s":"merge-13","img":"https://img.gamemonetize.com/rgp8js0jwsdt8cmt13ojt3jvks7w7dvy/512x384.jpg","c":2,"p":0,"r":0.0,"f":false},{"id":16795,"t":"Sanicball Downhill","s":"sanicball-downhill","img":"https://img.gamemonetize.com/bjugz0ce7yzwccr6fbta1te7v9beq181/512x384.jpg","c":4,"p":0,"r":0.0,"f":false},{"id":16796,"t":"Magic World","s":"magic-world","img":"https://img.gamemonetize.com/9fjbfcbmwcdb9dgfimtzwbfd0nj5ww76/512x384.jpg","c":4,"p":0,"r":0.0,"f":false},{"id":16797,"t":"Bitcoin Clicker","s":"bitcoin-clicker","img":"https://img.gamemonetize.com/jf232ikv637oysftpsufwib245zmjf03/512x384.jpg","c":4,"p":0,"r":0.0,"f":false},{"id":16798,"t":"Knife Ninja","s":"knife-ninja","img":"https://img.gamemonetize.com/1tdgxk99fni5o4i6zw9p0p18u7dhxnmy/512x384.jpg","c":4,"p":0,"r":0.0,"f":false},{"id":16799,"t":"Military Wars Strike","s":"military-wars-strike","img":"https://img.gamemonetize.com/9hpj5t68i7oe3rfb4e8cb3bbzr1ntpw3/512x384.jpg","c":3,"p":0,"r":0.0,"f":false},{"id":16800,"t":"Jet Pack Kid","s":"jet-pack-kid","img":"https://img.gamemonetize.com/18ky89ytxu1a62lmv5my9wx9w9we7kn9/512x384.jpg","c":4,"p":0,"r":0.0,"f":false}]